Workbook
Name boxmaterials: [1]!Table1[Material de construcție]
Name PHPP_Daten_Komponentensortierung: [2]Data!$A$194:$A$195
Name PHPP_Flaechen_Liste_Bauteile: [2]Areas!$AN$40:$AN$139
Name PHPP_Komponenten_Liste_Bauteilaufbauten: [2]Components!$FZ$12:$FZ$412
Name PHPP_Komponenten_Liste_Fensterrahmen: [2]Components!$GH$12:$GH$412
Name PHPP_Komponenten_Liste_Verglasung: [2]Components!$GD$12:$GD$412
Name PHPP_Komponenten_Liste_Waermerueckgewinnungsgeraet: [2]Components!$GL$12:$GL$412

Sheet Intro
B2: Current calculation tool can serve a basis for elaboration of energy audit report in buildings.
B4: Tables with input data and calculations have to be attached as an annex to the energy audit report.
B6: Indications for use:
B8: Tables can be multiplied or modified depending on various situations, rows and columns can be deleted, added or combined.
D11: Cells which require input data or text
D13: Cells with automatic calculations or text
D15: Cells which are advised to remain unchanged, but not mandatory.
B17: The energy auditor is free to add graphs, or improve the tool in any way he considers relevant
B18: Energy consumption can be expressed in various units of measure, further all calculations to be done in kWh.
B20: Calculations related to water savings are not considered by the current tool, it can be developed further by the auditor in case if it will be required.
B23: The values and contents (formulas, links etc.) of the spreadsheet provided as a input data for energy audit report is in full responsability of the energy auditor.

Sheet Sheet1
A1: Республика, вилоят, жой | B1: Ойлик ўртача ҳарорат | N1: Ўртача йиллик ҳарорат | O1: Энг кичик мутлақ ҳарорат | P1: Энг катта мутлақ ҳарорат | Q1: Энг иссиқ ойдаги энг катта ўртача ҳарорат | R1: Энг совуқ ойдаги энг кичик ўртача ҳарорат
B2: I | C2: II | D2: III | E2: IV | F2: V | G2: VI | H2: VII | I2: VIII | J2: IX | K2: X | L2: XI | M2: XII
A3: 1 | B3: 2 | C3: 3 | D3: 4 | E3: 5 | F3: 6 | G3: 7 | H3: 8 | I3: 9 | J3: 10 | K3: 11 | L3: 12 | M3: 13 | N3: 14 | O3: 15 | P3: 16 | Q3: 17 | R3: 18
A4: Тошкент вилояти
A5: Тошкент | B5: 1,9 | C5: 3,9 | D5: 9,4 | E5: 15,5 | F5: 20,5 | G5: 25,8 | H5: 27,8 | I5: 26,2 | J5: 20,6 | K5: 13,8 | L5: 8,5 | M5: 3,5 | N5: 14,8 | O5: =-29.5/1930 -> -0.015284974 | P5: 44.6/1997 | Q5: 35,6 | R5: -1,5
A6: Янгийўл | B6: 0,4 | C6: 2,9 | D6: 9,0 | E6: 15,6 | F6: 21,1 | G6: 26,3 | H6: 27,8 | I6: 25,7 | J6: 20,2 | K6: 13,5 | L6: 7,3 | M6: 1,7 | N6: 14,3 | O6: =-32/1930 -> -0.016580311 | P6: 45.5/1998 | Q6: 36,2 | R6: -3,1
A7: Туябўғуз | B7: 1,1 | C7: 3,5 | D7: 9,3 | E7: 16,0 | F7: 21,2 | G7: 26,3 | H7: 27,8 | I7: 26,1 | J7: 21,1 | K7: 14,5 | L7: 8,3 | M7: 2,6 | N7: 14,8 | O7: =-27.1/1969 -> -0.013763332 | P7: 42.7/1983 | Q7: 35,2 | R7: -2,1
A8: Кўкорол | B8: -0,1 | C8: 2,5 | D8: 8,6 | E8: 15,3 | F8: 20,3 | G8: 24,7 | H8: 25,7 | I8: 23,6 | J8: 18,4 | K8: 12,4 | L8: 6,6 | M8: 1,2 | N8: 13,3 | O8: =-32.2/1969 -> -0.016353479 | P8: 46.1/1944 | Q8: 34,3 | R8: -3,8
A9: Далварзин | B9: 1,5 | C9: 4,1 | D9: 9,9 | E9: 16,5 | F9: 21,8 | G9: 26,7 | H9: 27,7 | I9: 25,4 | J9: 20,2 | K9: 14,1 | L9: 8,3 | M9: 2,9 | N9: 14,9 | O9: =-35/1930 -> -0.018134715 | P9: 43.5/2005 | Q9: 35,2 | R9: -2,2
A10: Бекобод | B10: 1,6 | C10: 3,8 | D10: 9,8 | E10: 16,4 | F10: 21,6 | G10: 26,4 | H10: 27,6 | I10: 25,5 | J10: 20,4 | K10: 14,2 | L10: 8,6 | M10: 3,0 | N10: 14,9 | O10: =-30.2/1930 -> -0.015647668 | P10: 43.8/1944 | Q10: 34,8 | R10: -0,9
A11: Олмалиқ | B11: 1,5 | C11: 3,7 | D11: 9,3 | E11: 15,8 | F11: 21,1 | G11: 26,6 | H11: 28,2 | I11: 26,4 | J11: 21,1 | K11: 14,6 | L11: 8,6 | M11: 3,2 | N11: 15,0 | O11: =-20.5/1979 -> -0.010358767 | P11: 43.5/1993 | Q11: 34,8 | R11: -2,2
A12: Ангрен | B12: 0,9 | C12: 2,3 | D12: 7,4 | E12: 13,6 | F12: 18,5 | G12: 23,7 | H12: 25,8 | I12: 24,5 | J12: 19,5 | K12: 12,8 | L12: 7,7 | M12: 2,9 | N12: 13,3 | O12: =-27/1935 -> -0.013953488 | P12: 42.6/1944 | Q12: 32,1 | R12: -2,7
A13: Бошқизилсой | B13: -0,4 | C13: 0,9 | D13: 5,4 | E13: 11,4 | F13: 15,9 | G13: 21,1 | H13: 23,6 | I13: 22,6 | J13: 17,5 | K13: 10,9 | L13: 6,1 | M13: 1,6 | N13: 11,4 | O13: =-29.7/1969 -> -0.015083799 | P13: 40.0/1984 | Q13: 30,0 | R13: -3,4
A14: Сўқоқ | B14: 0,1 | C14: 1,0 | D14: 5,1 | E14: 11,2 | F14: 15,7 | G14: 21,0 | H14: 23,2 | I14: 22,4 | J14: 17,6 | K14: 11,4 | L14: 6,6 | M14: 2,3 | N14: 11,5 | O14: =-25.4/1974 -> -0.012867275 | P14: 37.2/1983 | Q14: 28,6 | R14: -3,3
A15: Дукент | B15: -2,9 | C15: -2,4 | D15: 1,5 | E15: 7,5 | F15: 11,9 | G15: 17,0 | H15: 19,6 | I15: 19,2 | J15: 14,7 | K15: 8,3 | L15: 3,6 | M15: -0,6 | N15: 8,1 | O15: =-24.5/1969 -> -0.012442864 | P15: 35.2/1983,2008 | Q15: 25,4 | R15: -5,9
A16: Чимён | B16: -2,9 | C16: -2,1 | D16: 2,0 | E16: 8,4 | F16: 13,1 | G16: 18,3 | H16: 20,8 | I16: 20,4 | J16: 15,5 | K16: 9,0 | L16: 4,0 | M16: -0,6 | N16: 8,8 | O16: =-23/1941 -> -0.011849562 | P16: 35.2/2008 | Q16: 26,1 | R16: -6,0
A17: Пскем | B17: -2,9 | C17: -1,7 | D17: 3,2 | E17: 10,1 | F17: 14,3 | G17: 18,8 | H17: 21,8 | I17: 21,7 | J17: 16,8 | K17: 9,9 | L17: 4,5 | M17: -0,7 | N17: 9,7 | O17: =-26.9/1943 -> -0.01384457 | P17: 41.7/1983 | Q17: 29,8 | R17: -6,5
A18: Ойгаинг | B18: -9,8 | C18: -8,8 | D18: -4,3 | E18: 1,5 | F18: 7,7 | G18: 12,2 | H18: 14,9 | I18: 15,3 | J18: 10,6 | K18: 3,4 | L18: -2,9 | M18: -7,7 | N18: 2,7 | O18: =-31.6/1969 -> -0.016048756 | P18: 36.0/1976 | Q18: 23,2 | R18: -14,1

Sheet Building_data
B3: Description | C3: Unit | D3: Value
B4: Total net heated floor area | C4: [m²] | D4: =Envelope!L95 -> 2515.415
B5: Total net heated volume | C5: [m³] | D5: =Envelope!M95 -> 7546.245
B6: Total net cooled floor area (if any) | C6: [m²] | D6: 0
B7: Duration of the heating season (as per NCM M.01.02:2016, Annex A) | C7: [days] | D7: 163
B8: Average inside temperature during heating season in non-operation hours (standardized) | C8: [°C] | D8: 14
B9: Average inside temperature during heating season in operation hours (standardized) | C9: [°C] | D9: 22
B10: Medium outside temperature during heating season (as per NCM M.01.02:2016, Annex A) | C10: [°C] | D10: 3.9
B11: Coldest 5 days outside temperature (design temperature, as per СНиП 2.01.01-82) | C11: [°C] | D11: -14
B12: Operation hours during heating season | C12: [h/y] | D12: =D14*D7 -> 1630
B13: Non-operation hours during heating season | C13: [h/y] | D13: 14
B14: Operation hours per day | C14: [h/d] | D14: 10
B15: Average inside enthalpy during cooling period for +24°C and relative humidity of 50% | C15: [kJ/kg] | D15: 48.4
B16: Average outside enthalpy during cooling period | C16: [kJ/kg] | D16: 59.5
B17: Outside enthalpy during the hottest summer day | C17: [kJ/kg] | D17: 69.13
B18: Average number of people inside the building | C18: [No of people] | D18: =360+58 -> 418

Sheet Envelope
B4: Block | C4: Orientation | D4: Side of the building | E4: Element | F4: Walls | L4: Windows | U4: Doors
F5: Dimension | I5: Area | L5: Dimension | N5: Type | Q5: Area | T5: Perimeter of window sills [m] | U5: Dimension | W5: Type | Z5: Area | AC5: Perimeter of door sills [m]
F6: Lenght [m] | G6: Height of the wall in contact with environment [m] | H6: Height of the wall in contact with the ground [m] | I6: Brut area of the wall in contact with environment [m2] | J6: Area of the wall in contact with the ground [m2] | K6: Net area of the wall in contact with environment [m2] | L6: Lenght [m] | M6: Height [m] | N6: Win 1 [units] | O6: Win 2 [units] | P6: Win 3 [units] | Q6: Win 1 [m2] | R6: Win 2 [m2] | S6: Win 3 [m2] | U6: Lenght [m] | V6: Height [m] | W6: D 1 [units] | X6: D 2 [units] | Y6: D 3 [units] | Z6: D 1 [m2] | AA6: D 2 [m2] | AB6: D 3 [m2] | AD6: =SUM(AD7:AD73) -> 256.62
B7: 3-DMTT | C7: N | D7: P1 | E7: W1 | F7: 50.7 | G7: =3.3*2 -> 6.6 | I7: =F7*G7 -> 334.62 | J7: =F7*H7 -> 0 | K7: =I7-Q7-R7-S7-Z7-AA7-AB7 -> 277.82 | L7: 1.2 | M7: 1.8 | P7: 21 | Q7: =L7*M7*N7 -> 0 | R7: =L7*M7*O7 -> 0 | S7: =L7*M7*P7 -> 45.36 | T7: =((L7+M7)*2)*(N7+O7+P7) -> 126 | U7: 2.2 | V7: 2.6 | W7: 2 | Z7: =U7*V7*W7 -> 11.44 | AA7: =U7*V7*X7 -> 0 | AB7: =U7*V7*Y7 -> 0 | AC7: =((U7+V7)*2)*(W7+X7+Y7) -> 19.2 | AD7: =SUM(Q7:S7) -> 45.36 | AE7: S | AF7: =SUMIF($C$7:$C$73,AE7,$AD$7:$AD$73) -> 79.02
E8: Socle 1. (unheated space) | F8: 50.7 | G8: 0.55 | I8: =F8*G8 -> 27.885 | J8: =F8*H8 -> 0 | K8: =I8-Q8-R8-S8-Z8-AA8-AB8 -> 22.485 | L8: 1 | M8: 1.8 | P8: 1 | Q8: =L8*M8*N8 -> 0 | R8: =L8*M8*O8 -> 0 | S8: =L8*M8*P8 -> 1.8 | T8: =((L8+M8)*2)*(N8+O8+P8) -> 5.6 | U8: 0.9 | V8: 2 | W8: 2 | Z8: =U8*V8*W8 -> 3.6 | AA8: =U8*V8*X8 -> 0 | AB8: =U8*V8*Y8 -> 0 | AC8: =((U8+V8)*2)*(W8+X8+Y8) -> 11.6 | AD8: =SUM(Q8:S8) -> 1.8 | AE8: N | AF8: =SUMIF($C$7:$C$73,AE8,$AD$7:$AD$73) -> 86.4
I9: =F9*G9 -> 0 | J9: =F9*H9 -> 0 | K9: =I9-Q9-R9-S9-Z9-AA9-AB9 -> -2.56 | L9: 0.8 | M9: 0.8 | P9: 4 | Q9: =L9*M9*N9 -> 0 | R9: =L9*M9*O9 -> 0 | S9: =L9*M9*P9 -> 2.56 | T9: =((L9+M9)*2)*(N9+O9+P9) -> 12.8 | Z9: =U9*V9*W9 -> 0 | AA9: =U9*V9*X9 -> 0 | AB9: =U9*V9*Y9 -> 0 | AC9: =((U9+V9)*2)*(W9+X9+Y9) -> 0 | AD9: =SUM(Q9:S9) -> 2.56 | AE9: E | AF9: =SUMIF($C$7:$C$73,AE9,$AD$7:$AD$73) -> 10.8
C10: W | D10: P2 | E10: W1 | F10: 13.2 | G10: =3.3*2 -> 6.6 | I10: =F10*G10 -> 87.12 | J10: =F10*H10 -> 0 | K10: =I10-Q10-R10-S10-Z10-AA10-AB10 -> 75.24 | L10: 1.2 | M10: 1.8 | P10: 3 | Q10: =L10*M10*N10 -> 0 | R10: =L10*M10*O10 -> 0 | S10: =L10*M10*P10 -> 6.48 | T10: =((L10+M10)*2)*(N10+O10+P10) -> 18 | U10: 0.9 | V10: 2 | W10: 3 | Z10: =U10*V10*W10 -> 5.4 | AA10: =U10*V10*X10 -> 0 | AB10: =U10*V10*Y10 -> 0 | AC10: =((U10+V10)*2)*(W10+X10+Y10) -> 17.4 | AD10: =SUM(Q10:S10) -> 6.48 | AE10: W | AF10: =SUMIF($C$7:$C$73,AE10,$AD$7:$AD$73) -> 14.76
E11: Socle 1. (unheated space) | F11: 13.2 | G11: 0.55 | I11: =F11*G11 -> 7.26 | J11: =F11*H11 -> 0 | K11: =I11-Q11-R11-S11-Z11-AA11-AB11 -> 0.06 | L11: 1 | M11: 1.8 | P11: 4 | Q11: =L11*M11*N11 -> 0 | R11: =L11*M11*O11 -> 0 | S11: =L11*M11*P11 -> 7.2 | T11: =((L11+M11)*2)*(N11+O11+P11) -> 22.4 | Z11: =U11*V11*W11 -> 0 | AA11: =U11*V11*X11 -> 0 | AB11: =U11*V11*Y11 -> 0 | AC11: =((U11+V11)*2)*(W11+X11+Y11) -> 0 | AD11: =SUM(Q11:S11) -> 7.2 | AE11: SW | AF11: =SUMIF($C$7:$C$73,AE11,$AD$7:$AD$73) -> 0
C12: S | D12: P3 | E12: W1 | F12: 24.5 | G12: 6.6 | I12: =F12*G12 -> 161.7 | J12: =F12*H12 -> 0 | K12: =I12-Q12-R12-S12-Z12-AA12-AB12 -> 135.78 | L12: 1.2 | M12: 1.8 | P12: 12 | Q12: =L12*M12*N12 -> 0 | R12: =L12*M12*O12 -> 0 | S12: =L12*M12*P12 -> 25.92 | T12: =((L12+M12)*2)*(N12+O12+P12) -> 72 | Z12: =U12*V12*W12 -> 0 | AA12: =U12*V12*X12 -> 0 | AB12: =U12*V12*Y12 -> 0 | AC12: =((U12+V12)*2)*(W12+X12+Y12) -> 0 | AD12: =SUM(Q12:S12) -> 25.92 | AE12: SE | AF12: =SUMIF($C$7:$C$73,AE12,$AD$7:$AD$73) -> 0
E13: Socle 1. (unheated space) | F13: 24.5 | G13: 0.55 | I13: =F13*G13 -> 13.475 | J13: =F13*H13 -> 0 | K13: =I13-Q13-R13-S13-Z13-AA13-AB13 -> 12.195 | L13: 0.8 | M13: 0.8 | P13: 2 | Q13: =L13*M13*N13 -> 0 | R13: =L13*M13*O13 -> 0 | S13: =L13*M13*P13 -> 1.28 | T13: =((L13+M13)*2)*(N13+O13+P13) -> 6.4 | Z13: =U13*V13*W13 -> 0 | AA13: =U13*V13*X13 -> 0 | AB13: =U13*V13*Y13 -> 0 | AC13: =((U13+V13)*2)*(W13+X13+Y13) -> 0 | AD13: =SUM(Q13:S13) -> 1.28 | AE13: NE | AF13: =SUMIF($C$7:$C$73,AE13,$AD$7:$AD$73) -> 0
C14: W | D14: P4 | E14: W1 | F14: 13.25 | G14: 3.3 | I14: =F14*G14 -> 43.725 | J14: =F14*H14 -> 0 | K14: =I14-Q14-R14-S14-Z14-AA14-AB14 -> 40.125 | L14: 1 | M14: 1.8 | P14: 1 | Q14: =L14*M14*N14 -> 0 | R14: =L14*M14*O14 -> 0 | S14: =L14*M14*P14 -> 1.8 | T14: =((L14+M14)*2)*(N14+O14+P14) -> 5.6 | U14: 0.9 | V14: 2 | W14: 1 | Z14: =U14*V14*W14 -> 1.8 | AA14: =U14*V14*X14 -> 0 | AB14: =U14*V14*Y14 -> 0 | AC14: =((U14+V14)*2)*(W14+X14+Y14) -> 5.8 | AD14: =SUM(Q14:S14) -> 1.8 | AE14: NW | AF14: =SUMIF($C$7:$C$73,AE14,$AD$7:$AD$73) -> 0
E15: Socle 1. (unheated space) | F15: 13.25 | G15: 0.55 | I15: =F15*G15 -> 7.2875 | J15: =F15*H15 -> 0 | K15: =I15-Q15-R15-S15-Z15-AA15-AB15 -> 7.2875 | Q15: =L15*M15*N15 -> 0 | R15: =L15*M15*O15 -> 0 | S15: =L15*M15*P15 -> 0 | T15: =((L15+M15)*2)*(N15+O15+P15) -> 0 | Z15: =U15*V15*W15 -> 0 | AA15: =U15*V15*X15 -> 0 | AB15: =U15*V15*Y15 -> 0 | AC15: =((U15+V15)*2)*(W15+X15+Y15) -> 0 | AD15: =SUM(Q15:S15) -> 0
I16: =F16*G16 -> 0 | J16: =F16*H16 -> 0 | K16: =I16-Q16-R16-S16-Z16-AA16-AB16 -> 0 | Q16: =L16*M16*N16 -> 0 | R16: =L16*M16*O16 -> 0 | S16: =L16*M16*P16 -> 0 | T16: =((L16+M16)*2)*(N16+O16+P16) -> 0 | Z16: =U16*V16*W16 -> 0 | AA16: =U16*V16*X16 -> 0 | AB16: =U16*V16*Y16 -> 0 | AC16: =((U16+V16)*2)*(W16+X16+Y16) -> 0 | AD16: =SUM(Q16:S16) -> 0
I17: =F17*G17 -> 0 | J17: =F17*H17 -> 0 | K17: =I17-Q17-R17-S17-Z17-AA17-AB17 -> 0 | Q17: =L17*M17*N17 -> 0 | R17: =L17*M17*O17 -> 0 | S17: =L17*M17*P17 -> 0 | T17: =((L17+M17)*2)*(N17+O17+P17) -> 0 | Z17: =U17*V17*W17 -> 0 | AA17: =U17*V17*X17 -> 0 | AB17: =U17*V17*Y17 -> 0 | AC17: =((U17+V17)*2)*(W17+X17+Y17) -> 0 | AD17: =SUM(Q17:S17) -> 0
I18: =F18*G18 -> 0 | J18: =F18*H18 -> 0 | K18: =I18-Q18-R18-S18-Z18-AA18-AB18 -> 0 | Q18: =L18*M18*N18 -> 0 | R18: =L18*M18*O18 -> 0 | S18: =L18*M18*P18 -> 0 | T18: =((L18+M18)*2)*(N18+O18+P18) -> 0 | Z18: =U18*V18*W18 -> 0 | AA18: =U18*V18*X18 -> 0 | AB18: =U18*V18*Y18 -> 0 | AC18: =((U18+V18)*2)*(W18+X18+Y18) -> 0 | AD18: =SUM(Q18:S18) -> 0
C19: N | D19: P5 | E19: W1 | F19: 24.5 | G19: 6.6 | I19: =F19*G19 -> 161.7 | J19: =F19*H19 -> 0 | K19: =I19-Q19-R19-S19-Z19-AA19-AB19 -> 135.78 | L19: 1.2 | M19: 1.8 | P19: 12 | Q19: =L19*M19*N19 -> 0 | R19: =L19*M19*O19 -> 0 | S19: =L19*M19*P19 -> 25.92 | T19: =((L19+M19)*2)*(N19+O19+P19) -> 72 | Z19: =U19*V19*W19 -> 0 | AA19: =U19*V19*X19 -> 0 | AB19: =U19*V19*Y19 -> 0 | AC19: =((U19+V19)*2)*(W19+X19+Y19) -> 0 | AD19: =SUM(Q19:S19) -> 25.92
E20: Socle 1. (unheated space) | F20: 24.5 | G20: 0.55 | I20: =F20*G20 -> 13.475 | J20: =F20*H20 -> 0 | K20: =I20-Q20-R20-S20-Z20-AA20-AB20 -> 12.195 | L20: 0.8 | M20: 0.8 | P20: 2 | Q20: =L20*M20*N20 -> 0 | R20: =L20*M20*O20 -> 0 | S20: =L20*M20*P20 -> 1.28 | T20: =((L20+M20)*2)*(N20+O20+P20) -> 6.4 | Z20: =U20*V20*W20 -> 0 | AA20: =U20*V20*X20 -> 0 | AB20: =U20*V20*Y20 -> 0 | AC20: =((U20+V20)*2)*(W20+X20+Y20) -> 0 | AD20: =SUM(Q20:S20) -> 1.28
I21: =F21*G21 -> 0 | J21: =F21*H21 -> 0 | K21: =I21-Q21-R21-S21-Z21-AA21-AB21 -> 0 | Q21: =L21*M21*N21 -> 0 | R21: =L21*M21*O21 -> 0 | S21: =L21*M21*P21 -> 0 | T21: =((L21+M21)*2)*(N21+O21+P21) -> 0 | Z21: =U21*V21*W21 -> 0 | AA21: =U21*V21*X21 -> 0 | AB21: =U21*V21*Y21 -> 0 | AC21: =((U21+V21)*2)*(W21+X21+Y21) -> 0 | AD21: =SUM(Q21:S21) -> 0
Q22: =L22*M22*N22 -> 0 | R22: =L22*M22*O22 -> 0 | S22: =L22*M22*P22 -> 0 | T22: =((L22+M22)*2)*(N22+O22+P22) -> 0 | Z22: =U22*V22*W22 -> 0 | AA22: =U22*V22*X22 -> 0 | AB22: =U22*V22*Y22 -> 0 | AC22: =((U22+V22)*2)*(W22+X22+Y22) -> 0 | AD22: =SUM(Q22:S22) -> 0
Q23: =L23*M23*N23 -> 0 | R23: =L23*M23*O23 -> 0 | S23: =L23*M23*P23 -> 0 | T23: =((L23+M23)*2)*(N23+O23+P23) -> 0 | Z23: =U23*V23*W23 -> 0 | AA23: =U23*V23*X23 -> 0 | AB23: =U23*V23*Y23 -> 0 | AC23: =((U23+V23)*2)*(W23+X23+Y23) -> 0 | AD23: =SUM(Q23:S23) -> 0
C24: W | D24: P6 | E24: W1 | F24: 13.2 | G24: 6.6 | I24: =F24*G24 -> 87.12 | J24: =F24*H24 -> 0 | K24: =I24-Q24-R24-S24-Z24-AA24-AB24 -> 75.24 | L24: 1.2 | M24: 1.8 | P24: 3 | Q24: =L24*M24*N24 -> 0 | R24: =L24*M24*O24 -> 0 | S24: =L24*M24*P24 -> 6.48 | T24: =((L24+M24)*2)*(N24+O24+P24) -> 18 | U24: 0.9 | V24: 2 | W24: 3 | Z24: =U24*V24*W24 -> 5.4 | AA24: =U24*V24*X24 -> 0 | AB24: =U24*V24*Y24 -> 0 | AC24: =((U24+V24)*2)*(W24+X24+Y24) -> 17.4 | AD24: =SUM(Q24:S24) -> 6.48
E25: Socle 1. (unheated space) | F25: 13.2 | G25: 0.55 | I25: =F25*G25 -> 7.26 | J25: =F25*H25 -> 0 | K25: =I25-Q25-R25-S25-Z25-AA25-AB25 -> -1.74 | L25: 1 | M25: 1.8 | P25: 5 | Q25: =L25*M25*N25 -> 0 | R25: =L25*M25*O25 -> 0 | S25: =L25*M25*P25 -> 9 | T25: =((L25+M25)*2)*(N25+O25+P25) -> 28 | Z25: =U25*V25*W25 -> 0 | AA25: =U25*V25*X25 -> 0 | AB25: =U25*V25*Y25 -> 0 | AC25: =((U25+V25)*2)*(W25+X25+Y25) -> 0 | AD25: =SUM(Q25:S25) -> 9
I26: =F26*G26 -> 0 | J26: =F26*H26 -> 0 | K26: =I26-Q26-R26-S26-Z26-AA26-AB26 -> 0 | Q26: =L26*M26*N26 -> 0 | R26: =L26*M26*O26 -> 0 | S26: =L26*M26*P26 -> 0 | T26: =((L26+M26)*2)*(N26+O26+P26) -> 0 | Z26: =U26*V26*W26 -> 0 | AA26: =U26*V26*X26 -> 0 | AB26: =U26*V26*Y26 -> 0 | AC26: =((U26+V26)*2)*(W26+X26+Y26) -> 0 | AD26: =SUM(Q26:S26) -> 0
C27: S | D27: P7 | E27: W1 | F27: 50.7 | G27: 6.6 | I27: =F27*G27 -> 334.62 | J27: =F27*H27 -> 0 | K27: =I27-Q27-R27-S27-Z27-AA27-AB27 -> 275.66 | L27: 1.2 | M27: 1.8 | P27: 22 | Q27: =L27*M27*N27 -> 0 | R27: =L27*M27*O27 -> 0 | S27: =L27*M27*P27 -> 47.52 | T27: =((L27+M27)*2)*(N27+O27+P27) -> 132 | U27: 2.2 | V27: 2.6 | W27: 2 | Z27: =U27*V27*W27 -> 11.44 | AA27: =U27*V27*X27 -> 0 | AB27: =U27*V27*Y27 -> 0 | AC27: =((U27+V27)*2)*(W27+X27+Y27) -> 19.2 | AD27: =SUM(Q27:S27) -> 47.52
E28: Socle 1. (unheated space) | F28: 50.7 | G28: 0.55 | I28: =F28*G28 -> 27.885 | J28: =F28*H28 -> 0 | K28: =I28-Q28-R28-S28-Z28-AA28-AB28 -> 21.725 | L28: 0.8 | M28: 0.8 | P28: 4 | Q28: =L28*M28*N28 -> 0 | R28: =L28*M28*O28 -> 0 | S28: =L28*M28*P28 -> 2.56 | T28: =((L28+M28)*2)*(N28+O28+P28) -> 12.8 | U28: 0.9 | V28: 2 | W28: 2 | Z28: =U28*V28*W28 -> 3.6 | AA28: =U28*V28*X28 -> 0 | AB28: =U28*V28*Y28 -> 0 | AC28: =((U28+V28)*2)*(W28+X28+Y28) -> 11.6 | AD28: =SUM(Q28:S28) -> 2.56
I29: =F29*G29 -> 0 | J29: =F29*H29 -> 0 | K29: =I29-Q29-R29-S29-Z29-AA29-AB29 -> 0 | Q29: =L29*M29*N29 -> 0 | R29: =L29*M29*O29 -> 0 | S29: =L29*M29*P29 -> 0 | T29: =((L29+M29)*2)*(N29+O29+P29) -> 0 | Z29: =U29*V29*W29 -> 0 | AA29: =U29*V29*X29 -> 0 | AB29: =U29*V29*Y29 -> 0 | AC29: =((U29+V29)*2)*(W29+X29+Y29) -> 0 | AD29: =SUM(Q29:S29) -> 0
I30: =F30*G30 -> 0 | J30: =F30*H30 -> 0 | K30: =I30-Q30-R30-S30-Z30-AA30-AB30 -> 0 | Q30: =L30*M30*N30 -> 0 | R30: =L30*M30*O30 -> 0 | S30: =L30*M30*P30 -> 0 | T30: =((L30+M30)*2)*(N30+O30+P30) -> 0 | Z30: =U30*V30*W30 -> 0 | AA30: =U30*V30*X30 -> 0 | AB30: =U30*V30*Y30 -> 0 | AC30: =((U30+V30)*2)*(W30+X30+Y30) -> 0 | AD30: =SUM(Q30:S30) -> 0
I31: =F31*G31 -> 0 | J31: =F31*H31 -> 0 | K31: =I31-Q31-R31-S31-Z31-AA31-AB31 -> 0 | Q31: =L31*M31*N31 -> 0 | R31: =L31*M31*O31 -> 0 | S31: =L31*M31*P31 -> 0 | T31: =((L31+M31)*2)*(N31+O31+P31) -> 0 | Z31: =U31*V31*W31 -> 0 | AA31: =U31*V31*X31 -> 0 | AB31: =U31*V31*Y31 -> 0 | AC31: =((U31+V31)*2)*(W31+X31+Y31) -> 0 | AD31: =SUM(Q31:S31) -> 0
C32: E | D32: P8 | E32: W1 | F32: 13.2 | G32: 6.6 | I32: =F32*G32 -> 87.12 | J32: =F32*H32 -> 0 | K32: =I32-Q32-R32-S32-Z32-AA32-AB32 -> 79.2 | L32: 1.2 | M32: 1.8 | P32: 2 | Q32: =L32*M32*N32 -> 0 | R32: =L32*M32*O32 -> 0 | S32: =L32*M32*P32 -> 4.32 | T32: =((L32+M32)*2)*(N32+O32+P32) -> 12 | U32: 0.9 | V32: 2 | W32: 2 | Z32: =U32*V32*W32 -> 3.6 | AA32: =U32*V32*X32 -> 0 | AB32: =U32*V32*Y32 -> 0 | AC32: =((U32+V32)*2)*(W32+X32+Y32) -> 11.6 | AD32: =SUM(Q32:S32) -> 4.32
E33: Socle 1. (unheated space) | F33: 13.2 | G33: 0.55 | I33: =F33*G33 -> 7.26 | J33: =F33*H33 -> 0 | K33: =I33-Q33-R33-S33-Z33-AA33-AB33 -> 0.06 | L33: 1 | M33: 1.8 | P33: 4 | Q33: =L33*M33*N33 -> 0 | R33: =L33*M33*O33 -> 0 | S33: =L33*M33*P33 -> 7.2 | T33: =((L33+M33)*2)*(N33+O33+P33) -> 22.4 | Z33: =U33*V33*W33 -> 0 | AA33: =U33*V33*X33 -> 0 | AB33: =U33*V33*Y33 -> 0 | AC33: =((U33+V33)*2)*(W33+X33+Y33) -> 0 | AD33: =SUM(Q33:S33) -> 7.2
I34: =F34*G34 -> 0 | J34: =F34*H34 -> 0 | K34: =I34-Q34-R34-S34-Z34-AA34-AB34 -> 0 | Q34: =L34*M34*N34 -> 0 | R34: =L34*M34*O34 -> 0 | S34: =L34*M34*P34 -> 0 | T34: =((L34+M34)*2)*(N34+O34+P34) -> 0 | Z34: =U34*V34*W34 -> 0 | AA34: =U34*V34*X34 -> 0 | AB34: =U34*V34*Y34 -> 0 | AC34: =((U34+V34)*2)*(W34+X34+Y34) -> 0 | AD34: =SUM(Q34:S34) -> 0
C35: N | D35: P9 | E35: W1 | F35: 21.3 | G35: 6.6 | I35: =F35*G35 -> 140.58 | J35: =F35*H35 -> 0 | K35: =I35-Q35-R35-S35-Z35-AA35-AB35 -> 125.82 | L35: 1.2 | M35: 1.8 | P35: 6 | Q35: =L35*M35*N35 -> 0 | R35: =L35*M35*O35 -> 0 | S35: =L35*M35*P35 -> 12.96 | T35: =((L35+M35)*2)*(N35+O35+P35) -> 36 | U35: 0.9 | V35: 2 | W35: 1 | Z35: =U35*V35*W35 -> 1.8 | AA35: =U35*V35*X35 -> 0 | AB35: =U35*V35*Y35 -> 0 | AC35: =((U35+V35)*2)*(W35+X35+Y35) -> 5.8 | AD35: =SUM(Q35:S35) -> 12.96
E36: Socle 1. (unheated space) | F36: 21.3 | G36: 0.55 | I36: =F36*G36 -> 11.715 | J36: =F36*H36 -> 0 | K36: =I36-Q36-R36-S36-Z36-AA36-AB36 -> 9.915 | L36: 1 | M36: 1.8 | P36: 1 | Q36: =L36*M36*N36 -> 0 | R36: =L36*M36*O36 -> 0 | S36: =L36*M36*P36 -> 1.8 | T36: =((L36+M36)*2)*(N36+O36+P36) -> 5.6 | Z36: =U36*V36*W36 -> 0 | AA36: =U36*V36*X36 -> 0 | AB36: =U36*V36*Y36 -> 0 | AC36: =((U36+V36)*2)*(W36+X36+Y36) -> 0 | AD36: =SUM(Q36:S36) -> 1.8
I37: =F37*G37 -> 0 | J37: =F37*H37 -> 0 | K37: =I37-Q37-R37-S37-Z37-AA37-AB37 -> 0 | Q37: =L37*M37*N37 -> 0 | R37: =L37*M37*O37 -> 0 | S37: =L37*M37*P37 -> 0 | T37: =((L37+M37)*2)*(N37+O37+P37) -> 0 | Z37: =U37*V37*W37 -> 0 | AA37: =U37*V37*X37 -> 0 | AB37: =U37*V37*Y37 -> 0 | AC37: =((U37+V37)*2)*(W37+X37+Y37) -> 0 | AD37: =SUM(Q37:S37) -> 0
I38: =F38*G38 -> 0 | J38: =F38*H38 -> 0 | K38: =I38-Q38-R38-S38-Z38-AA38-AB38 -> 0 | Q38: =L38*M38*N38 -> 0 | R38: =L38*M38*O38 -> 0 | S38: =L38*M38*P38 -> 0 | T38: =((L38+M38)*2)*(N38+O38+P38) -> 0 | Z38: =U38*V38*W38 -> 0 | AA38: =U38*V38*X38 -> 0 | AB38: =U38*V38*Y38 -> 0 | AC38: =((U38+V38)*2)*(W38+X38+Y38) -> 0 | AD38: =SUM(Q38:S38) -> 0
C39: E | D39: P10 | E39: W1 | F39: 13.25 | G39: 3.3 | I39: =F39*G39 -> 43.725 | J39: =F39*H39 -> 0 | K39: =I39-Q39-R39-S39-Z39-AA39-AB39 -> 39.375 | Q39: =L39*M39*N39 -> 0 | R39: =L39*M39*O39 -> 0 | S39: =L39*M39*P39 -> 0 | T39: =((L39+M39)*2)*(N39+O39+P39) -> 0 | U39: 1.5 | V39: 2.9 | W39: 1 | Z39: =U39*V39*W39 -> 4.35 | AA39: =U39*V39*X39 -> 0 | AB39: =U39*V39*Y39 -> 0 | AC39: =((U39+V39)*2)*(W39+X39+Y39) -> 8.8 | AD39: =SUM(Q39:S39) -> 0
E40: Socle 1. (unheated space) | F40: 13.25 | G40: 0.55 | I40: =F40*G40 -> 7.2875 | J40: =F40*H40 -> 0 | K40: =I40-Q40-R40-S40-Z40-AA40-AB40 -> 7.2875 | Q40: =L40*M40*N40 -> 0 | R40: =L40*M40*O40 -> 0 | S40: =L40*M40*P40 -> 0 | T40: =((L40+M40)*2)*(N40+O40+P40) -> 0 | Z40: =U40*V40*W40 -> 0 | AA40: =U40*V40*X40 -> 0 | AB40: =U40*V40*Y40 -> 0 | AC40: =((U40+V40)*2)*(W40+X40+Y40) -> 0 | AD40: =SUM(Q40:S40) -> 0
I41: =F41*G41 -> 0 | J41: =F41*H41 -> 0 | K41: =I41-Q41-R41-S41-Z41-AA41-AB41 -> 0 | Q41: =L41*M41*N41 -> 0 | R41: =L41*M41*O41 -> 0 | S41: =L41*M41*P41 -> 0 | T41: =((L41+M41)*2)*(N41+O41+P41) -> 0 | Z41: =U41*V41*W41 -> 0 | AA41: =U41*V41*X41 -> 0 | AB41: =U41*V41*Y41 -> 0 | AC41: =((U41+V41)*2)*(W41+X41+Y41) -> 0 | AD41: =SUM(Q41:S41) -> 0
I42: =F42*G42 -> 0 | J42: =F42*H42 -> 0 | K42: =I42-Q42-R42-S42-Z42-AA42-AB42 -> 0 | Q42: =L42*M42*N42 -> 0 | R42: =L42*M42*O42 -> 0 | S42: =L42*M42*P42 -> 0 | T42: =((L42+M42)*2)*(N42+O42+P42) -> 0 | Z42: =U42*V42*W42 -> 0 | AA42: =U42*V42*X42 -> 0 | AB42: =U42*V42*Y42 -> 0 | AC42: =((U42+V42)*2)*(W42+X42+Y42) -> 0 | AD42: =SUM(Q42:S42) -> 0
C43: S | D43: P11 | E43: W1 | F43: =10.3+11 -> 21.3 | G43: 6.6 | I43: =F43*G43 -> 140.58 | J43: =F43*H43 -> 0 | K43: =I43-Q43-R43-S43-Z43-AA43-AB43 -> 133.56 | L43: 1.9 | M43: 1.8 | P43: 1 | Q43: =L43*M43*N43 -> 0 | R43: =L43*M43*O43 -> 0 | S43: =L43*M43*P43 -> 3.42 | T43: =((L43+M43)*2)*(N43+O43+P43) -> 7.4 | U43: 0.9 | V43: 2 | W43: 2 | Z43: =U43*V43*W43 -> 3.6 | AA43: =U43*V43*X43 -> 0 | AB43: =U43*V43*Y43 -> 0 | AC43: =((U43+V43)*2)*(W43+X43+Y43) -> 11.6 | AD43: =SUM(Q43:S43) -> 3.42
E44: Socle 1. (unheated space) | F44: =10.3+11 -> 21.3 | G44: 0.55 | I44: =F44*G44 -> 11.715 | J44: =F44*H44 -> 0 | K44: =I44-Q44-R44-S44-Z44-AA44-AB44 -> 9.555 | L44: 1.2 | M44: 1.8 | P44: 1 | Q44: =L44*M44*N44 -> 0 | R44: =L44*M44*O44 -> 0 | S44: =L44*M44*P44 -> 2.16 | T44: =((L44+M44)*2)*(N44+O44+P44) -> 6 | Z44: =U44*V44*W44 -> 0 | AA44: =U44*V44*X44 -> 0 | AB44: =U44*V44*Y44 -> 0 | AC44: =((U44+V44)*2)*(W44+X44+Y44) -> 0 | AD44: =SUM(Q44:S44) -> 2.16
I45: =F45*G45 -> 0 | J45: =F45*H45 -> 0 | K45: =I45-Q45-R45-S45-Z45-AA45-AB45 -> -19.8 | L45: 1 | M45: 1.8 | P45: 11 | Q45: =L45*M45*N45 -> 0 | R45: =L45*M45*O45 -> 0 | S45: =L45*M45*P45 -> 19.8 | T45: =((L45+M45)*2)*(N45+O45+P45) -> 61.6 | Z45: =U45*V45*W45 -> 0 | AA45: =U45*V45*X45 -> 0 | AB45: =U45*V45*Y45 -> 0 | AC45: =((U45+V45)*2)*(W45+X45+Y45) -> 0 | AD45: =SUM(Q45:S45) -> 19.8
I46: =F46*G46 -> 0 | J46: =F46*H46 -> 0 | K46: =I46-Q46-R46-S46-Z46-AA46-AB46 -> 0 | Q46: =L46*M46*N46 -> 0 | R46: =L46*M46*O46 -> 0 | S46: =L46*M46*P46 -> 0 | T46: =((L46+M46)*2)*(N46+O46+P46) -> 0 | Z46: =U46*V46*W46 -> 0 | AA46: =U46*V46*X46 -> 0 | AB46: =U46*V46*Y46 -> 0 | AC46: =((U46+V46)*2)*(W46+X46+Y46) -> 0 | AD46: =SUM(Q46:S46) -> 0
I47: =F47*G47 -> 0 | J47: =F47*H47 -> 0 | K47: =I47-Q47-R47-S47-Z47-AA47-AB47 -> 0 | Q47: =L47*M47*N47 -> 0 | R47: =L47*M47*O47 -> 0 | S47: =L47*M47*P47 -> 0 | T47: =((L47+M47)*2)*(N47+O47+P47) -> 0 | Z47: =U47*V47*W47 -> 0 | AA47: =U47*V47*X47 -> 0 | AB47: =U47*V47*Y47 -> 0 | AC47: =((U47+V47)*2)*(W47+X47+Y47) -> 0 | AD47: =SUM(Q47:S47) -> 0
I48: =F48*G48 -> 0 | J48: =F48*H48 -> 0 | K48: =I48-Q48-R48-S48-Z48-AA48-AB48 -> 0 | Q48: =L48*M48*N48 -> 0 | R48: =L48*M48*O48 -> 0 | S48: =L48*M48*P48 -> 0 | T48: =((L48+M48)*2)*(N48+O48+P48) -> 0 | Z48: =U48*V48*W48 -> 0 | AA48: =U48*V48*X48 -> 0 | AB48: =U48*V48*Y48 -> 0 | AC48: =((U48+V48)*2)*(W48+X48+Y48) -> 0 | AD48: =SUM(Q48:S48) -> 0
I49: =F49*G49 -> 0 | J49: =F49*H49 -> 0 | K49: =I49-Q49-R49-S49-Z49-AA49-AB49 -> 0 | Q49: =L49*M49*N49 -> 0 | R49: =L49*M49*O49 -> 0 | S49: =L49*M49*P49 -> 0 | T49: =((L49+M49)*2)*(N49+O49+P49) -> 0 | Z49: =U49*V49*W49 -> 0 | AA49: =U49*V49*X49 -> 0 | AB49: =U49*V49*Y49 -> 0 | AC49: =((U49+V49)*2)*(W49+X49+Y49) -> 0 | AD49: =SUM(Q49:S49) -> 0
I50: =F50*G50 -> 0 | J50: =F50*H50 -> 0 | K50: =I50-Q50-R50-S50-Z50-AA50-AB50 -> 0 | Q50: =L50*M50*N50 -> 0 | R50: =L50*M50*O50 -> 0 | S50: =L50*M50*P50 -> 0 | T50: =((L50+M50)*2)*(N50+O50+P50) -> 0 | Z50: =U50*V50*W50 -> 0 | AA50: =U50*V50*X50 -> 0 | AB50: =U50*V50*Y50 -> 0 | AC50: =((U50+V50)*2)*(W50+X50+Y50) -> 0 | AD50: =SUM(Q50:S50) -> 0
I51: =F51*G51 -> 0 | J51: =F51*H51 -> 0 | K51: =I51-Q51-R51-S51-Z51-AA51-AB51 -> 0 | Q51: =L51*M51*N51 -> 0 | R51: =L51*M51*O51 -> 0 | S51: =L51*M51*P51 -> 0 | T51: =((L51+M51)*2)*(N51+O51+P51) -> 0 | Z51: =U51*V51*W51 -> 0 | AA51: =U51*V51*X51 -> 0 | AB51: =U51*V51*Y51 -> 0 | AC51: =((U51+V51)*2)*(W51+X51+Y51) -> 0 | AD51: =SUM(Q51:S51) -> 0
C52: E | D52: P12 | E52: W1 | F52: 13.2 | G52: 6.6 | I52: =F52*G52 -> 87.12 | J52: =F52*H52 -> 0 | K52: =I52-Q52-R52-S52-Z52-AA52-AB52 -> 75.24 | L52: 1.2 | M52: 1.8 | P52: 3 | Q52: =L52*M52*N52 -> 0 | R52: =L52*M52*O52 -> 0 | S52: =L52*M52*P52 -> 6.48 | T52: =((L52+M52)*2)*(N52+O52+P52) -> 18 | U52: 0.9 | V52: 2 | W52: 3 | Z52: =U52*V52*W52 -> 5.4 | AA52: =U52*V52*X52 -> 0 | AB52: =U52*V52*Y52 -> 0 | AC52: =((U52+V52)*2)*(W52+X52+Y52) -> 17.4 | AD52: =SUM(Q52:S52) -> 6.48
E53: Socle 1. (unheated space) | F53: 13.2 | G53: 0.55 | I53: =F53*G53 -> 7.26 | J53: =F53*H53 -> 0 | K53: =I53-Q53-R53-S53-Z53-AA53-AB53 -> 0.06 | L53: 1 | M53: 1.8 | P53: 4 | Q53: =L53*M53*N53 -> 0 | R53: =L53*M53*O53 -> 0 | S53: =L53*M53*P53 -> 7.2 | T53: =((L53+M53)*2)*(N53+O53+P53) -> 22.4 | Z53: =U53*V53*W53 -> 0 | AA53: =U53*V53*X53 -> 0 | AB53: =U53*V53*Y53 -> 0 | AC53: =((U53+V53)*2)*(W53+X53+Y53) -> 0 | AD53: =SUM(Q53:S53) -> 7.2
I54: =F54*G54 -> 0 | J54: =F54*H54 -> 0 | K54: =I54-Q54-R54-S54-Z54-AA54-AB54 -> 0 | Q54: =L54*M54*N54 -> 0 | R54: =L54*M54*O54 -> 0 | S54: =L54*M54*P54 -> 0 | T54: =((L54+M54)*2)*(N54+O54+P54) -> 0 | Z54: =U54*V54*W54 -> 0 | AA54: =U54*V54*X54 -> 0 | AB54: =U54*V54*Y54 -> 0 | AC54: =((U54+V54)*2)*(W54+X54+Y54) -> 0 | AD54: =SUM(Q54:S54) -> 0
I55: =F55*G55 -> 0 | J55: =F55*H55 -> 0 | K55: =I55-Q55-R55-S55-Z55-AA55-AB55 -> 0 | Q55: =L55*M55*N55 -> 0 | R55: =L55*M55*O55 -> 0 | S55: =L55*M55*P55 -> 0 | T55: =((L55+M55)*2)*(N55+O55+P55) -> 0 | Z55: =U55*V55*W55 -> 0 | AA55: =U55*V55*X55 -> 0 | AB55: =U55*V55*Y55 -> 0 | AC55: =((U55+V55)*2)*(W55+X55+Y55) -> 0 | AD55: =SUM(Q55:S55) -> 0
C56: S | D56: P13 | E56: W1 | F56: 4.3 | G56: 3.3 | I56: =F56*G56 -> 14.19 | J56: =F56*H56 -> 0 | K56: =I56-Q56-R56-S56-Z56-AA56-AB56 -> 12.03 | L56: 1.2 | M56: 1.8 | P56: 1 | Q56: =L56*M56*N56 -> 0 | R56: =L56*M56*O56 -> 0 | S56: =L56*M56*P56 -> 2.16 | T56: =((L56+M56)*2)*(N56+O56+P56) -> 6 | Z56: =U56*V56*W56 -> 0 | AA56: =U56*V56*X56 -> 0 | AB56: =U56*V56*Y56 -> 0 | AC56: =((U56+V56)*2)*(W56+X56+Y56) -> 0 | AD56: =SUM(Q56:S56) -> 2.16
E57: Socle 1. (unheated space) | F57: 4.3 | G57: 0.55 | I57: =F57*G57 -> 2.365 | J57: =F57*H57 -> 0 | K57: =I57-Q57-R57-S57-Z57-AA57-AB57 -> 0.565 | L57: 1 | M57: 1.8 | P57: 1 | Q57: =L57*M57*N57 -> 0 | R57: =L57*M57*O57 -> 0 | S57: =L57*M57*P57 -> 1.8 | T57: =((L57+M57)*2)*(N57+O57+P57) -> 5.6 | Z57: =U57*V57*W57 -> 0 | AA57: =U57*V57*X57 -> 0 | AB57: =U57*V57*Y57 -> 0 | AC57: =((U57+V57)*2)*(W57+X57+Y57) -> 0 | AD57: =SUM(Q57:S57) -> 1.8
I58: =F58*G58 -> 0 | J58: =F58*H58 -> 0 | K58: =I58-Q58-R58-S58-Z58-AA58-AB58 -> 0 | Q58: =L58*M58*N58 -> 0 | R58: =L58*M58*O58 -> 0 | S58: =L58*M58*P58 -> 0 | T58: =((L58+M58)*2)*(N58+O58+P58) -> 0 | Z58: =U58*V58*W58 -> 0 | AA58: =U58*V58*X58 -> 0 | AB58: =U58*V58*Y58 -> 0 | AC58: =((U58+V58)*2)*(W58+X58+Y58) -> 0 | AD58: =SUM(Q58:S58) -> 0
C59: N | D59: P14 | E59: W1 | F59: 4.3 | G59: 3.3 | I59: =F59*G59 -> 14.19 | J59: =F59*H59 -> 0 | K59: =I59-Q59-R59-S59-Z59-AA59-AB59 -> 12.03 | L59: 1.2 | M59: 1.8 | P59: 1 | Q59: =L59*M59*N59 -> 0 | R59: =L59*M59*O59 -> 0 | S59: =L59*M59*P59 -> 2.16 | T59: =((L59+M59)*2)*(N59+O59+P59) -> 6 | Z59: =U59*V59*W59 -> 0 | AA59: =U59*V59*X59 -> 0 | AB59: =U59*V59*Y59 -> 0 | AC59: =((U59+V59)*2)*(W59+X59+Y59) -> 0 | AD59: =SUM(Q59:S59) -> 2.16
E60: Socle 1. (unheated space) | F60: 4.3 | G60: 0.55 | I60: =F60*G60 -> 2.365 | J60: =F60*H60 -> 0 | K60: =I60-Q60-R60-S60-Z60-AA60-AB60 -> 2.365 | Q60: =L60*M60*N60 -> 0 | R60: =L60*M60*O60 -> 0 | S60: =L60*M60*P60 -> 0 | T60: =((L60+M60)*2)*(N60+O60+P60) -> 0 | Z60: =U60*V60*W60 -> 0 | AA60: =U60*V60*X60 -> 0 | AB60: =U60*V60*Y60 -> 0 | AC60: =((U60+V60)*2)*(W60+X60+Y60) -> 0 | AD60: =SUM(Q60:S60) -> 0
I61: =F61*G61 -> 0 | J61: =F61*H61 -> 0 | K61: =I61-Q61-R61-S61-Z61-AA61-AB61 -> 0 | Q61: =L61*M61*N61 -> 0 | R61: =L61*M61*O61 -> 0 | S61: =L61*M61*P61 -> 0 | T61: =((L61+M61)*2)*(N61+O61+P61) -> 0 | Z61: =U61*V61*W61 -> 0 | AA61: =U61*V61*X61 -> 0 | AB61: =U61*V61*Y61 -> 0 | AC61: =((U61+V61)*2)*(W61+X61+Y61) -> 0 | AD61: =SUM(Q61:S61) -> 0
I62: =F62*G62 -> 0 | J62: =F62*H62 -> 0 | K62: =I62-Q62-R62-S62-Z62-AA62-AB62 -> 0 | Q62: =L62*M62*N62 -> 0 | R62: =L62*M62*O62 -> 0 | S62: =L62*M62*P62 -> 0 | T62: =((L62+M62)*2)*(N62+O62+P62) -> 0 | Z62: =U62*V62*W62 -> 0 | AA62: =U62*V62*X62 -> 0 | AB62: =U62*V62*Y62 -> 0 | AC62: =((U62+V62)*2)*(W62+X62+Y62) -> 0 | AD62: =SUM(Q62:S62) -> 0
I63: =F63*G63 -> 0 | J63: =F63*H63 -> 0 | K63: =I63-Q63-R63-S63-Z63-AA63-AB63 -> 0 | Q63: =L63*M63*N63 -> 0 | R63: =L63*M63*O63 -> 0 | S63: =L63*M63*P63 -> 0 | T63: =((L63+M63)*2)*(N63+O63+P63) -> 0 | Z63: =U63*V63*W63 -> 0 | AA63: =U63*V63*X63 -> 0 | AB63: =U63*V63*Y63 -> 0 | AC63: =((U63+V63)*2)*(W63+X63+Y63) -> 0 | AD63: =SUM(Q63:S63) -> 0
I64: =F64*G64 -> 0 | J64: =F64*H64 -> 0 | K64: =I64-Q64-R64-S64-Z64-AA64-AB64 -> 0 | Q64: =L64*M64*N64 -> 0 | R64: =L64*M64*O64 -> 0 | S64: =L64*M64*P64 -> 0 | T64: =((L64+M64)*2)*(N64+O64+P64) -> 0 | Z64: =U64*V64*W64 -> 0 | AA64: =U64*V64*X64 -> 0 | AB64: =U64*V64*Y64 -> 0 | AC64: =((U64+V64)*2)*(W64+X64+Y64) -> 0 | AD64: =SUM(Q64:S64) -> 0
I65: =F65*G65 -> 0 | J65: =F65*H65 -> 0 | K65: =I65-Q65-R65-S65-Z65-AA65-AB65 -> 0 | Q65: =L65*M65*N65 -> 0 | R65: =L65*M65*O65 -> 0 | S65: =L65*M65*P65 -> 0 | T65: =((L65+M65)*2)*(N65+O65+P65) -> 0 | Z65: =U65*V65*W65 -> 0 | AA65: =U65*V65*X65 -> 0 | AB65: =U65*V65*Y65 -> 0 | AC65: =((U65+V65)*2)*(W65+X65+Y65) -> 0 | AD65: =SUM(Q65:S65) -> 0
I66: =F66*G66 -> 0 | J66: =F66*H66 -> 0 | K66: =I66-Q66-R66-S66-Z66-AA66-AB66 -> 0 | Q66: =L66*M66*N66 -> 0 | R66: =L66*M66*O66 -> 0 | S66: =L66*M66*P66 -> 0 | T66: =((L66+M66)*2)*(N66+O66+P66) -> 0 | Z66: =U66*V66*W66 -> 0 | AA66: =U66*V66*X66 -> 0 | AB66: =U66*V66*Y66 -> 0 | AC66: =((U66+V66)*2)*(W66+X66+Y66) -> 0 | AD66: =SUM(Q66:S66) -> 0
I67: =F67*G67 -> 0 | J67: =F67*H67 -> 0 | K67: =I67-Q67-R67-S67-Z67-AA67-AB67 -> 0 | Q67: =L67*M67*N67 -> 0 | R67: =L67*M67*O67 -> 0 | S67: =L67*M67*P67 -> 0 | T67: =((L67+M67)*2)*(N67+O67+P67) -> 0 | Z67: =U67*V67*W67 -> 0 | AA67: =U67*V67*X67 -> 0 | AB67: =U67*V67*Y67 -> 0 | AC67: =((U67+V67)*2)*(W67+X67+Y67) -> 0 | AD67: =SUM(Q67:S67) -> 0
I68: =F68*G68 -> 0 | J68: =F68*H68 -> 0 | K68: =I68-Q68-R68-S68-Z68-AA68-AB68 -> 0 | Q68: =L68*M68*N68 -> 0 | R68: =L68*M68*O68 -> 0 | S68: =L68*M68*P68 -> 0 | T68: =((L68+M68)*2)*(N68+O68+P68) -> 0 | Z68: =U68*V68*W68 -> 0 | AA68: =U68*V68*X68 -> 0 | AB68: =U68*V68*Y68 -> 0 | AC68: =((U68+V68)*2)*(W68+X68+Y68) -> 0 | AD68: =SUM(Q68:S68) -> 0
I69: =F69*G69 -> 0 | J69: =F69*H69 -> 0 | K69: =I69-Q69-R69-S69-Z69-AA69-AB69 -> 0 | Q69: =L69*M69*N69 -> 0 | R69: =L69*M69*O69 -> 0 | S69: =L69*M69*P69 -> 0 | T69: =((L69+M69)*2)*(N69+O69+P69) -> 0 | Z69: =U69*V69*W69 -> 0 | AA69: =U69*V69*X69 -> 0 | AB69: =U69*V69*Y69 -> 0 | AC69: =((U69+V69)*2)*(W69+X69+Y69) -> 0 | AD69: =SUM(Q69:S69) -> 0
I70: =F70*G70 -> 0 | J70: =F70*H70 -> 0 | K70: =I70-Q70-R70-S70-Z70-AA70-AB70 -> 0 | Q70: =L70*M70*N70 -> 0 | R70: =L70*M70*O70 -> 0 | S70: =L70*M70*P70 -> 0 | T70: =((L70+M70)*2)*(N70+O70+P70) -> 0 | Z70: =U70*V70*W70 -> 0 | AA70: =U70*V70*X70 -> 0 | AB70: =U70*V70*Y70 -> 0 | AC70: =((U70+V70)*2)*(W70+X70+Y70) -> 0 | AD70: =SUM(Q70:S70) -> 0
I71: =F71*G71 -> 0 | J71: =F71*H71 -> 0 | K71: =I71-Q71-R71-S71-Z71-AA71-AB71 -> 0 | Q71: =L71*M71*N71 -> 0 | R71: =L71*M71*O71 -> 0 | S71: =L71*M71*P71 -> 0 | T71: =((L71+M71)*2)*(N71+O71+P71) -> 0 | Z71: =U71*V71*W71 -> 0 | AA71: =U71*V71*X71 -> 0 | AB71: =U71*V71*Y71 -> 0 | AC71: =((U71+V71)*2)*(W71+X71+Y71) -> 0 | AD71: =SUM(Q71:S71) -> 0
I72: =F72*G72 -> 0 | J72: =F72*H72 -> 0 | K72: =I72-Q72-R72-S72-Z72-AA72-AB72 -> 0 | Q72: =L72*M72*N72 -> 0 | R72: =L72*M72*O72 -> 0 | S72: =L72*M72*P72 -> 0 | T72: =((L72+M72)*2)*(N72+O72+P72) -> 0 | Z72: =U72*V72*W72 -> 0 | AA72: =U72*V72*X72 -> 0 | AB72: =U72*V72*Y72 -> 0 | AC72: =((U72+V72)*2)*(W72+X72+Y72) -> 0 | AD72: =SUM(Q72:S72) -> 0
I73: =F73*G73 -> 0 | J73: =F73*H73 -> 0 | K73: =I73-Q73-R73-S73-Z73-AA73-AB73 -> 0 | Q73: =L73*M73*N73 -> 0 | R73: =L73*M73*O73 -> 0 | S73: =L73*M73*P73 -> 0 | T73: =((L73+M73)*2)*(N73+O73+P73) -> 0 | Z73: =U73*V73*W73 -> 0 | AA73: =U73*V73*X73 -> 0 | AB73: =U73*V73*Y73 -> 0 | AC73: =((U73+V73)*2)*(W73+X73+Y73) -> 0 | AD73: =SUM(Q73:S73) -> 0
D74: Total | E74: W1 | K74: =SUMIF(E7:E73,E74,K7:K73) -> 1492.9 | L74: Total area by type [m2] | Q74: =SUM(Q7:Q73) -> 0 | R74: =SUM(R7:R73) -> 0 | S74: =SUM(S7:S73) -> 256.62 | Z74: =SUM(Z7:Z73) -> 61.43 | AA74: =SUM(AA7:AA73) -> 0 | AB74: =SUM(AB7:AB73) -> 0
E75: W2 (unheated) | K75: =SUMIF(E7:E73,E75,K7:K73) -> 0
E76: Socle 1. (heated space) | K76: =SUMIF(E7:E73,E76,K7:K73) -> 0 | L76: Total area [m2] | Q76: =Q74+R74+S74 -> 256.62 | Z76: =Z74+AA74+AB74 -> 61.43
E77: Socle 1. (unheated space) | K77: =SUMIF(E7:E73,E77,K7:K73) -> 104.015
L78: Total sills perimeter [m] | T78: =SUM(T7:T73) -> 747 | AC78: =SUM(AC7:AC73) -> 157.4
E79: Socle 2 | F79: =SUMIF(E7:E73,E79,F7:F73) -> 0 | K79: =SUMIF(E7:E73,E79,J7:J73) -> 0
N80: =SUM(N7:N73) -> 0 | O80: =SUM(O7:O73) -> 0 | P80: =SUM(P7:P73) -> 132
D84: Space name | E84: Brut area of one floor [m²] | F84: Number of floors | G84: Total brut heated area [m²] | H84: Net height of one floor | I84: Perimeter of the building [m] | J84: Thickness of exterior walls [m] | K84: Total area of the walls in section [m²] | L84: Net heated area [m²] | M84: Net heated volume [m³] | AE84: Element | AF84: Description of windows and doors before renovation | AG84: Type | AH84: Uvalue [W/m²K] | AI84: Area [m²]
AE86: Window | AF86: PVC framed, 3 camera, double glazed [3-12-3mm] | AG86: Win1 | AH86: 2.56 | AI86: =Q74 -> 0
D87: A blok | E87: =50.7*13.2 -> 669.24 | F87: 2 | G87: =E87*F87 -> 1338.48 | H87: 3 | I87: =(50.7+13.2)*2 -> 127.8 | J87: 0.4 | K87: =(I87*J87)*F87 -> 102.24 | L87: =G87-K87 -> 1236.24 | M87: =L87*H87 -> 3708.72 | AF87: Wooden double framed [3-50-3mm] | AG87: Win2 | AH87: 2.78 | AI87: =R74 -> 0
D88: B blok | E88: =50.7*13.2 -> 669.24 | F88: 2 | G88: =E88*F88 -> 1338.48 | H88: 3 | I88: =(50.7+13.2)*2 -> 127.8 | J88: 0.4 | K88: =(I88*J88)*F88 -> 102.24 | L88: =G88-K88 -> 1236.24 | M88: =L88*H88 -> 3708.72 | AF88: Aluminum frame 4-40-4 | AG88: Win3 | AH88: 2.94 | AI88: =S74 -> 256.62
D89: C blok | E89: =13.25*4.3 -> 56.975 | F89: 1 | G89: =E89*F89 -> 56.975 | H89: 3 | I89: =(13.25+4.3)*2 -> 35.1 | J89: 0.4 | K89: =(I89*J89)*F89 -> 14.04 | L89: =G89-K89 -> 42.935 | M89: =L89*H89 -> 128.805
G90: =E90*F90 -> 0 | K90: =(I90*J90)*F90 -> 0 | L90: =G90-K90 -> 0 | M90: =L90*H90 -> 0 | AE90: Door | AF90: Aluminum frame 4-40-4, double glazed [3-12-3mm] | AG90: D1 | AH90: 3.5 | AI90: =Z74 -> 61.43
G91: =E91*F91 -> 0 | K91: =(I91*J91)*F91 -> 0 | L91: =G91-K91 -> 0 | M91: =L91*H91 -> 0 | AF91: Wooden – 50mm | AG91: D2 | AH91: 4 | AI91: =AA74 -> 0
G92: =E92*F92 -> 0 | K92: =(I92*J92)*F92 -> 0 | L92: =G92-K92 -> 0 | M92: =L92*H92 -> 0 | AF92: Metal | AG92: D3 | AH92: 5.88 | AI92: =AB74 -> 0
G93: =E93*F93 -> 0 | K93: =(I93*J93)*F93 -> 0 | L93: =G93-K93 -> 0 | M93: =L93*H93 -> 0
G94: =E94*F94 -> 0 | K94: =(I94*J94)*F94 -> 0 | L94: =G94-K94 -> 0 | M94: =L94*H94 -> 0
D95: Total | G95: =SUM(G87:G94) -> 2733.935 | L95: =SUM(L87:L94) -> 2515.415 | M95: =SUM(M87:M94) -> 7546.245
AE96: Element | AF96: Description of windows and doors after renovation | AG96: Type | AH96: Uvalue [W/m²K]
AE98: Window | AF98: PVC framed, 5 camera, double glazed [4mm (Low-e < 0.1) - 20 Ar - 4mm] . | AG98: Win4 | AH98: 1.5
AE99: Door | AF99: PVC framed, 5 camera, sandwich panel 28 mm, double glazed [4mm (Low-e < 0.1) - 20 Ar - 4mm] . | AG99: D4 | AH99: 1.8
AF101: Types of walls
AF102: Description of existing walls | AG102: Type | AH102: Area [m²]
AF104: Internal plaster 10mm, Prefabricated concrete panels filled with ceramzit 350 mm, external plaster 10mm. | AG104: W1 | AH104: =K74 -> 1492.9
AF105: Internal plaster 10mm, Prefabricated concrete panels filled with ceramzit 350 mm | AG105: W2 (unheated) | AH105: =K75 -> 0 | AI105: heat losses do not calc
AF106: Socle area in contact with environment. Prefabricated concrete panels filled with ceramzit 350 mm, Concrete/sand mix 20mm, Decorative stone 30mm. | AG106: Socle 1. (heated space) | AH106: =K76 -> 0
AF107: Socle area in contact with environment. Concrete 600mm, Concrete/sand mix 20mm, Decorative stone 30mm. | AG107: Socle 1. (unheated space) | AH107: =K77 -> 104.015
AF108: Socle area in contact with the ground. Concrete 600mm | AG108: Socle 2 | AH108: =K79 -> 0
AF112: Types of floors
AF113: Description of existing floors | AG113: Type | AH113: Area [m²]
...

Sheet Consumption
B4: GAS | D4: Anul 2023 | G4: Anul 2024 | J4: Anul 2025 | M4: Average for the past 3 years (Baseline)
B5: № | C5: Davr | D5: Consum | E5: Expenses | F5: Tarif [so'm/m3] | G5: Consum | H5: Expenses | I5: Tarif [so'm/m3] | J5: Consum | K5: Expenses | L5: Tarif [so'm/m3] | M5: Consum | N5: Expenses | O5: Tarif [so'm/m3] | R5: According to latest tariff | U5: =Measures_summary!D45 -> 700000 | V5: so'm/gcal
D6: [m3] | E6: [so'm] | G6: [m3] | H6: [so'm] | J6: [m3] | K6: [so'm] | M6: [kWh] | N6: [so'm] | S6: Thermal | U6: =U5/1163 -> 601.89166 | V6: so'm/kWh
B7: 1 | C7: January | D7: 7274 | E7: =D7*F7 -> 18185000 | F7: =$U$8 -> 2500 | G7: 5691 | H7: =G7*I7 -> 14227500 | I7: =$U$8 -> 2500 | J7: 6976 | K7: =J7*L7 -> 17440000 | L7: =$U$8 -> 2500 | M7: =(D7+G7+J7)*9.5/3 -> 63146.5 | N7: =M7*O7 -> 69461150 | O7: 1100 | S7: Electrical | U7: =Measures_summary!D46 -> 1100 | V7: so'm/kWh | X7: 8887
B8: 2 | C8: February | D8: 5399 | E8: =D8*F8 -> 13497500 | F8: =$U$8 -> 2500 | G8: 5304 | H8: =G8*I8 -> 13260000 | I8: =$U$8 -> 2500 | J8: 5774 | K8: =J8*L8 -> 14435000 | L8: =$U$8 -> 2500 | M8: =(D8+G8+J8)*9.5/3 -> 52177.167 | N8: =M8*O8 -> 57394883 | O8: 1100 | S8: GAS | U8: =Measures_summary!D47 -> 2500 | V8: so'm/m3
B9: 3 | C9: March | D9: 1710 | E9: =D9*F9 -> 4275000 | F9: =$U$8 -> 2500 | G9: 3218 | H9: =G9*I9 -> 8045000 | I9: =$U$8 -> 2500 | J9: 2989 | K9: =J9*L9 -> 7472500 | L9: =$U$8 -> 2500 | M9: =(D9+G9+J9)*9.5/3 -> 25070.5 | N9: =M9*O9 -> 27577550 | O9: 1100
B10: 4 | C10: April | D10: 645 | E10: =D10*F10 -> 1612500 | F10: =$U$8 -> 2500 | G10: 514 | H10: =G10*I10 -> 1285000 | I10: =$U$8 -> 2500 | J10: 79 | K10: =J10*L10 -> 197500 | L10: =$U$8 -> 2500 | M10: =(D10+G10+J10)*9.5/3 -> 3920.3333 | N10: =M10*O10 -> 4312366.7 | O10: 1100
B11: 5 | C11: May | D11: 564 | E11: =D11*F11 -> 1410000 | F11: =$U$8 -> 2500 | G11: 557 | H11: =G11*I11 -> 1392500 | I11: =$U$8 -> 2500 | J11: 66 | K11: =J11*L11 -> 165000 | L11: =$U$8 -> 2500 | M11: =(D11+G11+J11)*9.5/3 -> 3758.8333 | N11: =M11*O11 -> 4134716.7 | O11: 1100
B12: 6 | C12: June | D12: 609 | E12: =D12*F12 -> 1522500 | F12: =$U$8 -> 2500 | G12: 519 | H12: =G12*I12 -> 1297500 | I12: =$U$8 -> 2500 | J12: 54 | K12: =J12*L12 -> 135000 | L12: =$U$8 -> 2500 | M12: =(D12+G12+J12)*9.5/3 -> 3743 | N12: =M12*O12 -> 4117300 | O12: 1100
B13: 7 | C13: July | D13: 614 | E13: =D13*F13 -> 1535000 | F13: =$U$8 -> 2500 | G13: 526 | H13: =G13*I13 -> 1315000 | I13: =$U$8 -> 2500 | J13: 47 | K13: =J13*L13 -> 117500 | L13: =$U$8 -> 2500 | M13: =(D13+G13+J13)*9.5/3 -> 3758.8333 | N13: =M13*O13 -> 4134716.7 | O13: 1100
B14: 8 | C14: August | D14: 571 | E14: =D14*F14 -> 1427500 | F14: =$U$8 -> 2500 | G14: 106 | H14: =G14*I14 -> 265000 | I14: =$U$8 -> 2500 | J14: 1054 | K14: =J14*L14 -> 2635000 | L14: =$U$8 -> 2500 | M14: =(D14+G14+J14)*9.5/3 -> 5481.5 | N14: =M14*O14 -> 6029650 | O14: 1100
B15: 9 | C15: September | D15: 205 | E15: =D15*F15 -> 512500 | F15: =$U$8 -> 2500 | G15: 95 | H15: =G15*I15 -> 237500 | I15: =$U$8 -> 2500 | J15: 62 | K15: =J15*L15 -> 155000 | L15: =$U$8 -> 2500 | M15: =(D15+G15+J15)*9.5/3 -> 1146.3333 | N15: =M15*O15 -> 1260966.7 | O15: 1100
B16: 10 | C16: October | D16: 1138 | E16: =D16*F16 -> 2845000 | F16: =$U$8 -> 2500 | G16: 1062 | H16: =G16*I16 -> 2655000 | I16: =$U$8 -> 2500 | J16: 65 | K16: =J16*L16 -> 162500 | L16: =$U$8 -> 2500 | M16: =(D16+G16+J16)*9.5/3 -> 7172.5 | N16: =M16*O16 -> 7889750 | O16: 1100
B17: 11 | C17: November | D17: 3196 | E17: =D17*F17 -> 7990000 | F17: =$U$8 -> 2500 | G17: 1609 | H17: =G17*I17 -> 4022500 | I17: =$U$8 -> 2500 | J17: 2933 | K17: =J17*L17 -> 7332500 | L17: =$U$8 -> 2500 | M17: =(D17+G17+J17)*9.5/3 -> 24503.667 | N17: =M17*O17 -> 26954033 | O17: 1100
B18: 12 | C18: December | D18: 4965 | E18: =D18*F18 -> 12412500 | F18: =$U$8 -> 2500 | G18: 5476 | H18: =G18*I18 -> 13690000 | I18: =$U$8 -> 2500 | J18: 4239 | K18: =J18*L18 -> 10597500 | L18: =$U$8 -> 2500 | M18: =(D18+G18+J18)*9.5/3 -> 46486.667 | N18: =M18*O18 -> 51135333 | O18: 1100
B19: TOTAL | D19: =SUM(D7:D18) -> 26890 | E19: =SUM(E7:E18) -> 67225000 | G19: =SUM(G7:G18) -> 24677 | H19: =SUM(H7:H18) -> 61692500 | J19: =SUM(J7:J18) -> 24338 | K19: =SUM(K7:K18) -> 60845000 | M19: =SUM(M7:M18) -> 240365.83 | N19: =SUM(N7:N18) -> 2.6440242e+08
B22: Electrical Energy | D22: Anul 2023 | G22: Anul 2024 | J22: Anul 2025 | M22: Average for the past 3 years (Baseline)
B23: № | C23: Davr | D23: Consum | E23: Expenses | F23: Tarif [so'm/kWh] | G23: Consum | H23: Expenses | I23: Tarif [so'm/kWh] | J23: Consum | K23: Expenses | L23: Tarif [so'm/kWh] | M23: Consum | N23: Expenses | O23: Tarif [so'm/kWh]
D24: [kWh] | E24: [so'm] | G24: [kWh] | H24: [so'm] | J24: [kWh] | K24: [so'm] | M24: [kWh] | N24: [so'm]
B25: 1 | C25: January | D25: 4211 | E25: =D25*F25 -> 3789900 | F25: =900 -> 900 | G25: 7119 | H25: =G25*I25 -> 6407100 | I25: =900 -> 900 | J25: 6699 | K25: =J25*L25 -> 6029100 | L25: =900 -> 900 | M25: =(D25+G25+J25)/3 -> 6009.6667 | N25: =M25*O25 -> 6610633.3 | O25: =$U$7 -> 1100
B26: 2 | C26: February | D26: 4389 | E26: =D26*F26 -> 3950100 | F26: =900 -> 900 | G26: 6447 | H26: =G26*I26 -> 5802300 | I26: =900 -> 900 | J26: 5964 | K26: =J26*L26 -> 5367600 | L26: =900 -> 900 | M26: =(D26+G26+J26)/3 -> 5600 | N26: =M26*O26 -> 6160000 | O26: =$U$7 -> 1100
B27: 3 | C27: March | D27: 3633 | E27: =D27*F27 -> 3269700 | F27: =900 -> 900 | G27: 5439 | H27: =G27*I27 -> 4895100 | I27: =900 -> 900 | J27: 4893 | K27: =J27*L27 -> 4403700 | L27: =900 -> 900 | M27: =(D27+G27+J27)/3 -> 4655 | N27: =M27*O27 -> 5120500 | O27: =$U$7 -> 1100
B28: 4 | C28: April | D28: 6111 | E28: =D28*F28 -> 5499900 | F28: =900 -> 900 | G28: 4641 | H28: =G28*I28 -> 4176900 | I28: =900 -> 900 | J28: 4473 | K28: =J28*L28 -> 4025700 | L28: =900 -> 900 | M28: =(D28+G28+J28)/3 -> 5075 | N28: =M28*O28 -> 5582500 | O28: =$U$7 -> 1100
B29: 5 | C29: May | D29: 4095 | E29: =D29*F29 -> 3685500 | F29: =900 -> 900 | G29: 4630 | H29: =G29*I29 -> 4167000 | I29: =900 -> 900 | J29: 4059 | K29: =J29*L29 -> 3653100 | L29: =900 -> 900 | M29: =(D29+G29+J29)/3 -> 4261.3333 | N29: =M29*O29 -> 4687466.7 | O29: =$U$7 -> 1100
B30: 6 | C30: June | D30: 2604 | E30: =D30*F30 -> 2343600 | F30: =900 -> 900 | G30: 3620 | H30: =G30*I30 -> 3258000 | I30: =900 -> 900 | J30: 4000 | K30: =J30*L30 -> 3600000 | L30: =900 -> 900 | M30: =(D30+G30+J30)/3 -> 3408 | N30: =M30*O30 -> 3748800 | O30: =$U$7 -> 1100
B31: 7 | C31: July | D31: 2900 | E31: =D31*F31 -> 2610000 | F31: =900 -> 900 | G31: 3499 | H31: =G31*I31 -> 3149100 | I31: =900 -> 900 | J31: 4138 | K31: =J31*L31 -> 3724200 | L31: =900 -> 900 | M31: =(D31+G31+J31)/3 -> 3512.3333 | N31: =M31*O31 -> 3863566.7 | O31: =$U$7 -> 1100
B32: 8 | C32: August | D32: 2770 | E32: =D32*F32 -> 2493000 | F32: =900 -> 900 | G32: 4157 | H32: =G32*I32 -> 3741300 | I32: =900 -> 900 | J32: 3964 | K32: =J32*L32 -> 3567600 | L32: =900 -> 900 | M32: =(D32+G32+J32)/3 -> 3630.3333 | N32: =M32*O32 -> 3993366.7 | O32: =$U$7 -> 1100
B33: 9 | C33: September | D33: 3780 | E33: =D33*F33 -> 3402000 | F33: =900 -> 900 | G33: 4296 | H33: =G33*I33 -> 3866400 | I33: =900 -> 900 | J33: 3663 | K33: =J33*L33 -> 3296700 | L33: =900 -> 900 | M33: =(D33+G33+J33)/3 -> 3913 | N33: =M33*O33 -> 4304300 | O33: =$U$7 -> 1100
B34: 10 | C34: October | D34: 3507 | E34: =D34*F34 -> 3156300 | F34: =900 -> 900 | G34: 5124 | H34: =G34*I34 -> 4611600 | I34: =900 -> 900 | J34: 4486 | K34: =J34*L34 -> 4037400 | L34: =900 -> 900 | M34: =(D34+G34+J34)/3 -> 4372.3333 | N34: =M34*O34 -> 4809566.7 | O34: =$U$7 -> 1100
B35: 11 | C35: November | D35: 5607 | E35: =D35*F35 -> 5046300 | F35: =900 -> 900 | G35: 5565 | H35: =G35*I35 -> 5008500 | I35: =900 -> 900 | J35: 5751 | K35: =J35*L35 -> 5175900 | L35: =900 -> 900 | M35: =(D35+G35+J35)/3 -> 5641 | N35: =M35*O35 -> 6205100 | O35: =$U$7 -> 1100
B36: 12 | C36: December | D36: 5586 | E36: =D36*F36 -> 5027400 | F36: =900 -> 900 | G36: 6111 | H36: =G36*I36 -> 5499900 | I36: =900 -> 900 | J36: 6204 | K36: =J36*L36 -> 5583600 | L36: =900 -> 900 | M36: =(D36+G36+J36)/3 -> 5967 | N36: =M36*O36 -> 6563700 | O36: =$U$7 -> 1100
B37: TOTAL | D37: =SUM(D25:D36) -> 49193 | E37: =SUM(E25:E36) -> 44273700 | G37: =SUM(G25:G36) -> 60648 | H37: =SUM(H25:H36) -> 54583200 | J37: =SUM(J25:J36) -> 58294 | K37: =SUM(K25:K36) -> 52464600 | M37: =SUM(M25:M36) -> 56045 | N37: =SUM(N25:N36) -> 61649500
B40: Energie Termică | D40: Anul 2023 | G40: Anul 2024 | J40: Anul 2025 | M40: Average for the past 3 years (Baseline)
B41: № | C41: Davr | D41: Consum | E41: Expenses | F41: Tarif [so'm/m3] | G41: Consum | H41: Expenses | I41: Tarif [so'm/m3] | J41: Consum | K41: Expenses | L41: Tarif [so'm/m3] | M41: Consum | N41: Expenses | O41: Tarif [so'm/m3]
D42: [m3] | E42: [so'm] | G42: [m3] | H42: [so'm] | J42: [m3] | K42: [so'm] | M42: [kWh] | N42: [so'm]
B43: 1 | C43: January | F43: 1122 | I43: 1122 | L43: 1122 | M43: =(D43+G43+J43)*1163/3 -> 0 | N43: =M43*O43 -> 0 | O43: =$U$6 -> 601.89166 | X43: 8887
B44: 2 | C44: February | F44: 1122 | I44: 1122 | L44: 1122 | M44: =(D44+G44+J44)*1163/3 -> 0 | N44: =M44*O44 -> 0 | O44: =$U$6 -> 601.89166
B45: 3 | C45: March | F45: 1122 | I45: 1122 | L45: 1122 | M45: =J45*1163 -> 0 | N45: =M45*O45 -> 0 | O45: =$U$6 -> 601.89166
B46: 4 | C46: April | F46: 1122 | I46: 1122 | L46: 1122 | M46: =J46*1163 -> 0 | N46: =M46*O46 -> 0 | O46: =$U$6 -> 601.89166
B47: 5 | C47: May | F47: 1122 | I47: 1122 | L47: 1122 | M47: =J47*1163 -> 0 | N47: =M47*O47 -> 0 | O47: =$U$6 -> 601.89166 | P47: =AA47/Z47 -> #DIV/0! | Q47: =(Z47+Z48+Z49+Z50+Z51)/5 -> 0 | S47: =AD47/AC47 -> #DIV/0! | T47: =(AC47+AC48+AC49+AC50+AC51)/5 -> 0 | V47: =AG47/AF47 -> #DIV/0! | W47: =(AF47+AF48+AF49+AF50+AF51)/5 -> 0
B48: 6 | C48: June | F48: 1122 | I48: 1122 | L48: 1122 | M48: =J48*1163 -> 0 | N48: =M48*O48 -> 0 | O48: =$U$6 -> 601.89166 | V48: =AG48/AF48 -> #DIV/0!
B49: 7 | C49: July | F49: 1122 | I49: 1122 | L49: 1122 | M49: =J49*1163 -> 0 | N49: =M49*O49 -> 0 | O49: =$U$6 -> 601.89166 | V49: =AG49/AF49 -> #DIV/0!
B50: 8 | C50: August | F50: 1122 | I50: 1122 | L50: 1122 | M50: =J50*1163 -> 0 | N50: =M50*O50 -> 0 | O50: =$U$6 -> 601.89166 | V50: =AG50/AF50 -> #DIV/0!
B51: 9 | C51: September | F51: 1122 | I51: 1122 | L51: 1122 | M51: =J51*1163 -> 0 | N51: =M51*O51 -> 0 | O51: =$U$6 -> 601.89166 | V51: =AG51/AF51 -> #DIV/0!
B52: 10 | C52: October | F52: 1122 | I52: 1122 | L52: 1122 | M52: =J52*1163 -> 0 | N52: =M52*O52 -> 0 | O52: =$U$6 -> 601.89166
B53: 11 | C53: November | F53: 1122 | I53: 1122 | L53: 1772 | M53: =J53*1163 -> 0 | N53: =M53*O53 -> 0 | O53: =$U$6 -> 601.89166
B54: 12 | C54: December | F54: 1122 | I54: 1122 | L54: 1772 | M54: =J54*1163 -> 0 | N54: =M54*O54 -> 0 | O54: =$U$6 -> 601.89166
B55: TOTAL | D55: =SUM(D43:D54) -> 0 | E55: =SUM(E43:E54) -> 0 | G55: =SUM(G43:G54) -> 0 | H55: =SUM(H43:H54) -> 0 | J55: =SUM(J43:J54) -> 0 | K55: =SUM(K43:K54) -> 0 | M55: =SUM(M43:M54) -> 0 | N55: =SUM(N43:N54) -> 0
B57: For DHW preparation the average (baseline energy consumption) should be also calculated in kWh
B58: For other types of fuels like biomass, natural gas, coal etc. the same principle to be applied.

Sheet Weather
B3: Normative Weather | P3: I propose to delete this page in general, because:
P4: 1. We have normative values in one single standard, for different climatic zones and different heating durations (3 zones x 2 types of heating duration = 6 tables)
B5: Month | C5: 1 | D5: 2 | E5: 3 | F5: 4 | G5: 5 | H5: 6 | I5: 7 | J5: 8 | K5: 9 | L5: 10 | M5: 11 | N5: 12 | P5: 2. We never use actual weather in calculations, only the normative because we don't have an open acces to weather data, it costs a lot of money and unfortunately even the Ministry cannot afford to by it yet to update the 40yo database from standards
B6: Ambient temp | C6: -1.7 | D6: -0.7 | E6: 4.5 | F6: 11 | G6: 17 | H6: 19.7 | I6: 21.1 | J6: 21 | K6: 15.3 | L6: 10.6 | M6: 5.4 | N6: -0.8 | P6: 3. These tables shouldn't be here because this data is fixed by the standard and is not an input data.
B7: North | C7: 9 | D7: 14 | E7: 25 | F7: 33 | G7: 46 | H7: 53 | I7: 53 | J7: 37 | K7: 27 | L7: 19 | M7: 12 | N7: 9
B8: East | C8: 17 | D8: 32 | E8: 63 | F8: 87 | G8: 111 | H8: 105 | I8: 117 | J8: 100 | K8: 76 | L8: 53 | M8: 28 | N8: 16
B9: South | C9: 47 | D9: 72 | E9: 112 | F9: 109 | G9: 104 | H9: 90 | I9: 100 | J9: 111 | K9: 119 | L9: 115 | M9: 75 | N9: 49
B10: West | C10: 19 | D10: 32 | E10: 66 | F10: 87 | G10: 106 | H10: 103 | I10: 108 | J10: 97 | K10: 79 | L10: 59 | M10: 30 | N10: 19
B11: Global | C11: 27 | D11: 49 | E11: 100 | F11: 140 | G11: 180 | H11: 177 | I11: 187 | J11: 164 | K11: 122 | L11: 81 | M11: 41 | N11: 26
B12: Dew point | C12: -3.6 | D12: -3.4 | E12: -0.3 | F12: 4.7 | G12: 10.4 | H12: 13.3 | I12: 15.5 | J12: 14.9 | K12: 10.7 | L12: 6.9 | M12: 2.5 | N12: -2.7
B13: Sky temp | C13: -11.7 | D13: -12.4 | E13: -8.4 | F13: -2.4 | G13: 4.5 | H13: 7.4 | I13: 9.6 | J13: 9.7 | K13: 4.6 | L13: -0.2 | M13: -4.9 | N13: -11.4
B14: Ground temp | C14: -1.7 | D14: -0.7 | E14: 4.5 | F14: 11 | G14: 17 | H14: 19.7 | I14: 21.1 | J14: 21 | K14: 15.3 | L14: 10.6 | M14: 5.4 | N14: -0.8
B16: Actual weather data of | E16: year
B18: Month | C18: 1 | D18: 2 | E18: 3 | F18: 4 | G18: 5 | H18: 6 | I18: 7 | J18: 8 | K18: 9 | L18: 10 | M18: 11 | N18: 12
B19: Ambient temp | C19: -1.7 | D19: -0.7 | E19: 4.5 | F19: 11 | G19: 17 | H19: 19.7 | I19: 21.1 | J19: 21 | K19: 15.3 | L19: 10.6 | M19: 5.4 | N19: -0.8
B20: North | C20: 9 | D20: 14 | E20: 25 | F20: 33 | G20: 46 | H20: 53 | I20: 53 | J20: 37 | K20: 27 | L20: 19 | M20: 12 | N20: 9
B21: East | C21: 17 | D21: 32 | E21: 63 | F21: 87 | G21: 111 | H21: 105 | I21: 117 | J21: 100 | K21: 76 | L21: 53 | M21: 28 | N21: 16
B22: South | C22: 47 | D22: 72 | E22: 112 | F22: 109 | G22: 104 | H22: 90 | I22: 100 | J22: 111 | K22: 119 | L22: 115 | M22: 75 | N22: 49
B23: West | C23: 19 | D23: 32 | E23: 66 | F23: 87 | G23: 106 | H23: 103 | I23: 108 | J23: 97 | K23: 79 | L23: 59 | M23: 30 | N23: 19
B24: Global | C24: 27 | D24: 49 | E24: 100 | F24: 140 | G24: 180 | H24: 177 | I24: 187 | J24: 164 | K24: 122 | L24: 81 | M24: 41 | N24: 26
B25: Dew point | C25: -3.6 | D25: -3.4 | E25: -0.3 | F25: 4.7 | G25: 10.4 | H25: 13.3 | I25: 15.5 | J25: 14.9 | K25: 10.7 | L25: 6.9 | M25: 2.5 | N25: -2.7
B26: Sky temp | C26: -11.7 | D26: -12.4 | E26: -8.4 | F26: -2.4 | G26: 4.5 | H26: 7.4 | I26: 9.6 | J26: 9.7 | K26: 4.6 | L26: -0.2 | M26: -4.9 | N26: -11.4
B27: Ground temp | C27: -1.7 | D27: -0.7 | E27: 4.5 | F27: 11 | G27: 17 | H27: 19.7 | I27: 21.1 | J27: 21 | K27: 15.3 | L27: 10.6 | M27: 5.4 | N27: -0.8
B29: Actual weather data of | E29: year
B31: Month | C31: 1 | D31: 2 | E31: 3 | F31: 4 | G31: 5 | H31: 6 | I31: 7 | J31: 8 | K31: 9 | L31: 10 | M31: 11 | N31: 12
B32: Ambient temp | C32: -1.7 | D32: -0.7 | E32: 4.5 | F32: 11 | G32: 17 | H32: 19.7 | I32: 21.1 | J32: 21 | K32: 15.3 | L32: 10.6 | M32: 5.4 | N32: -0.8
B33: North | C33: 9 | D33: 14 | E33: 25 | F33: 33 | G33: 46 | H33: 53 | I33: 53 | J33: 37 | K33: 27 | L33: 19 | M33: 12 | N33: 9
B34: East | C34: 17 | D34: 32 | E34: 63 | F34: 87 | G34: 111 | H34: 105 | I34: 117 | J34: 100 | K34: 76 | L34: 53 | M34: 28 | N34: 16
B35: South | C35: 47 | D35: 72 | E35: 112 | F35: 109 | G35: 104 | H35: 90 | I35: 100 | J35: 111 | K35: 119 | L35: 115 | M35: 75 | N35: 49
B36: West | C36: 19 | D36: 32 | E36: 66 | F36: 87 | G36: 106 | H36: 103 | I36: 108 | J36: 97 | K36: 79 | L36: 59 | M36: 30 | N36: 19
B37: Global | C37: 27 | D37: 49 | E37: 100 | F37: 140 | G37: 180 | H37: 177 | I37: 187 | J37: 164 | K37: 122 | L37: 81 | M37: 41 | N37: 26
B38: Dew point | C38: -3.6 | D38: -3.4 | E38: -0.3 | F38: 4.7 | G38: 10.4 | H38: 13.3 | I38: 15.5 | J38: 14.9 | K38: 10.7 | L38: 6.9 | M38: 2.5 | N38: -2.7
B39: Sky temp | C39: -11.7 | D39: -12.4 | E39: -8.4 | F39: -2.4 | G39: 4.5 | H39: 7.4 | I39: 9.6 | J39: 9.7 | K39: 4.6 | L39: -0.2 | M39: -4.9 | N39: -11.4
B40: Ground temp | C40: -1.7 | D40: -0.7 | E40: 4.5 | F40: 11 | G40: 17 | H40: 19.7 | I40: 21.1 | J40: 21 | K40: 15.3 | L40: 10.6 | M40: 5.4 | N40: -0.8
B42: Actual weather data of | E42: year
B44: Month | C44: 1 | D44: 2 | E44: 3 | F44: 4 | G44: 5 | H44: 6 | I44: 7 | J44: 8 | K44: 9 | L44: 10 | M44: 11 | N44: 12
B45: Ambient temp | C45: -1.7 | D45: -0.7 | E45: 4.5 | F45: 11 | G45: 17 | H45: 19.7 | I45: 21.1 | J45: 21 | K45: 15.3 | L45: 10.6 | M45: 5.4 | N45: -0.8
B46: North | C46: 9 | D46: 14 | E46: 25 | F46: 33 | G46: 46 | H46: 53 | I46: 53 | J46: 37 | K46: 27 | L46: 19 | M46: 12 | N46: 9
B47: East | C47: 17 | D47: 32 | E47: 63 | F47: 87 | G47: 111 | H47: 105 | I47: 117 | J47: 100 | K47: 76 | L47: 53 | M47: 28 | N47: 16
B48: South | C48: 47 | D48: 72 | E48: 112 | F48: 109 | G48: 104 | H48: 90 | I48: 100 | J48: 111 | K48: 119 | L48: 115 | M48: 75 | N48: 49
B49: West | C49: 19 | D49: 32 | E49: 66 | F49: 87 | G49: 106 | H49: 103 | I49: 108 | J49: 97 | K49: 79 | L49: 59 | M49: 30 | N49: 19
B50: Global | C50: 27 | D50: 49 | E50: 100 | F50: 140 | G50: 180 | H50: 177 | I50: 187 | J50: 164 | K50: 122 | L50: 81 | M50: 41 | N50: 26
B51: Dew point | C51: -3.6 | D51: -3.4 | E51: -0.3 | F51: 4.7 | G51: 10.4 | H51: 13.3 | I51: 15.5 | J51: 14.9 | K51: 10.7 | L51: 6.9 | M51: 2.5 | N51: -2.7
B52: Sky temp | C52: -11.7 | D52: -12.4 | E52: -8.4 | F52: -2.4 | G52: 4.5 | H52: 7.4 | I52: 9.6 | J52: 9.7 | K52: 4.6 | L52: -0.2 | M52: -4.9 | N52: -11.4
B53: Ground temp | C53: -1.7 | D53: -0.7 | E53: 4.5 | F53: 11 | G53: 17 | H53: 19.7 | I53: 21.1 | J53: 21 | K53: 15.3 | L53: 10.6 | M53: 5.4 | N53: -0.8

Sheet U-values
C2: Calculation of Uvalue for external wall before renovation (W1) | J2: Calculation of Uvalue for external wall after renovation (W1)
C3: Layers | E3: Thickness | F3: Thermal conductivity | H3: Thermal resistance | J3: Layers | L3: Thickness | M3: Thermal conductivity | O3: Thermal resistance | Q3: Rezistența termică a suprafeței din Interior / Exterior [m²K/W] - SM SR EN ISO 6946
Q4: Rezistența termică a suprafeței în m2K/W | T4: Rint | U4: Rext
E5: [m] | F5: [W/mK] | H5: [m²K/W] | L5: [m] | M5: [W/mK] | O5: [m²K/W]
C6: 1 | D6: Internal plaster | E6: 0.002 | F6: =IFERROR(VLOOKUP(D6,$Y$7:$Z$46,2,FALSE),"") -> 0.7 | H6: =IFERROR(IF(F6=0,0,E6/F6),"") -> 0.0028571429 | J6: 1 | K6: Internal plaster | L6: 0.002 | M6: =IFERROR(VLOOKUP(K6,$Y$7:$Z$46,2,FALSE),"") -> 0.7 | O6: =IFERROR(IF(M6=0,0,L6/M6),"") -> 0.0028571429 | Q6: Tashqi muhit bilan aloqada bo'lgan vertikal element (masalan, devor) | T6: 0.115 | U6: 0.04 | Y6: Material de construcție | Z6: λ,W/(m∙K) | AA6: Column1
C7: 2 | D7: Concrete/sand mix | E7: 0.01 | F7: =IFERROR(VLOOKUP(D7,$Y$7:$Z$46,2,FALSE),"") -> 0.76 | H7: =IFERROR(IF(F7=0,0,E7/F7),"") -> 0.013157895 | J7: 2 | K7: Concrete/sand mix | L7: 0.01 | M7: =IFERROR(VLOOKUP(K7,$Y$7:$Z$46,2,FALSE),"") -> 0.76 | O7: =IFERROR(IF(M7=0,0,L7/M7),"") -> 0.013157895 | Q7: Isitilgan makon bilan aloqada bo'lgan devor | T7: 0.115 | U7: 0.115 | Y7: Internal plaster | Z7: 0.7
C8: 3 | D8: Bricks | E8: 0.38 | F8: =IFERROR(VLOOKUP(D8,$Y$7:$Z$46,2,FALSE),"") -> 0.7 | H8: =IFERROR(IF(F8=0,0,E8/F8),"") -> 0.54285714 | J8: 3 | K8: Bricks | L8: 0.38 | M8: =IFERROR(VLOOKUP(K8,$Y$7:$Z$46,2,FALSE),"") -> 0.7 | O8: =IFERROR(IF(M8=0,0,L8/M8),"") -> 0.54285714 | Q8: Yer bilan aloqada bo'lgan devor (vertikal) | T8: 2.1 | U8: 0 | Y8: External plaster | Z8: 0.76
C9: 4 | D9: Concrete/sand mix | E9: 0.01 | F9: =IFERROR(VLOOKUP(D9,$Y$7:$Z$46,2,FALSE),"") -> 0.76 | H9: =IFERROR(IF(F9=0,0,E9/F9),"") -> 0.013157895 | J9: 4 | K9: Concrete/sand mix | L9: 0.01 | M9: =IFERROR(VLOOKUP(K9,$Y$7:$Z$46,2,FALSE),"") -> 0.76 | O9: =IFERROR(IF(M9=0,0,L9/M9),"") -> 0.013157895 | Q9: Tom tashqi muhit bilan aloqada | T9: 0.115 | U9: 0.04 | Y9: Concrete | Z9: 1.92
C10: 5 | F10: =IFERROR(VLOOKUP(D10,$Y$7:$Z$33,2,FALSE),"") | H10: =IFERROR(IF(F10=0,0,E10/F10),"") | J10: 5 | M10: =IFERROR(VLOOKUP(K10,$Y$7:$Z$46,2,FALSE),"") | O10: =IFERROR(IF(M10=0,0,L10/M10),"") | Q10: Isitilmagan makon ostidagi shift | T10: 0.115 | U10: 0.083 | Y10: Concrete mixed with EPS (G-Sort) | Z10: 0.07
C11: 6 | F11: =IFERROR(VLOOKUP(D11,$Y$7:$Z$46,2,FALSE),"") | H11: =IFERROR(IF(F11=0,0,E11/F11),"") | J11: 6 | K11: Mineral wool MW | L11: 0.1 | M11: =IFERROR(VLOOKUP(K11,$Y$7:$Z$46,2,FALSE),"") -> 0.038 | O11: =IFERROR(IF(M11=0,0,L11/M11),"") -> 2.6315789 | Q11: Ochiq maydon ustidagi pol | T11: 0.115 | U11: 0.04 | Y11: Concrete with stones | Z11: 1.74
J12: 7 | K12: Ruberoid | L12: 0.005 | M12: =IFERROR(VLOOKUP(K12,$Y$7:$Z$46,2,FALSE),"") -> 0.17 | O12: =IFERROR(IF(M12=0,0,L12/M12),"") -> 0.029411765 | Y12: Polistirolbeton | Z12: 0.055
J13: 8 | K13: External plaster | L13: 0.005 | M13: =IFERROR(VLOOKUP(K13,$Y$7:$Z$46,2,FALSE),"") -> 0.76 | O13: =IFERROR(IF(M13=0,0,L13/M13),"") -> 0.0065789474
C14: Total | E14: =SUM(E6:E11) -> 0.402 | H14: =SUM(H6:H11) -> 0.57203008 | J14: Total | L14: =SUM(L6:L13) -> 0.512 | O14: =SUM(O6:O13) -> 3.2395997 | Q14: Isitilgan maydon ustidagi pol | T14: 0.115 | U14: 0.166 | Y14: Concrete with expanded clay | Z14: 0.52
C15: Thermal resistance of interior surface | F15: Rint | G15: [m²K/W] | H15: =T6 -> 0.115 | J15: Thermal resistance of interior surface | M15: Rint | N15: [m²K/W] | O15: =T6 -> 0.115 | Q15: Yer bilan aloqada pol | T15: 2.1 | U15: 0 | Y15: Aerated concrete (YTONG) | Z15: 0.41
C16: Thermal resistance of exterior surface | F16: Rext | G16: [m²K/W] | H16: =U6 -> 0.04 | J16: Thermal resistance of exterior surface | M16: Rext | N16: [m²K/W] | O16: =U6 -> 0.04 | Y16: Aggregated slug (from boilers) | Z16: 0.76
C17: Heat transfer coefficient (U value) | G17: [W/m²K] | H17: =1/(H16+H15+H14) -> 1.3754589 | J17: Heat transfer coefficient (U value) | N17: [W/m²K] | O17: =1/(O16+O15+O14) -> 0.29458554 | Y17: Ruberoid | Z17: 0.17
Y18: Bitumen polimeric materials | Z18: 0.27
Y19: Wood (pine) | Z19: 0.29
Y20: Mosaic | Z20: 1.74
Y21: Marble | Z21: 2.91
Y22: Granit | Z22: 3.49
Y23: Concrete/sand mix | Z23: 0.76
Y24: Limestone | Z24: 0.73
Y25: Bricks | Z25: 0.7
Y26: Hollow bricks | Z26: 0.58
Y27: Linoleum | Z27: 0.35
Y28: Expanded clay | Z28: 0.17
Y29: Tile | Z29: 1.1
Y30: Clay layer with straw | Z30: 0.65
R31: roof | Y31: Expanded polysterene EPS | Z31: 0.038
Y32: Extruded polysterene XPS | Z32: 0.035
C33: Calculation of Uvalue for external socle before renovation (Socle1)(heated space) | J33: Calculation of Uvalue for external socle after renovation (Socle1)(heated space) | R33: floor | Y33: Mineral wool MW | Z33: 0.038
C34: Layers | E34: Thickness | F34: Thermal conductivity | H34: Thermal resistance | J34: Layers | L34: Thickness | M34: Thermal conductivity | O34: Thermal resistance | Y34: Magnesium oxide plate | Z34: 0.21
Y35: Concrete hollow panels | Z35: 1.295 | AA35: Bo'shliqli beton panel 220mm
E36: [m] | F36: [W/mK] | H36: [m²K/W] | L36: [m] | M36: [W/mK] | O36: [m²K/W] | Y36: Decorative stone | Z36: 2.1
C37: 1 | D37: Concrete with stones | E37: 0.6 | F37: =IFERROR(VLOOKUP(D37,$Y$7:$Z$46,2,FALSE),"") -> 1.74 | H37: =IFERROR(IF(F37=0,0,E37/F37),"") -> 0.34482759 | J37: 1 | K37: Concrete with stones | L37: 0.6 | M37: =IFERROR(VLOOKUP(K37,$Y$7:$Z$46,2,FALSE),"") -> 1.74 | O37: =IFERROR(IF(M37=0,0,L37/M37),"") -> 0.34482759 | Y37: Sintipon prokladka | Z37: 0.04
C38: 2 | D38: Concrete/sand mix | E38: 0.02 | F38: =IFERROR(VLOOKUP(D38,$Y$7:$Z$46,2,FALSE),"") -> 0.76 | H38: =IFERROR(IF(F38=0,0,E38/F38),"") -> 0.026315789 | J38: 2 | K38: Concrete/sand mix | L38: 0.02 | M38: =IFERROR(VLOOKUP(K38,$Y$7:$Z$46,2,FALSE),"") -> 0.76 | O38: =IFERROR(IF(M38=0,0,L38/M38),"") -> 0.026315789 | Y38: Gidro-bugʻ izolyatsiyasi (Ustki) | Z38: 0.4
C39: 3 | D39: Decorative stone | E39: 0.03 | F39: =IFERROR(VLOOKUP(D39,$Y$7:$Z$46,2,FALSE),"") -> 2.1 | H39: =IFERROR(IF(F39=0,0,E39/F39),"") -> 0.014285714 | J39: 3 | K39: Decorative stone | L39: 0.03 | M39: =IFERROR(VLOOKUP(K39,$Y$7:$Z$46,2,FALSE),"") -> 2.1 | O39: =IFERROR(IF(M39=0,0,L39/M39),"") -> 0.014285714 | Y39: Tunika shifer | Z39: 0.01
C40: 4 | F40: =IFERROR(VLOOKUP(D40,$Y$7:$Z$46,2,FALSE),"") | H40: =IFERROR(IF(F40=0,0,E40/F40),"") | J40: 4 | K40: Mineral wool MW | L40: 0.1 | M40: =IFERROR(VLOOKUP(K40,$Y$7:$Z$46,2,FALSE),"") -> 0.038 | O40: =IFERROR(IF(M40=0,0,L40/M40),"") -> 2.6315789 | Y40: Pol taxta | Z40: 0.29
C41: 5 | F41: =IFERROR(VLOOKUP(D41,$Y$7:$Z$33,2,FALSE),"") | H41: =IFERROR(IF(F41=0,0,E41/F41),"") | J41: 5 | K41: Clay layer with straw | L41: 0.004 | M41: =IFERROR(VLOOKUP(K41,$Y$7:$Z$33,2,FALSE),"") -> 0.65 | O41: =IFERROR(IF(M41=0,0,L41/M41),"") -> 0.0061538462 | Y41: Gips (Гипс) | Z41: 0.35
C42: 6 | F42: =IFERROR(VLOOKUP(D42,$Y$7:$Z$46,2,FALSE),"") | H42: =IFERROR(IF(F42=0,0,E42/F42),"") | J42: 6 | K42: External plaster | L42: 0.003 | M42: =IFERROR(VLOOKUP(K42,$Y$7:$Z$46,2,FALSE),"") -> 0.76 | O42: =IFERROR(IF(M42=0,0,L42/M42),"") -> 0.0039473684 | Y42: Gipsokarton (Гипсокартон) | Z42: 0.19
C43: Total | E43: =SUM(E37:E42) -> 0.65 | H43: =SUM(H37:H42) -> 0.38542909 | J43: Total | L43: =SUM(L37:L42) -> 0.757 | O43: =SUM(O37:O42) -> 3.0271093 | Y43: Tsement-qum qorishmasi | Z43: 0.76
C44: Thermal resistance of interior surface | F44: Rint | G44: [m²K/W] | H44: =T6 -> 0.115 | J44: Thermal resistance of interior surface | M44: Rint | N44: [m²K/W] | O44: =H44 -> 0.115 | Y44: Ohak-qum qorishmasi | Z44: 0.7
C45: Thermal resistance of exterior surface | F45: Rext | G45: [m²K/W] | H45: =U6 -> 0.04 | J45: Thermal resistance of exterior surface | M45: Rext | N45: [m²K/W] | O45: =H45 -> 0.04 | Y45: Parket, laminat, linoleum | Z45: 0.38
C46: Heat transfer coefficient (U value) | G46: [W/m²K] | H46: =1/(H45+H44+H43) -> 1.8503815 | J46: Heat transfer coefficient (U value) | N46: [W/m²K] | O46: =1/(O45+O44+O43) -> 0.31425697 | Y46: Mineral wool MW 150 | Z46: 0.22
C63: Calculation of Uvalue for external socle before renovation (Socle2) | J63: Calculation of Uvalue for external socle before renovation (Socle2)
C64: Layers | E64: Thickness | F64: Thermal conductivity | H64: Thermal resistance | J64: Layers | L64: Thickness | M64: Thermal conductivity | O64: Thermal resistance
E66: [m] | F66: [W/mK] | H66: [m²K/W] | L66: [m] | M66: [W/mK] | O66: [m²K/W]
C67: 1 | D67: Concrete | E67: 0.6 | F67: =IFERROR(VLOOKUP(D67,$Y$7:$Z$46,2,FALSE),"") -> 1.92 | H67: =IFERROR(IF(F67=0,0,E67/F67),"") -> 0.3125 | J67: 1 | K67: Concrete | L67: 0.6 | M67: =IFERROR(VLOOKUP(K67,$Y$7:$Z$46,2,FALSE),"") -> 1.92 | O67: =IFERROR(IF(M67=0,0,L67/M67),"") -> 0.3125
C68: 2 | D68: Concrete/sand mix | E68: 0.03 | F68: =IFERROR(VLOOKUP(D68,$Y$7:$Z$46,2,FALSE),"") -> 0.76 | H68: =IFERROR(IF(F68=0,0,E68/F68),"") -> 0.039473684 | J68: 2 | K68: Concrete/sand mix | L68: 0.03 | M68: =IFERROR(VLOOKUP(K68,$Y$7:$Z$46,2,FALSE),"") -> 0.76 | O68: =IFERROR(IF(M68=0,0,L68/M68),"") -> 0.039473684
C69: 3 | D69: Concrete with stones | E69: 0.02 | F69: =IFERROR(VLOOKUP(D69,$Y$7:$Z$46,2,FALSE),"") -> 1.74 | H69: =IFERROR(IF(F69=0,0,E69/F69),"") -> 0.011494253 | J69: 3 | K69: Concrete with stones | L69: 0.02 | M69: =IFERROR(VLOOKUP(K69,$Y$7:$Z$46,2,FALSE),"") -> 1.74 | O69: =IFERROR(IF(M69=0,0,L69/M69),"") -> 0.011494253
C70: 4 | F70: =IFERROR(VLOOKUP(D70,$Y$7:$Z$33,2,FALSE),"") | H70: =IFERROR(IF(F70=0,0,E70/F70),"") | J70: 4 | K70: Mineral wool MW | L70: 0.1 | M70: =IFERROR(VLOOKUP(K70,$Y$7:$Z$33,2,FALSE),"") -> 0.038 | O70: =IFERROR(IF(M70=0,0,L70/M70),"") -> 2.6315789
C71: 5 | F71: =IFERROR(VLOOKUP(D71,$Y$7:$Z$33,2,FALSE),"") | H71: =IFERROR(IF(F71=0,0,E71/F71),"") | J71: 5 | K71: Clay layer with straw | L71: 0.004 | M71: =IFERROR(VLOOKUP(K71,$Y$7:$Z$33,2,FALSE),"") -> 0.65 | O71: =IFERROR(IF(M71=0,0,L71/M71),"") -> 0.0061538462
C72: 6 | F72: =IFERROR(VLOOKUP(D72,$Y$7:$Z$46,2,FALSE),"") | H72: =IFERROR(IF(F72=0,0,E72/F72),"") | J72: 6 | K72: External plaster | L72: 0.003 | M72: =IFERROR(VLOOKUP(K72,$Y$7:$Z$46,2,FALSE),"") -> 0.76 | O72: =IFERROR(IF(M72=0,0,L72/M72),"") -> 0.0039473684
C73: Total | E73: =SUM(E67:E72) -> 0.65 | H73: =SUM(H67:H72) -> 0.36346794 | J73: Total | L73: =SUM(L67:L72) -> 0.757 | O73: =SUM(O67:O72) -> 3.0051481
C74: Thermal resistance of interior surface | F74: Rint | G74: [m²K/W] | H74: =T8 -> 2.1 | J74: Thermal resistance of interior surface | M74: Rint | N74: [m²K/W] | O74: =H74 -> 2.1
C75: Thermal resistance of exterior surface | F75: Rext | G75: [m²K/W] | H75: =U15 -> 0 | J75: Thermal resistance of exterior surface | M75: Rext | N75: [m²K/W] | O75: =AB15 -> 0
C76: Heat transfer coefficient (U value) | G76: [W/m²K] | H76: =1/(H75+H74+H73) -> 0.40593181 | J76: Heat transfer coefficient (U value) | N76: [W/m²K] | O76: =1/(O75+O74+O73) -> 0.1958807
C78: Calculation of Uvalue for external roof before renovation (R1) | J78: Calculation of Uvalue for external roof after renovation (R1)
C79: Layers | E79: Thickness | F79: Thermal conductivity | H79: Thermal resistance | J79: Layers | L79: Thickness | M79: Thermal conductivity | O79: Thermal resistance
E81: [m] | F81: [W/mK] | H81: [m²K/W] | L81: [m] | M81: [W/mK] | O81: [m²K/W]
C82: 1 | D82: Internal plaster | E82: 0.01 | F82: =IFERROR(VLOOKUP(D82,$Y$7:$Z$46,2,FALSE),"") -> 0.7 | H82: =IFERROR(IF(F82=0,0,E82/F82),"") -> 0.014285714 | J82: 1 | K82: Internal plaster | L82: 0.01 | M82: =IFERROR(VLOOKUP(K82,$Y$7:$Z$46,2,FALSE),"") -> 0.7 | O82: =IFERROR(IF(M82=0,0,L82/M82),"") -> 0.014285714
C83: 2 | D83: Concrete hollow panels | E83: 0.22 | F83: =IFERROR(VLOOKUP(D83,$Y$7:$Z$46,2,FALSE),"") -> 1.295 | H83: =IFERROR(IF(F83=0,0,E83/F83),"") -> 0.16988417 | J83: 2 | K83: Concrete hollow panels | L83: 0.22 | M83: =IFERROR(VLOOKUP(K83,$Y$7:$Z$46,2,FALSE),"") -> 1.295 | O83: =IFERROR(IF(M83=0,0,L83/M83),"") -> 0.16988417
C84: 3 | D84: Concrete/sand mix | E84: 0.05 | F84: =IFERROR(VLOOKUP(D84,$Y$7:$Z$46,2,FALSE),"") -> 0.76 | H84: =IFERROR(IF(F84=0,0,E84/F84),"") -> 0.065789474 | J84: 3 | K84: Concrete/sand mix | L84: 0.05 | M84: =IFERROR(VLOOKUP(K84,$Y$7:$Z$46,2,FALSE),"") -> 0.76 | O84: =IFERROR(IF(M84=0,0,L84/M84),"") -> 0.065789474
C85: 4 | D85: Bitumen polimeric materials | E85: 0.01 | F85: =IFERROR(VLOOKUP(D85,$Y$7:$Z$33,2,FALSE),"") -> 0.27 | H85: =IFERROR(IF(F85=0,0,E85/F85),"") -> 0.037037037 | J85: 4 | K85: Bitumen polimeric materials | L85: 0.01 | M85: =IFERROR(VLOOKUP(K85,$Y$7:$Z$46,2,FALSE),"") -> 0.27 | O85: =IFERROR(IF(M85=0,0,L85/M85),"") -> 0.037037037
C86: 5 | F86: =IFERROR(VLOOKUP(D86,$Y$7:$Z$33,2,FALSE),"") | H86: =IFERROR(IF(F86=0,0,E86/F86),"") | J86: 5 | K86: Polistirolbeton | L86: 0.15 | M86: =IFERROR(VLOOKUP(K86,$Y$7:$Z$46,2,FALSE),"") -> 0.055 | O86: =IFERROR(IF(M86=0,0,L86/M86),"") -> 2.7272727
C87: 6 | F87: =IFERROR(VLOOKUP(D87,$Y$7:$Z$46,2,FALSE),"") | H87: =IFERROR(IF(F87=0,0,E87/F87),"") | J87: 6 | M87: =IFERROR(VLOOKUP(K87,$Y$7:$Z$46,2,FALSE),"") | O87: =IFERROR(IF(M87=0,0,L87/M87),"")
C88: Total | E88: =SUM(E82:E87) -> 0.29 | H88: =SUM(H82:H87) -> 0.28699639 | J88: Total | L88: =SUM(L82:L87) -> 0.44 | O88: =SUM(O82:O87) -> 3.0142691
C89: Thermal resistance of interior surface | F89: Rint | G89: [m²K/W] | H89: =T10 -> 0.115 | J89: Thermal resistance of interior surface | M89: Rint | N89: [m²K/W] | O89: =H89 -> 0.115
C90: Thermal resistance of exterior surface | F90: Rext | G90: [m²K/W] | H90: =U10 -> 0.083 | J90: Thermal resistance of exterior surface | M90: Rext | N90: [m²K/W] | O90: =H90 -> 0.083
C91: Heat transfer coefficient (U value) | G91: [W/m²K] | H91: =1/(H90+H89+H88) -> 2.061871 | J91: Heat transfer coefficient (U value) | N91: [W/m²K] | O91: =1/(O90+O89+O88) -> 0.31130642
C94: Calculation of Uvalue for external roof before renovation (R2) | J94: Calculation of Uvalue for external roof after renovation (R2)
C95: Layers | E95: Thickness | F95: Thermal conductivity | H95: Thermal resistance | J95: Layers | L95: Thickness | M95: Thermal conductivity | O95: Thermal resistance
E97: [m] | F97: [W/mK] | H97: [m²K/W] | L97: [m] | M97: [W/mK] | O97: [m²K/W]
C98: 1 | F98: =IFERROR(VLOOKUP(D98,$Y$7:$Z$46,2,FALSE),"") | H98: =IFERROR(IF(F98=0,0,E98/F98),"") | J98: 1 | M98: =IFERROR(VLOOKUP(K98,$Y$7:$Z$46,2,FALSE),"") | O98: =IFERROR(IF(M98=0,0,L98/M98),"")
C99: 2 | F99: =IFERROR(VLOOKUP(D99,$Y$7:$Z$46,2,FALSE),"") | H99: =IFERROR(IF(F99=0,0,E99/F99),"") | J99: 2 | M99: =IFERROR(VLOOKUP(K99,$Y$7:$Z$46,2,FALSE),"") | O99: =IFERROR(IF(M99=0,0,L99/M99),"")
C100: 3 | F100: =IFERROR(VLOOKUP(D100,$Y$7:$Z$46,2,FALSE),"") | H100: =IFERROR(IF(F100=0,0,E100/F100),"") | J100: 3 | M100: =IFERROR(VLOOKUP(K100,$Y$7:$Z$46,2,FALSE),"") | O100: =IFERROR(IF(M100=0,0,L100/M100),"")
C101: 4 | F101: =IFERROR(VLOOKUP(D101,$Y$7:$Z$33,2,FALSE),"") | H101: =IFERROR(IF(F101=0,0,E101/F101),"") | J101: 4 | M101: =IFERROR(VLOOKUP(K101,$Y$7:$Z$46,2,FALSE),"") | O101: =IFERROR(IF(M101=0,0,L101/M101),"")
C102: 5 | F102: =IFERROR(VLOOKUP(D102,$Y$7:$Z$46,2,FALSE),"") | H102: =IFERROR(IF(F102=0,0,E102/F102),"") | J102: 5 | M102: =IFERROR(VLOOKUP(K102,$Y$7:$Z$33,2,FALSE),"") | O102: =IFERROR(IF(M102=0,0,L102/M102),"")
C103: 6 | F103: =IFERROR(VLOOKUP(D103,$Y$7:$Z$46,2,FALSE),"") | H103: =IFERROR(IF(F103=0,0,E103/F103),"") | J103: 6 | M103: =IFERROR(VLOOKUP(K103,$Y$7:$Z$46,2,FALSE),"") | O103: =IFERROR(IF(M103=0,0,L103/M103),"")
C104: Total | E104: =SUM(E98:E103) -> 0 | H104: =SUM(H98:H103) -> 0 | J104: Total | L104: =SUM(L98:L103) -> 0 | O104: =SUM(O98:O103) -> 0
C105: Thermal resistance of interior surface | F105: Rint | G105: [m²K/W] | J105: Thermal resistance of interior surface | M105: Rint | N105: [m²K/W] | O105: =H105 -> 0
C106: Thermal resistance of exterior surface | F106: Rext | G106: [m²K/W] | J106: Thermal resistance of exterior surface | M106: Rext | N106: [m²K/W] | O106: =H106 -> 0
C107: Heat transfer coefficient (U value) | G107: [W/m²K] | H107: =1/(H106+H105+H104) -> #DIV/0! | J107: Heat transfer coefficient (U value) | N107: [W/m²K] | O107: =1/(O106+O105+O104) -> #DIV/0!
C108: Calculation of Uvalue for external floor before renovation (F1) | J108: Calculation of Uvalue for external floor after renovation (F1)
C109: Layers | E109: Thickness | F109: Thermal conductivity | H109: Thermal resistance | J109: Layers | L109: Thickness | M109: Thermal conductivity | O109: Thermal resistance
E111: [m] | F111: [W/mK] | H111: [m²K/W] | L111: [m] | M111: [W/mK] | O111: [m²K/W]
C112: 1 | D112: Concrete hollow panels | E112: 0.22 | F112: =IFERROR(VLOOKUP(D112,$Y$7:$Z$46,2,FALSE),"") -> 1.295 | H112: =IFERROR(IF(F112=0,0,E112/F112),"") -> 0.16988417 | J112: 1 | K112: Concrete hollow panels | L112: 0.22 | M112: =IFERROR(VLOOKUP(K112,$Y$7:$Z$46,2,FALSE),"") -> 1.295 | O112: =IFERROR(IF(M112=0,0,L112/M112),"") -> 0.16988417
C113: 2 | D113: Concrete/sand mix | E113: 0.05 | F113: =IFERROR(VLOOKUP(D113,$Y$7:$Z$46,2,FALSE),"") -> 0.76 | H113: =IFERROR(IF(F113=0,0,E113/F113),"") -> 0.065789474 | J113: 2 | K113: Concrete/sand mix | L113: 0.05 | M113: =IFERROR(VLOOKUP(K113,$Y$7:$Z$46,2,FALSE),"") -> 0.76 | O113: =IFERROR(IF(M113=0,0,L113/M113),"") -> 0.065789474
C114: 3 | H114: =IFERROR(IF(F114=0,0,E114/F114),"") -> 0 | J114: 3 | M114: =IFERROR(VLOOKUP(K114,$Y$7:$Z$46,2,FALSE),"") | O114: =IFERROR(IF(M114=0,0,L114/M114),"")
J115: 4 | M115: =IFERROR(VLOOKUP(K115,$Y$7:$Z$46,2,FALSE),"") | O115: =IFERROR(IF(M115=0,0,L115/M115),"")
C116: 4 | F116: =IFERROR(VLOOKUP(D116,$Y$7:$Z$46,2,FALSE),"") | H116: =IFERROR(IF(F116=0,0,E116/F116),"") | J116: 5 | M116: =IFERROR(VLOOKUP(K116,$Y$7:$Z$33,2,FALSE),"") | O116: =IFERROR(IF(M116=0,0,L116/M116),"") | P116: Gidro-bugʻ izolyatsiyasi (Ustki)
C117: 5 | F117: =IFERROR(VLOOKUP(D117,$Y$7:$Z$33,2,FALSE),"") | H117: =IFERROR(IF(F117=0,0,E117/F117),"") | J117: 6 | M117: =IFERROR(VLOOKUP(K117,$Y$7:$Z$46,2,FALSE),"") | O117: =IFERROR(IF(M117=0,0,L117/M117),"")
C118: 6 | F118: =IFERROR(VLOOKUP(D118,$Y$7:$Z$46,2,FALSE),"") | H118: =IFERROR(IF(F118=0,0,E118/F118),"") | J118: 7 | M118: =IFERROR(VLOOKUP(K118,$Y$7:$Z$46,2,FALSE),"") | O118: =IFERROR(IF(M118=0,0,L118/M118),"")
C119: Total | E119: =SUM(E112:E118) -> 0.27 | H119: =SUM(H112:H118) -> 0.23567364 | J119: Total | L119: =SUM(L112:L118) -> 0.27 | O119: =SUM(O112:O118) -> 0.23567364
C120: Thermal resistance of interior surface | F120: Rint | G120: [m²K/W] | H120: =H74 -> 2.1 | J120: Thermal resistance of interior surface | M120: Rint | N120: [m²K/W] | O120: =H120 -> 2.1
C121: Thermal resistance of exterior surface | F121: Rext | G121: [m²K/W] | H121: =H75 -> 0 | J121: Thermal resistance of exterior surface | M121: Rext | N121: [m²K/W] | O121: =H121 -> 0
C122: Heat transfer coefficient (U value) | G122: [W/m²K] | H122: =1/(H121+H120+H119) -> 0.42814201 | J122: Heat transfer coefficient (U value) | N122: [W/m²K] | O122: =1/(O121+O120+O119) -> 0.42814201
C124: Calculation of Uvalue for external floor before renovation (F2) | J124: Calculation of Uvalue for external floor after renovation (F2)
C125: Layers | E125: Thickness | F125: Thermal conductivity | H125: Thermal resistance | J125: Layers | L125: Thickness | M125: Thermal conductivity | O125: Thermal resistance
...

Sheet Losses env. before
B2: Cumulative annual heat losses before renovation through building envelope
B4: Element | C4: In contact with | D4: Wall type | E4: Area | F4: U value | G4: Qtot
E5: [m²] | F5: [W/m²K] | G5: [kWh/y]
B6: Walls | C6: Environment | G6: =IF(D6=D42,SUM(E42:K42),0) -> 0
D7: =Envelope!AG104 -> W1 | E7: =Envelope!AH104 -> 1492.9 | F7: ='U-values'!H17 -> 1.3754589 | G7: =IF(D7=D43,SUM(E43:K44),0) -> 95776.559
D9: =Envelope!AG106 -> Socle 1. (heated space) | E9: =Envelope!AH106 -> 0 | F9: ='U-values'!H46 -> 1.8503815 | G9: =IF(D9=D45,SUM(E45:K45),0) -> 0
C11: Ground | D11: =Envelope!AG108 -> Socle 2 | E11: =Envelope!AH108 -> 0 | F11: ='U-values'!H76 -> 0.40593181 | G11: =IF(D11=D47,SUM(E47:K47),0) -> 0
C13: Total annual heat losses through walls | G13: =SUM(G6:G12) -> 95776.559
B14: Roof | C14: Environment | D14: =Envelope!AG123 -> R2 | E14: =Envelope!AH123 -> 0 | F14: ='U-values'!H107 -> #DIV/0!
C16: Semi-closed un-heated space
C18: Closed un-heated space | D18: =Envelope!AG122 -> R1 | E18: =Envelope!AH122 -> 1279.175 | F18: ='U-values'!H91 -> 2.061871 | G18: =IF(D18=D54,SUM(E53:K54),0) -> 123019.04
C19: Total annual heat losses through roof | G19: =SUM(G14:G18) -> 123019.04
B20: Floor | C20: Ground | G20: =IF(D20=D56,SUM(E56:K56),0) -> 0
C21: Closed un-heated basement | D21: =Envelope!AG115 -> F1 | E21: =Envelope!AH115 -> 1279.175 | F21: ='U-values'!H122 -> 0.42814201 | G21: =IF(D21=D57,SUM(E57:K57),0) -> 14809.505
C22: In contact with environment | D22: =Envelope!AG116 -> F2 | E22: =Envelope!AH116 -> 0
C23: Total annual heat losses through floor | G23: =SUM(G20:G22) -> 14809.505
B24: Windows and Doors | D24: =Envelope!AG86 -> Win1 | E24: =Envelope!AI86 -> 0 | F24: =Envelope!AH86 -> 2.56 | G24: =IF(D24=D60,SUM(E60:K60),0) -> 0
D25: =Envelope!AG87 -> Win2 | E25: =Envelope!AI87 -> 0 | F25: =Envelope!AH87 -> 2.78 | G25: =IF(D25=D61,SUM(E61:K61),0) -> 0
D26: =Envelope!AG88 -> Win3 | E26: =Envelope!AI88 -> 256.62 | F26: =Envelope!AH88 -> 2.94 | G26: =IF(D26=D62,SUM(E62:K62),0) -> 20401.429
G27: =IF(D27=D63,SUM(E63:K63),0) -> 0
D28: =Envelope!AG90 -> D1 | E28: =Envelope!AI90 -> 61.43 | F28: =Envelope!AH90 -> 3.5 | G28: =IF(D28=D64,SUM(E64:K64),0) -> 5813.9502
D29: =Envelope!AG91 -> D2 | E29: =Envelope!AI91 -> 0 | F29: =Envelope!AH91 -> 4 | G29: =IF(D29=D65,SUM(E65:K65),0) -> 0
D30: =Envelope!AG92 -> D3 | E30: =Envelope!AI92 -> 0 | F30: =Envelope!AH92 -> 5.88 | G30: =IF(D30=D66,SUM(E66:K66),0) -> 0
C31: Total annual heat losses through windows and doors | G31: =SUM(G24:G30) -> 26215.379
B32: Total annual heat losses through building envelope | G32: =G31+G23+G19+G13 -> 259820.49
B34: Monthly heat losses before renovation through building envelope | M34: Heating season monthly data for Hospitals placed in II Climatic zone
N35: 13.8 | O35: 8.5 | P35: 3.5 | Q35: 1.9 | R35: 3.9 | S35: 9.4 | T35: 15.5
M36: Month | N36: Oct | O36: Nov | P36: Dec | Q36: Jan | R36: Feb | S36: Mar | T36: Apr
M37: Average temp [°C] | N37: 12,4 | O37: 6,6 | P37: 1,2 | Q37: -0,1 | R37: 2,5 | S37: 8,6 | T37: 15,3
M38: Duration [days] | N38: 15 | O38: 27 | P38: 28 | Q38: 28 | R38: 25 | S38: 28 | T38: 12
E39: N | F39: O | G39: P | H39: Q Jan | I39: R | J39: S | K39: T | M39: Δt [°C] | N39: =Building_data!$D$9-'Losses env. before'!N37 -> 9.6 | O39: =Building_data!$D$9-'Losses env. before'!O37 -> 15.4 | P39: =Building_data!$D$9-'Losses env. before'!P37 -> 20.8 | Q39: =Building_data!$D$9-'Losses env. before'!Q37 -> 22.1 | R39: =Building_data!$D$9-'Losses env. before'!R37 -> 19.5 | S39: =Building_data!$D$9-'Losses env. before'!S37 -> 13.4 | T39: =Building_data!$D$9-'Losses env. before'!T37 -> 6.7
B40: Element | C40: In contact with | D40: Wall type | E40: Q Oct | F40: Q Nov | G40: Q Dec | H40: Q Jan | I40: Q Feb | J40: Q Mar | K40: Q Apr | M40: Duration [h] | N40: =N38*Building_data!$D$14 -> 150 | O40: =O38*Building_data!$D$14 -> 270 | P40: =P38*Building_data!$D$14 -> 280 | Q40: =Q38*Building_data!$D$14 -> 280 | R40: =R38*Building_data!$D$14 -> 250 | S40: =S38*Building_data!$D$14 -> 280 | T40: =T38*Building_data!$D$14 -> 120
E41: [kWh/month] | F41: [kWh/month] | G41: [kWh/month] | H41: [kWh/month] | I41: [kWh/month] | J41: [kWh/month] | K41: [kWh/month]
B42: Walls | C42: Environment | D42: =D6 -> 0 | E42: =($E$6*$F$6*N39*N40)/1000 -> 0 | F42: =($E$6*$F$6*O39*O40)/1000 -> 0 | G42: =($E$6*$F$6*P39*P40)/1000 -> 0 | H42: =($E$6*$F$6*Q39*Q40)/1000 -> 0 | I42: =($E$6*$F$6*R39*R40)/1000 -> 0 | J42: =($E$6*$F$6*S39*S40)/1000 -> 0 | K42: =($E$6*$F$6*T39*T40)/1000 -> 0 | M42: Month | N42: Oct | O42: Nov | P42: Dec | Q42: Jan | R42: Feb | S42: Mar | T42: Apr
D43: =D7 -> W1 | E43: =($E$7*$F$7*N39*N40)/1000 -> 2956.9286 | F43: =($E$7*$F$7*O39*O40)/1000 -> 8538.1312 | G43: =($E$7*$F$7*P39*P40)/1000 -> 11959.133 | H43: =($E$7*$F$7*Q39*Q40)/1000 -> 12706.579 | I43: =($E$7*$F$7*R39*R40)/1000 -> 10010.435 | J43: =($E$7*$F$7*S39*S40)/1000 -> 7704.4417 | K43: =($E$7*$F$7*T39*T40)/1000 -> 1650.9518 | M43: Average temp [°C] | N43: 12,4 | O43: 6,6 | P43: 1,2 | Q43: -0,1 | R43: 2,5 | S43: 8,6 | T43: 15,3
D44: W1 | E44: =($E$7*$F$7*N45*N46)/1000 -> 689.95 | F44: =($E$7*$F$7*O45*O46)/1000 -> 5743.8337 | G44: =($E$7*$F$7*P45*P46)/1000 -> 10303.253 | H44: =($E$7*$F$7*Q45*Q46)/1000 -> 11349.677 | I44: =($E$7*$F$7*R45*R46)/1000 -> 8265.026 | J44: =($E$7*$F$7*S45*S46)/1000 -> 4346.685 | K44: =($E$7*$F$7*T45*T46)/1000 -> -448.4675 | M44: Duration [days] | N44: 15 | O44: 27 | P44: 28 | Q44: 28 | R44: 25 | S44: 28 | T44: 12
D45: =D9 -> Socle 1. (heated space) | E45: =($E$9*$F$9*N39*N40)/1000 -> 0 | F45: =($E$9*$F$9*O39*O40)/1000 -> 0 | G45: =($E$9*$F$9*P39*P40)/1000 -> 0 | H45: =($E$9*$F$9*Q39*Q40)/1000 -> 0 | I45: =($E$9*$F$9*R39*R40)/1000 -> 0 | J45: =($E$9*$F$9*S39*S40)/1000 -> 0 | K45: =($E$9*$F$9*T39*T40)/1000 -> 0 | M45: Δt [°C] | N45: =Building_data!$D8-'Losses env. before'!N43 -> 1.6 | O45: =Building_data!$D8-'Losses env. before'!O43 -> 7.4 | P45: =Building_data!$D8-'Losses env. before'!P43 -> 12.8 | Q45: =Building_data!$D8-'Losses env. before'!Q43 -> 14.1 | R45: =Building_data!$D8-'Losses env. before'!R43 -> 11.5 | S45: =Building_data!$D8-'Losses env. before'!S43 -> 5.4 | T45: =Building_data!$D8-'Losses env. before'!T43 -> -1.3
D46: =D10 -> 0 | E46: =($E$10*$F$10*N39*N40)/1000 -> 0 | F46: =($E$10*$F$10*O39*O40)/1000 -> 0 | G46: =($E$10*$F$10*P39*P40)/1000 -> 0 | H46: =($E$10*$F$10*Q39*Q40)/1000 -> 0 | I46: =($E$10*$F$10*R39*R40)/1000 -> 0 | J46: =($E$10*$F$10*S39*S40)/1000 -> 0 | K46: =($E$10*$F$10*T39*T40)/1000 -> 0 | M46: Duration [h] | N46: =N44*Building_data!$D$13 -> 210 | O46: =O44*Building_data!$D$13 -> 378 | P46: =P44*Building_data!$D$13 -> 392 | Q46: =Q44*Building_data!$D$13 -> 392 | R46: =R44*Building_data!$D$13 -> 350 | S46: =S44*Building_data!$D$13 -> 392 | T46: =T44*Building_data!$D$13 -> 168
C47: Ground | D47: =D11 -> Socle 2 | E47: =($E$11*$F$11*N39*N40)/1000 -> 0 | F47: =($E$11*$F$11*O39*O40)/1000 -> 0 | G47: =($E$11*$F$11*P39*P40)/1000 -> 0 | H47: =($E$11*$F$11*Q39*Q40)/1000 -> 0 | I47: =($E$11*$F$11*R39*R40)/1000 -> 0 | J47: =($E$11*$F$11*S39*S40)/1000 -> 0 | K47: =($E$11*$F$11*T39*T40)/1000 -> 0
C48: Closed un-heated space | D48: =D12 -> 0 | E48: =($E$12*$F$12*N39*N40)/1000 -> 0 | F48: =($E$12*$F$12*O39*O40)/1000 -> 0 | G48: =($E$12*$F$12*P39*P40)/1000 -> 0 | H48: =($E$12*$F$12*Q39*Q40)/1000 -> 0 | I48: =($E$12*$F$12*R39*R40)/1000 -> 0 | J48: =($E$12*$F$12*S39*S40)/1000 -> 0 | K48: =($E$12*$F$12*T39*T40)/1000 -> 0
C49: Total monthly heat losses through walls | E49: =SUM(E42:E48) -> 3646.8786 | F49: =SUM(F42:F48) -> 14281.965 | G49: =SUM(G42:G48) -> 22262.387 | H49: =SUM(H42:H48) -> 24056.257 | I49: =SUM(I42:I48) -> 18275.461 | J49: =SUM(J42:J48) -> 12051.127 | K49: =SUM(K42:K48) -> 1202.4843
B50: Roof | C50: Environment | D50: R2
F51: =($E$15*$F$15*O39*O40)/1000 -> 0 | G51: =($E$15*$F$15*P39*P40)/1000 -> 0 | H51: =($E$15*$F$15*Q39*Q40)/1000 -> 0 | I51: =($E$15*$F$15*R39*R40)/1000 -> 0 | J51: =($E$15*$F$15*S39*S40)/1000 -> 0 | K51: =($E$15*$F$15*T39*T40)/1000 -> 0
C52: Semi-closed un-heated space | D52: =D16 -> 0 | F52: =($E$16*$F$16*O39*O40)/1000 -> 0 | G52: =($E$16*$F$16*P39*P40)/1000 -> 0 | H52: =($E$16*$F$16*Q39*Q40)/1000 -> 0 | I52: =($E$16*$F$16*R39*R40)/1000 -> 0 | J52: =($E$16*$F$16*S39*S40)/1000 -> 0 | K52: =($E$16*$F$16*T39*T40)/1000 -> 0
C53: Closed un-heated space | E53: =($E$18*$F$18*N45*N46)/1000 -> 886.19793 | F53: =($E$18*$F$18*O45*O46)/1000 -> 7377.5977 | G53: =($E$18*$F$18*P45*P46)/1000 -> 13233.889 | H53: =($E$18*$F$18*Q45*Q46)/1000 -> 14577.956 | I53: =($E$18*$F$18*R45*R46)/1000 -> 10615.913 | J53: =($E$18*$F$18*S45*S46)/1000 -> 5583.0469 | K53: =($E$18*$F$18*T45*T46)/1000 -> -576.02865
D54: R1 | E54: =($E$18*$F$18*N39*N40)/1000 -> 3797.9911 | F54: =($E$18*$F$18*O39*O40)/1000 -> 10966.699 | G54: =($E$18*$F$18*P39*P40)/1000 -> 15360.764 | H54: =($E$18*$F$18*Q39*Q40)/1000 -> 16320.812 | I54: =($E$18*$F$18*R39*R40)/1000 -> 12857.782 | J54: =($E$18*$F$18*S39*S40)/1000 -> 9895.8769 | K54: =($E$18*$F$18*T39*T40)/1000 -> 2120.545
C55: Total monthly heat losses through roof | E55: =SUM(E50:E54) -> 4684.189 | F55: =SUM(F50:F54) -> 18344.297 | G55: =SUM(G50:G54) -> 28594.653 | H55: =SUM(H50:H54) -> 30898.768 | I55: =SUM(I50:I54) -> 23473.695 | J55: =SUM(J50:J54) -> 15478.924 | K55: =SUM(K50:K54) -> 1544.5164
B56: Floor | C56: Ground | E56: =($E$20*$F$20*N39*N40)/1000 -> 0 | F56: =($E$20*$F$20*O39*O40)/1000 -> 0 | G56: =($E$20*$F$20*P39*P40)/1000 -> 0 | H56: =($E$20*$F$20*Q39*Q40)/1000 -> 0 | I56: =($E$20*$F$20*R39*R40)/1000 -> 0 | J56: =($E$20*$F$20*S39*S40)/1000 -> 0 | K56: =($E$20*$F$20*T39*T40)/1000 -> 0
C57: Closed un-heated basement | D57: F1 | E57: =($E$21*$F$21*N39*N40)/1000 -> 788.64271 | F57: =($E$21*$F$21*O39*O40)/1000 -> 2277.2058 | G57: =($E$21*$F$21*P39*P40)/1000 -> 3189.6216 | H57: =($E$21*$F$21*Q39*Q40)/1000 -> 3388.973 | I57: =($E$21*$F$21*R39*R40)/1000 -> 2669.8842 | J57: =($E$21*$F$21*S39*S40)/1000 -> 2054.8524 | K57: =($E$21*$F$21*T39*T40)/1000 -> 440.32552
C58: In contact with environment | D58: F2 | E58: =($E$22*$F$22*N39*N40)/1000 -> 0 | F58: =($E$22*$F$22*O39*O40)/1000 -> 0 | G58: =($E$22*$F$22*P39*P40)/1000 -> 0 | H58: =($E$22*$F$22*Q39*Q40)/1000 -> 0 | I58: =($E$22*$F$22*R39*R40)/1000 -> 0 | J58: =($E$22*$F$22*S39*S40)/1000 -> 0 | K58: =($E$22*$F$22*T39*T40)/1000 -> 0
C59: Total monthly heat losses through floor | E59: =SUM(E56:E58) -> 788.64271 | F59: =SUM(F56:F58) -> 2277.2058 | G59: =SUM(G56:G58) -> 3189.6216 | H59: =SUM(H56:H58) -> 3388.973 | I59: =SUM(I56:I58) -> 2669.8842 | J59: =SUM(J56:J58) -> 2054.8524 | K59: =SUM(K56:K58) -> 440.32552
B60: Windows and Doors | D60: =D24 -> Win1 | E60: =($E$24*$F$24*N39*N40)/1000 -> 0 | F60: =($E$24*$F$24*O39*O40)/1000 -> 0 | G60: =($E$24*$F$24*P39*P40)/1000 -> 0 | H60: =($E$24*$F$24*Q39*Q40)/1000 -> 0 | I60: =($E$24*$F$24*R39*R40)/1000 -> 0 | J60: =($E$24*$F$24*S39*S40)/1000 -> 0 | K60: =($E$24*$F$24*T39*T40)/1000 -> 0
D61: =D25 -> Win2 | E61: =($E$25*$F$25*N39*N40)/1000 -> 0 | F61: =($E$25*$F$25*O39*O40)/1000 -> 0 | G61: =($E$25*$F$25*P39*P40)/1000 -> 0 | H61: =($E$25*$F$25*Q39*Q40)/1000 -> 0 | I61: =($E$25*$F$25*R39*R40)/1000 -> 0 | J61: =($E$25*$F$25*S39*S40)/1000 -> 0 | K61: =($E$25*$F$25*T39*T40)/1000 -> 0
D62: =D26 -> Win3 | E62: =($E$26*$F$26*N39*N40)/1000 -> 1086.4264 | F62: =($E$26*$F$26*O39*O40)/1000 -> 3137.0563 | G62: =($E$26*$F$26*P39*P40)/1000 -> 4393.9913 | H62: =($E$26*$F$26*Q39*Q40)/1000 -> 4668.6158 | I62: =($E$26*$F$26*R39*R40)/1000 -> 3678.0062 | J62: =($E$26*$F$26*S39*S40)/1000 -> 2830.7444 | K62: =($E$26*$F$26*T39*T40)/1000 -> 606.58809
D63: =D27 -> 0 | E63: =($E$27*$F$27*N39*N40)/1000 -> 0 | F63: =($E$27*$F$27*O39*O40)/1000 -> 0 | G63: =($E$27*$F$27*P39*P40)/1000 -> 0 | H63: =($E$27*$F$27*Q39*Q40)/1000 -> 0 | I63: =($E$27*$F$27*R39*R40)/1000 -> 0 | J63: =($E$27*$F$27*S39*S40)/1000 -> 0 | K63: =($E$27*$F$27*T39*T40)/1000 -> 0
D64: =D28 -> D1 | E64: =($E$28*$F$28*N39*N40)/1000 -> 309.6072 | F64: =($E$28*$F$28*O39*O40)/1000 -> 893.99079 | G64: =($E$28*$F$28*P39*P40)/1000 -> 1252.1891 | H64: =($E$28*$F$28*Q39*Q40)/1000 -> 1330.4509 | I64: =($E$28*$F$28*R39*R40)/1000 -> 1048.1494 | J64: =($E$28*$F$28*S39*S40)/1000 -> 806.69876 | K64: =($E$28*$F$28*T39*T40)/1000 -> 172.86402
D65: =D29 -> D2 | E65: =($E$29*$F$29*N39*N40)/1000 -> 0 | F65: =($E$29*$F$29*O39*O40)/1000 -> 0 | G65: =($E$29*$F$29*P39*P40)/1000 -> 0 | H65: =($E$29*$F$29*Q39*Q40)/1000 -> 0 | I65: =($E$29*$F$29*R39*R40)/1000 -> 0 | J65: =($E$29*$F$29*S39*S40)/1000 -> 0 | K65: =($E$29*$F$29*T39*T40)/1000 -> 0
D66: =D30 -> D3 | E66: =($E$30*$F$30*N39*N40)/1000 -> 0 | F66: =($E$30*$F$30*O39*O40)/1000 -> 0 | G66: =($E$30*$F$30*P39*P40)/1000 -> 0 | H66: =($E$30*$F$30*Q39*Q40)/1000 -> 0 | I66: =($E$30*$F$30*R39*R40)/1000 -> 0 | J66: =($E$30*$F$30*S39*S40)/1000 -> 0 | K66: =($E$30*$F$30*T39*T40)/1000 -> 0
C67: Total monthly heat losses through openings | E67: =SUM(E60:E66) -> 1396.0336 | F67: =SUM(F60:F66) -> 4031.0471 | G67: =SUM(G60:G66) -> 5646.1805 | H67: =SUM(H60:H66) -> 5999.0667 | I67: =SUM(I60:I66) -> 4726.1555 | J67: =SUM(J60:J66) -> 3637.4432 | K67: =SUM(K60:K66) -> 779.45211
B68: Total monthly heat losses through building envelope | E68: =E67+E59+E55+E49 -> 10515.744 | F68: =F67+F59+F55+F49 -> 38934.515 | G68: =G67+G59+G55+G49 -> 59692.842 | H68: =H67+H59+H55+H49 -> 64343.064 | I68: =I67+I59+I55+I49 -> 49145.196 | J68: =J67+J59+J55+J49 -> 33222.346 | K68: =K67+K59+K55+K49 -> 3966.7783

Sheet Losses env. after
B2: Cumulative annual heat losses after renovation through building envelope
B4: Element | C4: In contact with | D4: Wall type | E4: Area | F4: U value | G4: Qtot
E5: [m²] | F5: [W/m²K] | G5: [kWh/y]
B6: Walls | C6: Environment | G6: =IF(D6=D38,SUM(E38:K38),0) -> 0
D7: ='Losses env. before'!D7 -> W1 | E7: ='Losses env. before'!E7 -> 1492.9 | F7: ='U-values'!O17 -> 0.29458554 | G7: =IF(D7=D39,SUM(E39:K40),0) -> 20512.71
D9: ='Losses env. before'!D9 -> Socle 1. (heated space) | E9: ='Losses env. before'!E9 -> 0 | F9: ='U-values'!O46 -> 0.31425697 | G9: =IF(D9=D41,SUM(E41:K41),0) -> 0
C11: Ground | D11: ='Losses env. before'!D11 -> Socle 2 | E11: ='Losses env. before'!E11 -> 0 | F11: ='U-values'!O76 -> 0.1958807 | G11: =IF(D11=D43,SUM(E43:K43),0) -> 0
C12: Closed un-heated space | G12: =IF(D12=D44,SUM(E44:K44),0) -> 0
C13: Total annual heat losses through walls | G13: =SUM(G6:G12) -> 20512.71
B14: Roof | C14: Environment | D14: R2 | E14: ='Losses env. before'!E14 -> 0
G15: =IF(D15=D47,SUM(E47:K47),0) -> 0
C16: Semi-closed un-heated space | G16: =IF(D16=D48,SUM(E48:K48),0) -> 0
C18: Closed un-heated space | D18: R1 | E18: ='Losses env. before'!E18 -> 1279.175 | F18: ='U-values'!O91 -> 0.31130642 | G18: =IF(D18=D50,SUM(E49:K50),0) -> 18573.721
C19: Total annual heat losses through roof | G19: =SUM(G14:G18) -> 18573.721
B20: Floor | C20: Ground | G20: =IF(D20=D52,SUM(E52:K52),0) -> 0
C21: Closed un-heated basement | D21: F1 | E21: ='Losses env. before'!E21 -> 1279.175 | F21: ='U-values'!O122 -> 0.42814201 | G21: =IF(D21=D53,SUM(E53:K53),0) -> 14809.505
C22: In contact with environment | D22: F2 | E22: ='Losses env. before'!E22 -> 0
C23: Total annual heat losses through floor | G23: =SUM(G20:G22) -> 14809.505
B24: Windows and Doors | D24: Win4 | E24: ='Losses env. before'!E24+'Losses env. before'!E25+'Losses env. before'!E26 -> 256.62 | F24: 1.5 | G24: =IF(D24=D56,SUM(E56:K56),0) -> 10408.892
G25: =IF(D25=D57,SUM(E57:K57),0) -> 0
D26: D4 | E26: ='Losses env. before'!E28+'Losses env. before'!E29+'Losses env. before'!E30 -> 61.43 | F26: 1.8 | G26: =IF(D26=D58,SUM(E58:K58),0) -> 2990.0315
C27: Total annual heat losses through windows and doors | G27: =SUM(G24:G26) -> 13398.924
B28: Total annual heat losses through building envelope | G28: =G27+G23+G19+G13 -> 67294.86
B30: Monthly heat losses before renovation through building envelope | M30: Heating season monthly data for Hospitals placed in II Climatic zone
M32: Month | N32: Oct | O32: Nov | P32: Dec | Q32: Jan | R32: Feb | S32: Mar | T32: Apr
M33: Average temp [°C] | N33: ='Losses env. before'!N37 -> 12,4 | O33: ='Losses env. before'!O37 -> 6,6 | P33: ='Losses env. before'!P37 -> 1,2 | Q33: ='Losses env. before'!Q37 -> -0,1 | R33: ='Losses env. before'!R37 -> 2,5 | S33: ='Losses env. before'!S37 -> 8,6 | T33: ='Losses env. before'!T37 -> 15,3
M34: Duration [days] | N34: 15 | O34: 27 | P34: 28 | Q34: 28 | R34: 25 | S34: 28 | T34: 12
E35: N | F35: O | G35: P | H35: Q Jan | I35: R | J35: S | K35: T | M35: Δt [°C] | N35: =Building_data!$D$9-'Losses env. before'!N37 -> 9.6 | O35: =Building_data!$D$9-'Losses env. before'!O37 -> 15.4 | P35: =Building_data!$D$9-'Losses env. before'!P37 -> 20.8 | Q35: =Building_data!$D$9-'Losses env. before'!Q37 -> 22.1 | R35: =Building_data!$D$9-'Losses env. before'!R37 -> 19.5 | S35: =Building_data!$D$9-'Losses env. before'!S37 -> 13.4 | T35: =Building_data!$D$9-'Losses env. before'!T37 -> 6.7
B36: Element | C36: In contact with | D36: Wall type | E36: Q Oct | F36: Q Nov | G36: Q Dec | H36: Q Jan | I36: Q Feb | J36: Q Mar | K36: Q Apr | M36: Duration [h] | N36: =N34*Building_data!$D$14 -> 150 | O36: =O34*Building_data!$D$14 -> 270 | P36: =P34*Building_data!$D$14 -> 280 | Q36: =Q34*Building_data!$D$14 -> 280 | R36: =R34*Building_data!$D$14 -> 250 | S36: =S34*Building_data!$D$14 -> 280 | T36: =T34*Building_data!$D$14 -> 120
E37: [kWh/month] | F37: [kWh/month] | G37: [kWh/month] | H37: [kWh/month] | I37: [kWh/month] | J37: [kWh/month] | K37: [kWh/month]
B38: Walls | C38: Environment | D38: =D6 -> 0 | E38: =($E$6*$F$6*N35*N36)/1000 -> 0 | F38: =($E$6*$F$6*O35*O36)/1000 -> 0 | G38: =($E$6*$F$6*P35*P36)/1000 -> 0 | H38: =($E$6*$F$6*Q35*Q36)/1000 -> 0 | I38: =($E$6*$F$6*R35*R36)/1000 -> 0 | J38: =($E$6*$F$6*S35*S36)/1000 -> 0 | K38: =($E$6*$F$6*T35*T36)/1000 -> 0 | M38: Month | N38: Oct | O38: Nov | P38: Dec | Q38: Jan | R38: Feb | S38: Mar | T38: Apr
D39: =D7 -> W1 | E39: =($E$7*$F$7*N35*N36)/1000 -> 633.29293 | F39: =($E$7*$F$7*O35*O36)/1000 -> 1828.6333 | G39: =($E$7*$F$7*P35*P36)/1000 -> 2561.3181 | H39: =($E$7*$F$7*Q35*Q36)/1000 -> 2721.4004 | I39: =($E$7*$F$7*R35*R36)/1000 -> 2143.9604 | J39: =($E$7*$F$7*S35*S36)/1000 -> 1650.0799 | K39: =($E$7*$F$7*T35*T36)/1000 -> 353.58855 | M39: Average temp [°C] | N39: ='Losses env. before'!N43 -> 12,4 | O39: ='Losses env. before'!O43 -> 6,6 | P39: ='Losses env. before'!P43 -> 1,2 | Q39: ='Losses env. before'!Q43 -> -0,1 | R39: ='Losses env. before'!R43 -> 2,5 | S39: ='Losses env. before'!S43 -> 8,6 | T39: ='Losses env. before'!T43 -> 15,3
D40: =D8 -> 0 | E40: =($E$7*$F$7*N41*N42)/1000 -> 147.76835 | F40: =($E$7*$F$7*O41*O42)/1000 -> 1230.1715 | G40: =($E$7*$F$7*P41*P42)/1000 -> 2206.674 | H40: =($E$7*$F$7*Q41*Q42)/1000 -> 2430.7893 | I40: =($E$7*$F$7*R41*R42)/1000 -> 1770.1417 | J40: =($E$7*$F$7*S41*S42)/1000 -> 930.9406 | K40: =($E$7*$F$7*T41*T42)/1000 -> -96.049427 | M40: Duration [days] | N40: 15 | O40: 27 | P40: 28 | Q40: 28 | R40: 25 | S40: 28 | T40: 12
D41: =D9 -> Socle 1. (heated space) | E41: =($E$9*$F$9*N35*N36)/1000 -> 0 | F41: =($E$9*$F$9*O35*O36)/1000 -> 0 | G41: =($E$9*$F$9*P35*P36)/1000 -> 0 | H41: =($E$9*$F$9*Q35*Q36)/1000 -> 0 | I41: =($E$9*$F$9*R35*R36)/1000 -> 0 | J41: =($E$9*$F$9*S35*S36)/1000 -> 0 | K41: =($E$9*$F$9*T35*T36)/1000 -> 0 | M41: Δt [°C] | N41: =Building_data!$D8-'Losses env. before'!N43 -> 1.6 | O41: =Building_data!$D8-'Losses env. before'!O43 -> 7.4 | P41: =Building_data!$D8-'Losses env. before'!P43 -> 12.8 | Q41: =Building_data!$D8-'Losses env. before'!Q43 -> 14.1 | R41: =Building_data!$D8-'Losses env. before'!R43 -> 11.5 | S41: =Building_data!$D8-'Losses env. before'!S43 -> 5.4 | T41: =Building_data!$D8-'Losses env. before'!T43 -> -1.3
D42: =D10 -> 0 | E42: =($E$10*$F$10*N35*N36)/1000 -> 0 | F42: =($E$10*$F$10*O35*O36)/1000 -> 0 | G42: =($E$10*$F$10*P35*P36)/1000 -> 0 | H42: =($E$10*$F$10*Q35*Q36)/1000 -> 0 | I42: =($E$10*$F$10*R35*R36)/1000 -> 0 | J42: =($E$10*$F$10*S35*S36)/1000 -> 0 | K42: =($E$10*$F$10*T35*T36)/1000 -> 0 | M42: Duration [h] | N42: =N40*Building_data!$D13 -> 210 | O42: =O40*Building_data!$D13 -> 378 | P42: =P40*Building_data!$D13 -> 392 | Q42: =Q40*Building_data!$D13 -> 392 | R42: =R40*Building_data!$D13 -> 350 | S42: =S40*Building_data!$D13 -> 392 | T42: =T40*Building_data!$D13 -> 168
C43: Ground | D43: =D11 -> Socle 2 | E43: =($E$11*$F$11*N35*N36)/1000 -> 0 | F43: =($E$11*$F$11*O35*O36)/1000 -> 0 | G43: =($E$11*$F$11*P35*P36)/1000 -> 0 | H43: =($E$11*$F$11*Q35*Q36)/1000 -> 0 | I43: =($E$11*$F$11*R35*R36)/1000 -> 0 | J43: =($E$11*$F$11*S35*S36)/1000 -> 0 | K43: =($E$11*$F$11*T35*T36)/1000 -> 0
C44: Closed un-heated space | D44: =D12 -> 0 | E44: =($E$12*$F$12*N35*N36)/1000 -> 0 | F44: =($E$12*$F$12*O35*O36)/1000 -> 0 | G44: =($E$12*$F$12*P35*P36)/1000 -> 0 | H44: =($E$12*$F$12*Q35*Q36)/1000 -> 0 | I44: =($E$12*$F$12*R35*R36)/1000 -> 0 | J44: =($E$12*$F$12*S35*S36)/1000 -> 0 | K44: =($E$12*$F$12*T35*T36)/1000 -> 0
C45: Total monthly heat losses through walls | E45: =SUM(E38:E44) -> 781.06128 | F45: =SUM(F38:F44) -> 3058.8048 | G45: =SUM(G38:G44) -> 4767.9921 | H45: =SUM(H38:H44) -> 5152.1898 | I45: =SUM(I38:I44) -> 3914.1021 | J45: =SUM(J38:J44) -> 2581.0205 | K45: =SUM(K38:K44) -> 257.53912
B46: Roof | C46: Environment | D46: =D14 -> R2 | E46: =($E$14*$F$14*N35*N36)/1000 -> 0 | F46: =($E$14*$F$14*O35*O36)/1000 -> 0 | G46: =($E$14*$F$14*P35*P36)/1000 -> 0 | H46: =($E$14*$F$14*Q35*Q36)/1000 -> 0 | I46: =($E$14*$F$14*R35*R36)/1000 -> 0 | J46: =($E$14*$F$14*S35*S36)/1000 -> 0 | K46: =($E$14*$F$14*T35*T36)/1000 -> 0
D47: =D15 -> 0 | E47: =($E$15*$F$15*N35*N36)/1000 -> 0 | F47: =($E$15*$F$15*O35*O36)/1000 -> 0 | G47: =($E$15*$F$15*P35*P36)/1000 -> 0 | H47: =($E$15*$F$15*Q35*Q36)/1000 -> 0 | I47: =($E$15*$F$15*R35*R36)/1000 -> 0 | J47: =($E$15*$F$15*S35*S36)/1000 -> 0 | K47: =($E$15*$F$15*T35*T36)/1000 -> 0
C48: Semi-closed un-heated space | D48: =D16 -> 0 | E48: =($E$16*$F$16*N35*N36)/1000 -> 0 | F48: =($E$16*$F$16*O35*O36)/1000 -> 0 | G48: =($E$16*$F$16*P35*P36)/1000 -> 0 | H48: =($E$16*$F$16*Q35*Q36)/1000 -> 0 | I48: =($E$16*$F$16*R35*R36)/1000 -> 0 | J48: =($E$16*$F$16*S35*S36)/1000 -> 0 | K48: =($E$16*$F$16*T35*T36)/1000 -> 0
C49: Closed un-heated space | D49: =D17 -> 0 | E49: =($E$18*$F$18*N41*N42)/1000 -> 133.80037 | F49: =($E$18*$F$18*O41*O42)/1000 -> 1113.8881 | G49: =($E$18*$F$18*P41*P42)/1000 -> 1998.0855 | H49: =($E$18*$F$18*Q41*Q42)/1000 -> 2201.0161 | I49: =($E$18*$F$18*R41*R42)/1000 -> 1602.8169 | J49: =($E$18*$F$18*S41*S42)/1000 -> 842.94234 | K49: =($E$18*$F$18*T41*T42)/1000 -> -86.970241
D50: =D18 -> R1 | E50: =($E$18*$F$18*N35*N36)/1000 -> 573.43016 | F50: =($E$18*$F$18*O35*O36)/1000 -> 1655.7796 | G50: =($E$18*$F$18*P35*P36)/1000 -> 2319.2064 | H50: =($E$18*$F$18*Q35*Q36)/1000 -> 2464.1568 | I50: =($E$18*$F$18*R35*R36)/1000 -> 1941.3 | J50: =($E$18*$F$18*S35*S36)/1000 -> 1494.1041 | K50: =($E$18*$F$18*T35*T36)/1000 -> 320.16517
C51: Total monthly heat losses through roof | E51: =SUM(E46:E50) -> 707.23053 | F51: =SUM(F46:F50) -> 2769.6677 | G51: =SUM(G46:G50) -> 4317.292 | H51: =SUM(H46:H50) -> 4665.1729 | I51: =SUM(I46:I50) -> 3544.117 | J51: =SUM(J46:J50) -> 2337.0465 | K51: =SUM(K46:K50) -> 233.19493
B52: Floor | C52: Ground | D52: =D20 -> 0 | E52: =($E$20*$F$20*N35*N36)/1000 -> 0 | F52: =($E$20*$F$20*O35*O36)/1000 -> 0 | G52: =($E$20*$F$20*P35*P36)/1000 -> 0 | H52: =($E$20*$F$20*Q35*Q36)/1000 -> 0 | I52: =($E$20*$F$20*R35*R36)/1000 -> 0 | J52: =($E$20*$F$20*S35*S36)/1000 -> 0 | K52: =($E$20*$F$20*T35*T36)/1000 -> 0
C53: Closed un-heated basement | D53: =D21 -> F1 | E53: =($E$21*$F$21*N35*N36)/1000 -> 788.64271 | F53: =($E$21*$F$21*O35*O36)/1000 -> 2277.2058 | G53: =($E$21*$F$21*P35*P36)/1000 -> 3189.6216 | H53: =($E$21*$F$21*Q35*Q36)/1000 -> 3388.973 | I53: =($E$21*$F$21*R35*R36)/1000 -> 2669.8842 | J53: =($E$21*$F$21*S35*S36)/1000 -> 2054.8524 | K53: =($E$21*$F$21*T35*T36)/1000 -> 440.32552
C54: In contact with environment | D54: =D22 -> F2 | E54: =($E$22*$F$22*N35*N36)/1000 -> 0 | F54: =($E$22*$F$22*O35*O36)/1000 -> 0 | G54: =($E$22*$F$22*P35*P36)/1000 -> 0 | H54: =($E$22*$F$22*Q35*Q36)/1000 -> 0 | I54: =($E$22*$F$22*R35*R36)/1000 -> 0 | J54: =($E$22*$F$22*S35*S36)/1000 -> 0 | K54: =($E$22*$F$22*T35*T36)/1000 -> 0
C55: Total monthly heat losses through floor | E55: =SUM(E52:E54) -> 788.64271 | F55: =SUM(F52:F54) -> 2277.2058 | G55: =SUM(G52:G54) -> 3189.6216 | H55: =SUM(H52:H54) -> 3388.973 | I55: =SUM(I52:I54) -> 2669.8842 | J55: =SUM(J52:J54) -> 2054.8524 | K55: =SUM(K52:K54) -> 440.32552
B56: Windows and Doors | D56: =D24 -> Win4 | E56: =($E$24*$F$24*N35*N36)/1000 -> 554.2992 | F56: =($E$24*$F$24*O35*O36)/1000 -> 1600.5389 | G56: =($E$24*$F$24*P35*P36)/1000 -> 2241.8323 | H56: =($E$24*$F$24*Q35*Q36)/1000 -> 2381.9468 | I56: =($E$24*$F$24*R35*R36)/1000 -> 1876.5338 | J56: =($E$24*$F$24*S35*S36)/1000 -> 1444.2574 | K56: =($E$24*$F$24*T35*T36)/1000 -> 309.48372
D57: =D25 -> 0 | E57: =($E$25*$F$25*N35*N36)/1000 -> 0 | F57: =($E$25*$F$25*O35*O36)/1000 -> 0 | G57: =($E$25*$F$25*P35*P36)/1000 -> 0 | H57: =($E$25*$F$25*Q35*Q36)/1000 -> 0 | I57: =($E$25*$F$25*R35*R36)/1000 -> 0 | J57: =($E$25*$F$25*S35*S36)/1000 -> 0 | K57: =($E$25*$F$25*T35*T36)/1000 -> 0
D58: =D26 -> D4 | E58: =($E$26*$F$26*N35*N36)/1000 -> 159.22656 | F58: =($E$26*$F$26*O35*O36)/1000 -> 459.76669 | G58: =($E$26*$F$26*P35*P36)/1000 -> 643.98298 | H58: =($E$26*$F$26*Q35*Q36)/1000 -> 684.23191 | I58: =($E$26*$F$26*R35*R36)/1000 -> 539.04825 | J58: =($E$26*$F$26*S35*S36)/1000 -> 414.87365 | K58: =($E$26*$F$26*T35*T36)/1000 -> 88.901496
C59: Total monthly heat losses through openings | E59: =SUM(E56:E58) -> 713.52576 | F59: =SUM(F56:F58) -> 2060.3056 | G59: =SUM(G56:G58) -> 2885.8153 | H59: =SUM(H56:H58) -> 3066.1788 | I59: =SUM(I56:I58) -> 2415.582 | J59: =SUM(J56:J58) -> 1859.131 | K59: =SUM(K56:K58) -> 398.38522
B60: Total monthly heat losses through building envelope | E60: =E59+E55+E51+E45 -> 2990.4603 | F60: =F59+F55+F51+F45 -> 10165.984 | G60: =G59+G55+G51+G45 -> 15160.721 | H60: =H59+H55+H51+H45 -> 16272.514 | I60: =I59+I55+I51+I45 -> 12543.685 | J60: =J59+J55+J51+J45 -> 8832.0504 | K60: =K59+K55+K51+K45 -> 1329.4448
L71: CAPEX
L72: Measure | M72: Description of works | N72: Type | O72: Unit cost [USD] | P72: Units | Q72: Total Investment [USD]
L73: Thermal insulation of walls | M73: Thermal insulation of external walls with MW of 100mm, density of at least 120kg/m³, λ max of 0.038 [W/(m∙K)] starting from 0.3m above the ground. | N73: W1, W2 | O73: 51 | P73: =Envelope!AH104+Envelope!AH105 -> 1492.9 | Q73: =O73*P73 -> 76137.9
M74: For socle part of the wall thermal insulation with XPS of 150mm, λ max of 0.035 [W/(m∙K)] starting from underground -0.7m up to 0.3m above the ground. Above insulation applied waterproofing layer. Visible part of socle covered with granite or decorative stone glued with metal mesh. | N74: Socle 1 | P74: =Envelope!AH107+Envelope!AH106 -> 104.015 | Q74: =O74*P74 -> 0
N75: =D11 -> Socle 2 | O75: 174 | P75: =Envelope!AH108 -> 0 | Q75: =O75*P75 -> 0
L76: Total for walls insulation | Q76: =SUM(Q73:Q75) -> 76137.9
L77: Thermal insulation of the roof | M77: Thermal insulation of the flat roof in contact with environment performed by removal of old layers, application of anticondens membrane, MW of 150mm thick and λ of MW 0.038 [W/(m∙K)], breathable membrane, concrete screw of 50mm thick with reinforce mesh, levelled to a smooth surface with angles for water drainage, rehabilitation of gatters, roof perimeter parapet, vent shafts and other, covered with PVC membrane of at least 2mm thick. Thermal insulation of the attic floor performed by removal of old layers, application of anticondens membrane, MW of 150mm thick and λ of MW 0.038 [W/(m∙K)], breathable membrane, concrete screw of 50mm thick with reinforce mesh. Flat roof above the attic cleaned, levelled to a smooth surface with angles for water drainage, rehabilitation of gatters, roof perimeter parapet, vent shafts and other, application of PVC membrane of at least 2mm thick | N77: =D14 -> R2 | P77: =Envelope!AH123 -> 0 | Q77: =O77*P77 -> 0
N78: =D18 -> R1 | O78: 12 | P78: =Envelope!AH122 -> 1279.175 | Q78: =O78*P78 -> 15350.1
L79: Total for roof insulation | Q79: =Q78+Q77 -> 15350.1
L80: Thermal insulation of floors | M80: Basement ceiling and floors in contact with environment insulation with 150 mm of MW with a thermal conductivity of λ = 0.038 W / (mK) by gluing and fixing with dowels the MW boards to the basement ceiling, covering MW boards with mesh and plaster, application of white paint for asthetic view of surface. | N80: F1, F2 | O80: 9 | P80: =Envelope!AH115+Envelope!AH116 -> 1279.175 | Q80: =O80*P80 -> 11512.575
L81: Replacement of windows and doors | M81: Replacing the existing openings with PVC framed, 5 camera, double glazed [4mm (Low-e < 0.1) - 20 Ar - 4mm] with maximum Uvalue for windows of 1.5 [W/m²K] and for doors 1.8 [W/m²K] with U shape metal reinforcement of at least 1.5mm. Doors to be equipped with automatic closing devices and aluminium dorstep. Vapor barrier membrane applied on the perimeter of PVC frame from inside and breathable membrane from outside. Insulation of perimeter of openings from inside and outside with high density MW of at least 40mm thick. | N81: Win4, D4. | O81: 255.75 | P81: 65 | Q81: =O81*P81 -> 16623.75

Sheet Ventilation losses
B2: Annual heat losses through natural ventilation before and after renovation
C3: Name of the Building | D3: Net heated volume | E3: Air exchange rate | F3: L | G3: Q
D4: [m³] | F4: [m³/h] | G4: [kWh/y]
B5: Before renovation | C5: =Envelope!B7 -> 3-DMTT | D5: =Envelope!M95 -> 7546.245 | E5: 0.4 | F5: =D5*E5 -> 3018.498 | G5: =SUM(G20:M20) -> 65614.086 | I5: wooden openings | J5: 0.5
F6: =D6*E6 -> 0 | G6: =SUM(G21:M21) -> 0 | I6: bad PVC | J6: 0.4
F7: =D7*E7 -> 0 | G7: =SUM(G22:M22) -> 0 | I7: new PVC | J7: 0.35
F8: =D8*E8 -> 0 | G8: =SUM(G22:M22) -> 0
C9: Total annual heat losses through natural ventilation and infiltration | G9: =SUM(G5:G8) -> 65614.086
B10: After renovation | C10: =C5 -> 3-DMTT | D10: =D5 -> 7546.245 | E10: 0.35 | F10: =D10*E10 -> 2641.1858 | G10: =SUM(G25:M25) -> 57412.325
C11: =C6 -> 0 | F11: =D11*E11 -> 0 | G11: =SUM(G26:M26) -> 0
F12: =D12*E12 -> 0 | G12: =SUM(G27:M27) -> 0
F13: =D13*E13 -> 0 | G13: =SUM(G28:M28) -> 0
C14: Total annual heat losses through natural ventilation and infiltration | G14: =SUM(G10:G13) -> 57412.325
B15: Heat savings from natural ventilation | G15: =G9-G14 -> 8201.7608
B17: Monthly heat losses through natural ventilation before and after renovation | O17: Heating season monthly data for Hospitals placed in II Climatic zone
C18: Name of the Building | D18: L | E18: cxƔ | F18: Conversion coeff. | G18: Q Oct | H18: Q Nov | I18: Q Dec | J18: Q Jan | K18: Q Feb | L18: Q Mar | M18: Q Apr
D19: [m³/h] | G19: [kWh/month] | H19: [kWh/month] | I19: [kWh/month] | J19: [kWh/month] | K19: [kWh/month] | L19: [kWh/month] | M19: [kWh/month] | O19: Month | P19: Oct | Q19: Nov | R19: Dec | S19: Jan | T19: Feb | U19: Mar | V19: Apr
B20: Before renovation | C20: =C5 -> 3-DMTT | D20: =F5 -> 3018.498 | E20: 0.288 | F20: 1.163 | G20: =(P$22*P$23*$D20*$E20*$F20)/1000 -> 3494.1121 | H20: =(Q$22*Q$23*$D20*$E20*$F20)/1000 -> 10089.249 | I20: =(R$22*R$23*$D20*$E20*$F20)/1000 -> 14131.742 | J20: =(S$22*S$23*$D20*$E20*$F20)/1000 -> 15014.976 | K20: =(T$22*T$23*$D20*$E20*$F20)/1000 -> 11829.025 | L20: =(U$22*U$23*$D20*$E20*$F20)/1000 -> 9104.1031 | M20: =(V$22*V$23*$D20*$E20*$F20)/1000 -> 1950.8792 | O20: Average temp [°C] | P20: ='Losses env. after'!N33 -> 12,4 | Q20: ='Losses env. after'!O33 -> 6,6 | R20: ='Losses env. after'!P33 -> 1,2 | S20: ='Losses env. after'!Q33 -> -0,1 | T20: ='Losses env. after'!R33 -> 2,5 | U20: ='Losses env. after'!S33 -> 8,6 | V20: ='Losses env. after'!T33 -> 15,3
C21: =C6 -> 0 | D21: =F6 -> 0 | E21: 0.288 | F21: 1.163 | G21: =(P$22*P$23*$D21*$E21*$F21)/1000 -> 0 | H21: =(Q$22*Q$23*$D21*$E21*$F21)/1000 -> 0 | I21: =(R$22*R$23*$D21*$E21*$F21)/1000 -> 0 | J21: =(S$22*S$23*$D21*$E21*$F21)/1000 -> 0 | K21: =(T$22*T$23*$D21*$E21*$F21)/1000 -> 0 | L21: =(U$22*U$23*$D21*$E21*$F21)/1000 -> 0 | M21: =(V$22*V$23*$D21*$E21*$F21)/1000 -> 0 | O21: Duration [days] | P21: 15 | Q21: 27 | R21: 28 | S21: 28 | T21: 25 | U21: 28 | V21: 12
D22: =F7 -> 0 | E22: 0.288 | F22: 1.163 | G22: =(P$22*P$23*$D22*$E22*$F22)/1000 -> 0 | H22: =(Q$22*Q$23*$D22*$E22*$F22)/1000 -> 0 | I22: =(R$22*R$23*$D22*$E22*$F22)/1000 -> 0 | J22: =(S$22*S$23*$D22*$E22*$F22)/1000 -> 0 | K22: =(T$22*T$23*$D22*$E22*$F22)/1000 -> 0 | L22: =(U$22*U$23*$D22*$E22*$F22)/1000 -> 0 | M22: =(V$22*V$23*$D22*$E22*$F22)/1000 -> 0 | O22: Δt [°C] | P22: ='Losses env. after'!N35 -> 9.6 | Q22: ='Losses env. after'!O35 -> 15.4 | R22: ='Losses env. after'!P35 -> 20.8 | S22: ='Losses env. after'!Q35 -> 22.1 | T22: ='Losses env. after'!R35 -> 19.5 | U22: ='Losses env. after'!S35 -> 13.4 | V22: ='Losses env. after'!T35 -> 6.7
D23: =F8 -> 0 | E23: 0.288 | F23: 1.163 | G23: =(P$22*P$23*$D23*$E23*$F23)/1000 -> 0 | H23: =(Q$22*Q$23*$D23*$E23*$F23)/1000 -> 0 | I23: =(R$22*R$23*$D23*$E23*$F23)/1000 -> 0 | J23: =(S$22*S$23*$D23*$E23*$F23)/1000 -> 0 | K23: =(T$22*T$23*$D23*$E23*$F23)/1000 -> 0 | L23: =(U$22*U$23*$D23*$E23*$F23)/1000 -> 0 | M23: =(V$22*V$23*$D23*$E23*$F23)/1000 -> 0 | O23: Duration [h] | P23: =P21*24 -> 360 | Q23: =Q21*24 -> 648 | R23: =R21*24 -> 672 | S23: =S21*24 -> 672 | T23: =T21*24 -> 600 | U23: =U21*24 -> 672 | V23: =V21*24 -> 288
C24: Total monthly heat losses through natural ventilation and infiltration | G24: =SUM(G20:G23) -> 3494.1121 | H24: =SUM(H20:H23) -> 10089.249 | I24: =SUM(I20:I23) -> 14131.742 | J24: =SUM(J20:J23) -> 15014.976 | K24: =SUM(K20:K23) -> 11829.025 | L24: =SUM(L20:L23) -> 9104.1031 | M24: =SUM(M20:M23) -> 1950.8792
B25: After renovation | C25: =C20 -> 3-DMTT | D25: =F10 -> 2641.1858 | E25: 0.288 | F25: 1.163 | G25: =(P$22*P$23*$D25*$E25*$F25)/1000 -> 3057.348 | H25: =(Q$22*Q$23*$D25*$E25*$F25)/1000 -> 8828.0925 | I25: =(R$22*R$23*$D25*$E25*$F25)/1000 -> 12365.274 | J25: =(S$22*S$23*$D25*$E25*$F25)/1000 -> 13138.104 | K25: =(T$22*T$23*$D25*$E25*$F25)/1000 -> 10350.397 | L25: =(U$22*U$23*$D25*$E25*$F25)/1000 -> 7966.0902 | M25: =(V$22*V$23*$D25*$E25*$F25)/1000 -> 1707.0193
C26: =C21 -> 0 | D26: =F11 -> 0 | E26: 0.288 | F26: 1.163 | G26: =(P$22*P$23*$D26*$E26*$F26)/1000 -> 0 | H26: =(Q$22*Q$23*$D26*$E26*$F26)/1000 -> 0 | I26: =(R$22*R$23*$D26*$E26*$F26)/1000 -> 0 | J26: =(S$22*S$23*$D26*$E26*$F26)/1000 -> 0 | K26: =(T$22*T$23*$D26*$E26*$F26)/1000 -> 0 | L26: =(U$22*U$23*$D26*$E26*$F26)/1000 -> 0 | M26: =(V$22*V$23*$D26*$E26*$F26)/1000 -> 0
D27: =F12 -> 0 | E27: 0.288 | F27: 1.163 | G27: =(P$22*P$23*$D27*$E27*$F27)/1000 -> 0 | H27: =(Q$22*Q$23*$D27*$E27*$F27)/1000 -> 0 | I27: =(R$22*R$23*$D27*$E27*$F27)/1000 -> 0 | J27: =(S$22*S$23*$D27*$E27*$F27)/1000 -> 0 | K27: =(T$22*T$23*$D27*$E27*$F27)/1000 -> 0 | L27: =(U$22*U$23*$D27*$E27*$F27)/1000 -> 0 | M27: =(V$22*V$23*$D27*$E27*$F27)/1000 -> 0
D28: =F13 -> 0 | E28: 0.288 | F28: 1.163 | G28: =(P$22*P$23*$D28*$E28*$F28)/1000 -> 0 | H28: =(Q$22*Q$23*$D28*$E28*$F28)/1000 -> 0 | I28: =(R$22*R$23*$D28*$E28*$F28)/1000 -> 0 | J28: =(S$22*S$23*$D28*$E28*$F28)/1000 -> 0 | K28: =(T$22*T$23*$D28*$E28*$F28)/1000 -> 0 | L28: =(U$22*U$23*$D28*$E28*$F28)/1000 -> 0 | M28: =(V$22*V$23*$D28*$E28*$F28)/1000 -> 0
C29: Total monthly heat losses through natural ventilation and infiltration | G29: =SUM(G25:G28) -> 3057.348 | H29: =SUM(H25:H28) -> 8828.0925 | I29: =SUM(I25:I28) -> 12365.274 | J29: =SUM(J25:J28) -> 13138.104 | K29: =SUM(K25:K28) -> 10350.397 | L29: =SUM(L25:L28) -> 7966.0902 | M29: =SUM(M25:M28) -> 1707.0193
B30: Monthly heat savings from natural ventilation | G30: =G24-G29 -> 436.76401 | H30: =H24-H29 -> 1261.1561 | I30: =I24-I29 -> 1766.4678 | J30: =J24-J29 -> 1876.872 | K30: =K24-K29 -> 1478.6281 | L30: =L24-L29 -> 1138.0129 | M30: =M24-M29 -> 243.8599
B34: Annual heat losses through mechanical ventilation before and after renovation
C35: Block/floor name | D35: Unit description | E35: No of people | F35: Fresh air per person | G35: VSUPPLY &/OR EXAHUST [m³/h] | H35: Heat recovery efficiency [%] | I35: Q [kWh/y]
F36: [m³/h/person]
B37: Before renovation | C37: =C5 -> 3-DMTT | D37: Mavjud egzoz ventilyatori | E37: =Building_data!D18 -> 418 | F37: 20 | G37: =F37*E37 -> 8360 | H37: 0 | I37: =SUM(J58:P58) -> 75718.365
I38: =SUM(J59:P59) -> 0
H39: 0 | I39: =SUM(J60:P60) -> 0
H40: 0 | I40: =SUM(J61:P61) -> 0
I41: =SUM(J62:P62) -> 0
C42: Annual heat losses through mechanical ventilation before renovation | I42: =SUM(I37:I41) -> 75718.365
C43: Annual electrical energy consumption for mechanical ventilation before renovation | I43: =Equipment!K35 -> 0
B44: After renovation | C44: =C37 -> 3-DMTT | I44: =SUM(J64:P64) -> 0
C45: =C38 -> 0 | D45: AHU's with heat recovery | E45: =Building_data!D18 -> 418 | F45: 20 | G45: =E45*F45 -> 8360 | H45: 0.85 | I45: =SUM(J65:P65) -> 11357.755
C46: =C39 -> 0 | D46: =Equipment!C85 -> 0 | G46: =G39 -> 0 | H46: =H39 -> 0 | I46: =SUM(J66:P66) -> 0
C47: =C40 -> 0 | D47: =D40 -> 0 | G47: =G40 -> 0 | H47: =H40 -> 0 | I47: =SUM(J67:P67) -> 0
C49: Annual heat losses through mechanical ventilation after renovation | I49: =SUM(I44:I48) -> 11357.755
C50: Annual electrical energy consumption for mechanical ventilation after renovation | I50: =Equipment!K85+Equipment!K86 -> 3424.256
B51: Annual electrical energy savings from mechanical ventilation | I51: =I43-I50 -> -3424.256
B52: Annual heat savings from mechanical ventilation | I52: =I42-I49 -> 64360.61
B53: Note: Fresh air per person of 80m3/h is assumed as an average value per hospital considered during the EA calculation. During the design phase, spaces as: surgery rooms, clean rooms, intensive care, x-ray etc. will be calculated separately according to the specific technological requirements.
B54: 20-30
B55: Monthly heat losses through mechanical ventilation before and after renovation
C56: Block/floor name | D56: Unit description | E56: VSUPPLY &/OR EXAHUST [m³/h] | F56: cxƔ | G56: Conversion coeff. | H56: Heat recovery efficiency [%] | I56: Utilization factor | J56: Q Oct | K56: Q Nov | L56: Q Dec | M56: Q Jan | N56: Q Feb | O56: Q Mar | P56: Q Apr
J57: [kWh/month] | K57: [kWh/month] | L57: [kWh/month] | M57: [kWh/month] | N57: [kWh/month] | O57: [kWh/month] | P57: [kWh/month]
B58: Before renovation | C58: =C37 -> 3-DMTT | D58: =D37 -> Mavjud egzoz ventilyatori | E58: =G37 -> 8360 | F58: 0.288 | G58: 1.163 | H58: =H37 -> 0 | I58: =10/24 -> 0.41666667 | J58: =((P$22*P$23*$E58*$F58*$G58)/1000*(1-$H58))*$I$58 -> 4032.1898 | K58: =((Q$22*Q$23*$E58*$F58*$G58)/1000*(1-$H58))*$I$58 -> 11642.948 | L58: =((R$22*R$23*$E58*$F58*$G58)/1000*(1-$H58))*$I$58 -> 16307.968 | M58: =((S$22*S$23*$E58*$F58*$G58)/1000*(1-$H58))*$I$58 -> 17327.216 | N58: =((T$22*T$23*$E58*$F58*$G58)/1000*(1-$H58))*$I$58 -> 13650.643 | O58: =((U$22*U$23*$E58*$F58*$G58)/1000*(1-$H58))*$I$58 -> 10506.095 | P58: =((V$22*V$23*$E58*$F58*$G58)/1000*(1-$H58))*$I$58 -> 2251.306
C59: =C38 -> 0 | D59: =D38 -> 0 | E59: =G38 -> 0 | F59: 0.288 | G59: 1.163 | H59: =H38 -> 0 | I59: 0.5 | J59: =((P$22*P$23*$E59*$F59*$G59)/1000*(1-$H59))*$I$59 -> 0 | K59: =((Q$22*Q$23*$E59*$F59*$G59)/1000*(1-$H59))*$I$59 -> 0 | L59: =((R$22*R$23*$E59*$F59*$G59)/1000*(1-$H59))*$I$59 -> 0 | M59: =((S$22*S$23*$E59*$F59*$G59)/1000*(1-$H59))*$I$59 -> 0 | N59: =((T$22*T$23*$E59*$F59*$G59)/1000*(1-$H59))*$I$59 -> 0 | O59: =((U$22*U$23*$E59*$F59*$G59)/1000*(1-$H59))*$I$59 -> 0 | P59: =((V$22*V$23*$E59*$F59*$G59)/1000*(1-$H59))*$I$59 -> 0
C60: =C39 -> 0 | D60: =D39 -> 0 | E60: =G39 -> 0 | F60: 0.288 | G60: 1.163 | H60: =H39 -> 0 | I60: 0.125 | J60: =((P$22*P$23*$E60*$F60*$G60)/1000*(1-$H60))*$I$60 -> 0 | K60: =((Q$22*Q$23*$E60*$F60*$G60)/1000*(1-$H60))*$I$60 -> 0 | L60: =((R$22*R$23*$E60*$F60*$G60)/1000*(1-$H60))*$I$60 -> 0 | M60: =((S$22*S$23*$E60*$F60*$G60)/1000*(1-$H60))*$I$60 -> 0 | N60: =((T$22*T$23*$E60*$F60*$G60)/1000*(1-$H60))*$I$60 -> 0 | O60: =((U$22*U$23*$E60*$F60*$G60)/1000*(1-$H60))*$I$60 -> 0 | P60: =((V$22*V$23*$E60*$F60*$G60)/1000*(1-$H60))*$I$60 -> 0
C61: =C40 -> 0 | D61: =D40 -> 0 | E61: =G40 -> 0 | F61: 0.288 | G61: 1.163 | H61: =H40 -> 0 | I61: 0.125 | J61: =((P$22*P$23*$E61*$F61*$G61)/1000*(1-$H61))*$I$61 -> 0 | K61: =((Q$22*Q$23*$E61*$F61*$G61)/1000*(1-$H61))*$I$61 -> 0 | L61: =((R$22*R$23*$E61*$F61*$G61)/1000*(1-$H61))*$I$61 -> 0 | M61: =((S$22*S$23*$E61*$F61*$G61)/1000*(1-$H61))*$I$61 -> 0 | N61: =((T$22*T$23*$E61*$F61*$G61)/1000*(1-$H61))*$I$61 -> 0 | O61: =((U$22*U$23*$E61*$F61*$G61)/1000*(1-$H61))*$I$61 -> 0 | P61: =((V$22*V$23*$E61*$F61*$G61)/1000*(1-$H61))*$I$61 -> 0
C62: =C41 -> 0 | D62: =D41 -> 0 | E62: =G41 -> 0 | F62: 0.288 | G62: 1.163 | H62: =H41 -> 0 | I62: 1 | J62: =((P$22*P$23*$E62*$F62*$G62)/1000*(1-$H62))*$I$62 -> 0 | K62: =((Q$22*Q$23*$E62*$F62*$G62)/1000*(1-$H62))*$I$62 -> 0 | L62: =((R$22*R$23*$E62*$F62*$G62)/1000*(1-$H62))*$I$62 -> 0 | M62: =((S$22*S$23*$E62*$F62*$G62)/1000*(1-$H62))*$I$62 -> 0 | N62: =((T$22*T$23*$E62*$F62*$G62)/1000*(1-$H62))*$I$62 -> 0 | O62: =((U$22*U$23*$E62*$F62*$G62)/1000*(1-$H62))*$I$62 -> 0 | P62: =((V$22*V$23*$E62*$F62*$G62)/1000*(1-$H62))*$I$62 -> 0
C63: Monthly heat losses through mechanical ventilation before renovation | J63: =SUM(J58:J62) -> 4032.1898 | K63: =SUM(K58:K62) -> 11642.948 | L63: =SUM(L58:L62) -> 16307.968 | M63: =SUM(M58:M62) -> 17327.216 | N63: =SUM(N58:N62) -> 13650.643 | O63: =SUM(O58:O62) -> 10506.095 | P63: =SUM(P58:P62) -> 2251.306
B64: After renovation | C64: =C44 -> 3-DMTT | D64: =D44 -> 0 | E64: =G44 -> 0 | F64: 0.288 | G64: 1.163 | H64: =H44 -> 0 | I64: =I58 -> 0.41666667 | J64: =((P$22*P$23*$E64*$F64*$G64)/1000*(1-$H64))*$I$64 -> 0 | K64: =((Q$22*Q$23*$E64*$F64*$G64)/1000*(1-$H64))*$I$64 -> 0 | L64: =((R$22*R$23*$E64*$F64*$G64)/1000*(1-$H64))*$I$64 -> 0 | M64: =((S$22*S$23*$E64*$F64*$G64)/1000*(1-$H64))*$I$64 -> 0 | N64: =((T$22*T$23*$E64*$F64*$G64)/1000*(1-$H64))*$I$64 -> 0 | O64: =((U$22*U$23*$E64*$F64*$G64)/1000*(1-$H64))*$I$64 -> 0 | P64: =((V$22*V$23*$E64*$F64*$G64)/1000*(1-$H64))*$I$64 -> 0
C65: =C45 -> 0 | D65: =D45 -> AHU's with heat recovery | E65: =G45 -> 8360 | F65: 0.288 | G65: 1.163 | H65: =H45 -> 0.85 | I65: =10/24 -> 0.41666667 | J65: =((P$22*P$23*$E65*$F65*$G65)/1000*(1-$H65))*$I$65 -> 604.82848 | K65: =((Q$22*Q$23*$E65*$F65*$G65)/1000*(1-$H65))*$I$65 -> 1746.4422 | L65: =((R$22*R$23*$E65*$F65*$G65)/1000*(1-$H65))*$I$65 -> 2446.1952 | M65: =((S$22*S$23*$E65*$F65*$G65)/1000*(1-$H65))*$I$65 -> 2599.0824 | N65: =((T$22*T$23*$E65*$F65*$G65)/1000*(1-$H65))*$I$65 -> 2047.5964 | O65: =((U$22*U$23*$E65*$F65*$G65)/1000*(1-$H65))*$I$65 -> 1575.9142 | P65: =((V$22*V$23*$E65*$F65*$G65)/1000*(1-$H65))*$I$65 -> 337.6959
C66: =C46 -> 0 | D66: =D46 -> 0 | E66: =G46 -> 0 | F66: 0.288 | G66: 1.163 | H66: =H46 -> 0 | I66: =I60 -> 0.125 | J66: =((P$22*P$23*$E66*$F66*$G66)/1000*(1-$H66))*$I$66 -> 0 | K66: =((Q$22*Q$23*$E66*$F66*$G66)/1000*(1-$H66))*$I$66 -> 0 | L66: =((R$22*R$23*$E66*$F66*$G66)/1000*(1-$H66))*$I$66 -> 0 | M66: =((S$22*S$23*$E66*$F66*$G66)/1000*(1-$H66))*$I$66 -> 0 | N66: =((T$22*T$23*$E66*$F66*$G66)/1000*(1-$H66))*$I$66 -> 0 | O66: =((U$22*U$23*$E66*$F66*$G66)/1000*(1-$H66))*$I$66 -> 0 | P66: =((V$22*V$23*$E66*$F66*$G66)/1000*(1-$H66))*$I$66 -> 0
C67: =C47 -> 0 | D67: =D47 -> 0 | E67: =G47 -> 0 | F67: 0.288 | G67: 1.163 | H67: =H47 -> 0 | I67: =I61 -> 0.125 | J67: =((P$22*P$23*$E67*$F67*$G67)/1000*(1-$H67))*$I$67 -> 0 | K67: =((Q$22*Q$23*$E67*$F67*$G67)/1000*(1-$H67))*$I$67 -> 0 | L67: =((R$22*R$23*$E67*$F67*$G67)/1000*(1-$H67))*$I$67 -> 0 | M67: =((S$22*S$23*$E67*$F67*$G67)/1000*(1-$H67))*$I$67 -> 0 | N67: =((T$22*T$23*$E67*$F67*$G67)/1000*(1-$H67))*$I$67 -> 0 | O67: =((U$22*U$23*$E67*$F67*$G67)/1000*(1-$H67))*$I$67 -> 0 | P67: =((V$22*V$23*$E67*$F67*$G67)/1000*(1-$H67))*$I$67 -> 0
C68: =C48 -> 0 | D68: =D48 -> 0 | E68: =G48 -> 0 | F68: 0.288 | G68: 1.163 | H68: =H48 -> 0 | I68: 0.1 | J68: =((P$22*P$23*$E68*$F68*$G68)/1000*(1-$H68))*$I$68 -> 0 | K68: =((Q$22*Q$23*$E68*$F68*$G68)/1000*(1-$H68))*$I$68 -> 0 | L68: =((R$22*R$23*$E68*$F68*$G68)/1000*(1-$H68))*$I$68 -> 0 | M68: =((S$22*S$23*$E68*$F68*$G68)/1000*(1-$H68))*$I$68 -> 0 | N68: =((T$22*T$23*$E68*$F68*$G68)/1000*(1-$H68))*$I$68 -> 0 | O68: =((U$22*U$23*$E68*$F68*$G68)/1000*(1-$H68))*$I$68 -> 0 | P68: =((V$22*V$23*$E68*$F68*$G68)/1000*(1-$H68))*$I$68 -> 0
C69: Monthly heat losses through mechanical ventilation after renovation | J69: =SUM(J64:J68) -> 604.82848 | K69: =SUM(K64:K68) -> 1746.4422 | L69: =SUM(L64:L68) -> 2446.1952 | M69: =SUM(M64:M68) -> 2599.0824 | N69: =SUM(N64:N68) -> 2047.5964 | O69: =SUM(O64:O68) -> 1575.9142 | P69: =SUM(P64:P68) -> 337.6959
B70: Monthly heat savings from mechanical ventilation | J70: =J63-J69 -> 3427.3614 | K70: =K63-K69 -> 9896.506 | L70: =L63-L69 -> 13861.773 | M70: =M63-M69 -> 14728.133 | N70: =N63-N69 -> 11603.046 | O70: =O63-O69 -> 8930.1805 | P70: =P63-P69 -> 1913.6101
D74: CAPEX
D75: Measure | E75: Description | F75: Cost [USD/m³] | G75: units | H75: Total Investment [USD]
D76: Mechanical ventilation with heat recovery | E76: Wallmounted AHU units with heat recover 85% | F76: 850 | G76: =G37/200 -> 41.8 | H76: 20139
D77: Note:The cost is assumed in average per 1m³ of heated volume of already rehabilitated hospitals, with updated market prices from Q3 of 2022.

Sheet Heat gains Mec Vent
B2: Annual heat gains from mechanical ventilation before and after renovation
C3: Block/floor name | D3: Unit description | E3: No of people | F3: Fresh air per person [m³/h/person] | G3: VSUPPLY &/OR EXAHUST * [m³/h] | H3: ρ [kg/m³] | I3: Conversion coeff. | J3: ΔI [kJ/kg] | K3: Operation hours during cooling season [h/y] | L3: Heat exchanger efficiency | M3: Q
L4: [%] | M4: [kWh/y]
B5: Before renovation | C5: ='Ventilation losses'!C37 -> 3-DMTT | D5: ='Ventilation losses'!D37 -> Mavjud egzoz ventilyatori | G5: ='Ventilation losses'!G37 -> 8360 | H5: 1.2 | I5: 0.277778 | J5: =Building_data!D$16-Building_data!D$15 -> 11.1 | K5: =Equipment!H35*Equipment!J35 -> 0 | L5: 0 | M5: =((G5*H5*I5*J5*K5)/1000)*(1-L5) -> 0
H6: 1.2 | I6: 0.277778 | J6: =Building_data!D$16-Building_data!D$15 -> 11.1 | L6: 0 | M6: =((G6*H6*I6*J6*K6)/1000)*(1-L6) -> 0
H7: 1.2 | I7: 0.277778 | J7: =Building_data!D$16-Building_data!D$15 -> 11.1 | L7: ='Ventilation losses'!H39 -> 0 | M7: =((G7*H7*I7*J7*K7)/1000)*(1-L7) -> 0
H8: 1.2 | I8: 0.277778 | J8: =Building_data!D$16-Building_data!D$15 -> 11.1 | L8: ='Ventilation losses'!H40 -> 0 | M8: =((G8*H8*I8*J8*K8)/1000)*(1-L8) -> 0
C9: ='Ventilation losses'!C41 -> 0 | E9: ='Ventilation losses'!E41 -> 0 | F9: ='Ventilation losses'!F41 -> 0 | G9: ='Ventilation losses'!G41 -> 0 | H9: 1.2 | I9: 0.277778 | J9: =Building_data!D$16-Building_data!D$15 -> 11.1 | L9: ='Ventilation losses'!H41 -> 0 | M9: =((G9*H9*I9*J9*K9)/1000)*(1-L9) -> 0
C10: Total heat gains through mechanical ventilation before renovation | M10: =SUM(M5:M9) -> 0
B11: After renovation | C11: =C5 -> 3-DMTT | D11: =D5 -> Mavjud egzoz ventilyatori | F11: ='Ventilation losses'!F44 -> 0 | G11: =G5 -> 8360 | H11: 1.2 | I11: 0.277778 | J11: =Building_data!D$16-Building_data!D$15 -> 11.1 | K11: =K5 -> 0 | L11: ='Ventilation losses'!H44 -> 0 | M11: =((G11*H11*I11*J11*K11)/1000)*(1-L11) -> 0
D12: ='Ventilation losses'!D45 -> AHU's with heat recovery | E12: ='Ventilation losses'!E45 -> 418 | F12: ='Ventilation losses'!F45 -> 20 | G12: =E12*F12 -> 8360 | H12: 1.2 | I12: 0.277778 | J12: =Building_data!D$16-Building_data!D$15 -> 11.1 | K12: =Equipment!H86*Equipment!J86 -> 720 | L12: ='Ventilation losses'!H45 -> 0.85 | M12: =((G12*H12*I12*J12*K12)/1000)*(1-L12) -> 3340.6587
D13: =D7 -> 0 | E13: ='Ventilation losses'!E46 -> 0 | F13: ='Ventilation losses'!F46 -> 0 | H13: 1.2 | I13: 0.277778 | J13: =Building_data!D$16-Building_data!D$15 -> 11.1 | K13: =K7 -> 0 | L13: ='Ventilation losses'!H46 -> 0 | M13: =((G13*H13*I13*J13*K13)/1000)*(1-L13) -> 0
D14: =D8 -> 0 | E14: ='Ventilation losses'!E47 -> 0 | F14: ='Ventilation losses'!F47 -> 0 | H14: 1.2 | I14: 0.277778 | J14: =Building_data!D$16-Building_data!D$15 -> 11.1 | K14: =K8 -> 0 | L14: ='Ventilation losses'!H47 -> 0 | M14: =((G14*H14*I14*J14*K14)/1000)*(1-L14) -> 0
F15: ='Ventilation losses'!F48 -> 0 | G15: =E15*F15 -> 0 | H15: 1.2 | I15: 0.277778 | J15: =Building_data!D$16-Building_data!D$15 -> 11.1 | K15: =K9 -> 0 | L15: ='Ventilation losses'!H48 -> 0 | M15: =((G15*H15*I15*J15*K15)/1000)*(1-L15) -> 0
C16: Total heat gains through mechanical ventilation after renovation | M16: =SUM(M11:M15) -> 3340.6587
B17: Cooling energy savings from mechanical ventilation | M17: =M10-M16 -> -3340.6587
C19: * - If some figure is dominating for supply or exhaust in the same space, please apply the maximum value. Please avoid double counting in case if 2 units serve same space (for ex. kitchen 1 supply fan of 800m3/h and 1 exhaust fan of 1000m3/h, only exhaust fan for 1000m3/h should be considered during cooling energy loss calculation. Cooling energy losses are calculated only for air conditioned spaces.

Sheet gains
A1: Before renovation
A3: Windows | N3: Table A.4, page 126, Solar radiation, kWh/m2
B4: Area, m2 | C4: gn | D4: Fw | E4: Fhor | F4: Fov | G4: Ffin | H4: Fsh | I4: Asol, m2 | J4: Fsh*Asol, m2 | N4: Month | O4: South | P4: North | Q4: East, West | R4: South-east, south-west | S4: North-east, north-west | T4: Horizontal
A5: South | B5: =Envelope!AF7 -> 79.02 | C5: 0.75 | D5: 0.6 | E5: 0.85 | F5: 0.9 | G5: 0.94 | H5: =E5*F5*G5 -> 0.7191 | I5: =(C5*D5)*(1-0.3)*B5 -> 24.8913 | J5: =H5*I5 -> 17.899334 | N5: January | O5: 65 | P5: 17.7 | Q5: 28.5 | R5: 51.2 | S5: 18.7 | T5: 33.5
A6: North | B6: =Envelope!AF8 -> 86.4 | C6: 0.75 | D6: 0.6 | E6: 0.98 | F6: 0.91 | G6: 1 | H6: =E6*F6*G6 -> 0.8918 | I6: =(C6*D6)*(1-0.3)*B6 -> 27.216 | J6: =H6*I6 -> 24.271229 | N6: February | O6: 76.3 | P6: 21.9 | Q6: 38.9 | R6: 62.3 | S6: 24.4 | T6: 49.8
A7: East, West | B7: =Envelope!AF9+Envelope!AF10 -> 25.56 | C7: 0.75 | D7: 0.6 | E7: 0.82 | F7: 0.89 | G7: 0.92 | H7: =E7*F7*G7 -> 0.671416 | I7: =(C7*D7)*(1-0.3)*B7 -> 8.0514 | J7: =H7*I7 -> 5.4058388 | N7: March | O7: 96 | P7: 29.3 | Q7: 61.3 | R7: 85 | S7: 37.5 | T7: 91.5
A8: South-east, south-west | B8: =Envelope!AF11+Envelope!AF12 -> 0 | C8: 0.75 | D8: 0.6 | E8: 0.82 | F8: 0.89 | G8: 0.92 | H8: =E8*F8*G8 -> 0.671416 | I8: =(C8*D8)*(1-0.3)*B8 -> 0 | J8: =H8*I8 -> 0 | N8: April | O8: 20.1 | P8: 7.9 | Q8: 16.7 | R8: 20.1 | S8: 11.6 | T8: 28.3
A9: North-east, north-west | B9: =Envelope!AF13+Envelope!AF14 -> 0 | C9: 0.75 | D9: 0.6 | E9: 0.82 | F9: 0.89 | G9: 0.92 | H9: =E9*F9*G9 -> 0.671416 | I9: =(C9*D9)*(1-0.3)*B9 -> 0 | J9: =H9*I9 -> 0 | N9: October | O9: 24.3 | P9: 5.8 | Q9: 12.7 | R9: 20.3 | S9: 7 | T9: 19.9
A10: Horizontal | C10: 0.75 | D10: 0.6 | E10: 1 | F10: 1 | G10: 1 | H10: =E10*F10*G10 -> 1 | I10: =(C10*D10)*(1-0.3)*B10 -> 0 | J10: =H10*I10 -> 0 | N10: November | O10: 60.8 | P10: 13.1 | Q10: 24 | R10: 48 | S10: 14.3 | T10: 37.5
N11: December | O11: 58.4 | P11: 11.5 | Q11: 20 | R11: 44.5 | S11: 11.7 | T11: 26.7
A12: Month | B12: Heating days | C12: Outdoor air temperature, oC | D12: Specific internal heat gains, kWh/m2 | E12: Internal heat gains, kWh | F12: Solar heat gains, kWh | G12: Total heat gains, kWh | H12: Total heat losses, kWh | I12: gains/losses | J12: Heat gain utilization factor | K12: Energy need for space heating, kWh | N12: Total | O12: =SUM(O5:O11) -> 400.9 | P12: =SUM(P5:P11) -> 107.2 | Q12: =SUM(Q5:Q11) -> 202.1 | R12: =SUM(R5:R11) -> 331.4 | S12: =SUM(S5:S11) -> 125.2 | T12: =SUM(T5:T11) -> 287.2 | W12: Measured data. kWh
A13: January | B13: 28 | C13: ='Losses env. after'!Q33 -> -0,1 | D13: =$O$15*B13*24/1000 -> 4.032 | E13: =D13*Building_data!$D$4 -> 10142.153 | F13: =$J$5*O5+$J$6*P5+$J$7*Q5+$J$8*R5+$J$9*S5+$J$10*T5 -> 1747.1239 | G13: =E13+F13 -> 11889.277 | H13: ='Losses env. before'!$H$68+'Ventilation losses'!$J$24+'Ventilation losses'!$M$63 -> 96685.256 | I13: =G13/H13 -> 0.12296887 | J13: =(1-I13^4.2)/(1-I13^5.2) -> 0.99986812 | K13: =H13-J13*G13 -> 84797.547 | W13: =Consumption!M7 -> 63146.5 | X13: =K13/W13 -> 1.3428701
A14: February | B14: 24 | C14: ='Losses env. after'!R33 -> 2,5 | D14: =$O$15*B14*24/1000 -> 3.456 | E14: =D14*Building_data!$D$4 -> 8693.2742 | F14: =$J$5*O6+$J$6*P6+$J$7*Q6+$J$8*R6+$J$9*S6+$J$10*T6 -> 2107.5462 | G14: =E14+F14 -> 10800.82 | H14: ='Losses env. before'!$I$68+'Ventilation losses'!$K$24+'Ventilation losses'!$N$63 -> 74624.864 | I14: =G14/H14 -> 0.14473488 | J14: =(1-I14^4.2)/(1-I14^5.2) -> 0.99974501 | K14: =H14-J14*G14 -> 63826.798 | N14: Table 10, page 100 | W14: =Consumption!M8 -> 52177.167 | X14: =K14/W14 -> 1.2232707
A15: March | B15: 28 | C15: ='Losses env. after'!S33 -> 8,6 | D15: =$O$15*B15*24/1000 -> 4.032 | E15: =D15*Building_data!$D$4 -> 10142.153 | F15: =$J$5*O7+$J$6*P7+$J$7*Q7+$J$8*R7+$J$9*S7+$J$10*T7 -> 2760.861 | G15: =E15+F15 -> 12903.014 | H15: ='Losses env. before'!$J$68+'Ventilation losses'!$L$24+'Ventilation losses'!$O$63 -> 52832.544 | I15: =G15/H15 -> 0.24422474 | J15: =(1-I15^4.2)/(1-I15^5.2) -> 0.99797048 | K15: =H15-J15*G15 -> 39955.717 | N15: Internal heat gains | O15: 6 | P15: W/m2 | W15: =Consumption!M9 -> 25070.5 | X15: =K15/W15 -> 1.5937343
A16: April | B16: 15 | C16: ='Losses env. after'!T33 -> 15,3 | D16: =$O$15*B16*24/1000 -> 2.16 | E16: =D16*Building_data!$D$4 -> 5433.2964 | F16: =$J$5*O8+$J$6*P8+$J$7*Q8+$J$8*R8+$J$9*S8+$J$10*T8 -> 641.79683 | G16: =E16+F16 -> 6075.0932 | H16: ='Losses env. before'!$K$68+'Ventilation losses'!$M$24+'Ventilation losses'!$P$63 -> 8168.9635 | I16: =G16/H16 -> 0.74367981 | J16: =(1-I16^4.2)/(1-I16^5.2) -> 0.90594158 | K16: =H16-J16*G16 -> 2665.284 | W16: =Consumption!M10 -> 3920.3333 | X16: =K16/W16 -> 0.67986157
A17: October | B17: 14 | C17: ='Losses env. after'!N33 -> 12,4 | D17: =$O$15*B17*24/1000 -> 2.016 | E17: =D17*Building_data!$D$4 -> 5071.0766 | F17: =$J$5*O9+$J$6*P9+$J$7*Q9+$J$8*R9+$J$9*S9+$J$10*T9 -> 644.38109 | G17: =E17+F17 -> 5715.4577 | H17: ='Losses env. before'!$E$68+'Ventilation losses'!$G$24+'Ventilation losses'!$J$63 -> 18042.046 | I17: =G17/H17 -> 0.31678546 | J17: =(1-I17^4.2)/(1-I17^5.2) -> 0.99451883 | K17: =H17-J17*G17 -> 12357.916 | N17: Table 11, page 102 | W17: =Consumption!M16 -> 7172.5 | X17: =K17/W17 -> 1.7229579
A18: November | B18: 26 | C18: ='Losses env. after'!O33 -> 6,6 | D18: =$O$15*B18*24/1000 -> 3.744 | E18: =D18*Building_data!$D$4 -> 9417.7138 | F18: =$J$5*O10+$J$6*P10+$J$7*Q10+$J$8*R10+$J$9*S10+$J$10*T10 -> 1535.9727 | G18: =E18+F18 -> 10953.686 | H18: ='Losses env. before'!$F$68+'Ventilation losses'!$H$24+'Ventilation losses'!$K$63 -> 60666.712 | I18: =G18/H18 -> 0.18055514 | J18: =(1-I18^4.2)/(1-I18^5.2) -> 0.9993815 | K18: =H18-J18*G18 -> 49719.8 | N18: Type of window | O18: gn | W18: =Consumption!M17 -> 24503.667 | X18: =K18/W18 -> 2.0290759
A19: December | B19: 28 | C19: ='Losses env. after'!P33 -> 1,2 | D19: =$O$15*B19*24/1000 -> 4.032 | E19: =D19*Building_data!$D$4 -> 10142.153 | F19: =$J$5*O11+$J$6*P11+$J$7*Q11+$J$8*R11+$J$9*S11+$J$10*T11 -> 1432.557 | G19: =E19+F19 -> 11574.71 | H19: ='Losses env. before'!$G$68+'Ventilation losses'!$I$24+'Ventilation losses'!$L$63 -> 90132.552 | I19: =G19/H19 -> 0.12841876 | J19: =(1-I19^4.2)/(1-I19^5.2) -> 0.99984276 | K19: =H19-J19*G19 -> 78559.662 | N19: One glass pane | O19: 0.85 | W19: =Consumption!M18 -> 46486.667 | X19: =K19/W19 -> 1.6899397
A20: Total | B20: =SUM(B13:B19) -> 163 | C20: =SUMPRODUCT(B13:B19,C13:C19)/B20 -> 0 | D20: =SUM(D13:D19) -> 23.472 | E20: =SUM(E13:E19) -> 59041.821 | F20: =SUM(F13:F19) -> 10870.239 | G20: =SUM(G13:G19) -> 69912.06 | H20: =SUM(H13:H19) -> 401152.94 | I20: =G20/H20 -> 0.17427782 | K20: =SUM(K13:K19) -> 331882.72 | N20: Double glass panes, double window | O20: 0.75 | W20: =SUM(W13:W19) -> 222477.33 | X20: =K20/W20 -> 1.4917597
N21: Double window with selective coating low-e | O21: 0.67
A22: After renovation | N22: Tripple glass window | O22: 0.7
N23: Tripple glass window wilh selective coating low-e | O23: 0.5
A24: Windows
B25: Area, m2 | C25: gn | D25: Fw | E25: Fhor | F25: Fov | G25: Ffin | H25: Fsh | I25: Asol, m2 | J25: Fsh*Asol, m2
A26: South | B26: =B5 -> 79.02 | C26: 0.7 | D26: 0.9 | E26: 0.85 | F26: 0.9 | G26: 0.94 | H26: =E26*F26*G26 -> 0.7191 | I26: =(C26*D26)*(1-0.3)*B26 -> 34.84782 | J26: =H26*I26 -> 25.059067
A27: North | B27: =B6 -> 86.4 | C27: 0.7 | D27: 0.9 | E27: 0.98 | F27: 0.91 | G27: 1 | H27: =E27*F27*G27 -> 0.8918 | I27: =(C27*D27)*(1-0.3)*B27 -> 38.1024 | J27: =H27*I27 -> 33.97972
A28: East, West | B28: =B7 -> 25.56 | C28: 0.7 | D28: 0.9 | E28: 0.82 | F28: 0.89 | G28: 0.92 | H28: =E28*F28*G28 -> 0.671416 | I28: =(C28*D28)*(1-0.3)*B28 -> 11.27196 | J28: =H28*I28 -> 7.5681743
A29: South-east, south-west | B29: =B8 -> 0 | C29: 0.7 | D29: 0.9 | E29: 0.82 | F29: 0.89 | G29: 0.92 | H29: =E29*F29*G29 -> 0.671416 | I29: =(C29*D29)*(1-0.3)*B29 -> 0 | J29: =H29*I29 -> 0
A30: North-east, north-west | B30: =B9 -> 0 | C30: 0.7 | D30: 0.9 | E30: 0.82 | F30: 0.89 | G30: 0.92 | H30: =E30*F30*G30 -> 0.671416 | I30: =(C30*D30)*(1-0.3)*B30 -> 0 | J30: =H30*I30 -> 0
A31: Horizontal | B31: =B10 -> 0 | C31: 0.7 | D31: 0.9 | E31: 1 | F31: 1 | G31: 1 | H31: =E31*F31*G31 -> 1 | I31: =(C31*D31)*(1-0.3)*B31 -> 0 | J31: =H31*I31 -> 0
A33: Month | B33: Heating days | C33: Outdoor air temperature, oC | D33: Specific internal heat gains, kWh/m2 | E33: Internal heat gains, kWh | F33: Solar heat gains, kWh | G33: Total heat gains, kWh | H33: Total heat losses, kWh | I33: gains/losses | J33: Heat gain utilization factor | K33: Energy need for space heating, kWh
A34: January | B34: 28 | C34: -3.5 | D34: =$O$15*B34*24/1000 -> 4.032 | E34: =D34*Building_data!$D$4 -> 10142.153 | F34: =$J$26*O5+$J$27*P5+$J$28*Q5+$J$29*R5+$J$30*S5+$J$31*T5 -> 2445.9734 | G34: =E34+F34 -> 12588.127 | H34: ='Losses env. after'!$H$60+'Ventilation losses'!$J$29+'Ventilation losses'!$M$69 -> 32009.701 | I34: =G34/H34 -> 0.39325974 | J34: =(1-I34^5)/(1-I34^6) -> 0.99427191 | K34: =H34-J34*G34 -> 19493.68
A35: February | B35: 24 | C35: -2.5 | D35: =$O$15*B35*24/1000 -> 3.456 | E35: =D35*Building_data!$D$4 -> 8693.2742 | F35: =$J$26*O6+$J$27*P6+$J$28*Q6+$J$29*R6+$J$30*S6+$J$31*T6 -> 2950.5647 | G35: =E35+F35 -> 11643.839 | H35: ='Losses env. after'!$I$60+'Ventilation losses'!$K$29+'Ventilation losses'!$N$69 -> 24941.679 | I35: =G35/H35 -> 0.46684263 | J35: =(1-I35^5)/(1-I35^6) -> 0.98805387 | K35: =H35-J35*G35 -> 13436.939
A36: March | B36: 28 | C36: 2.6 | D36: =$O$15*B36*24/1000 -> 4.032 | E36: =D36*Building_data!$D$4 -> 10142.153 | F36: =$J$26*O7+$J$27*P7+$J$28*Q7+$J$29*R7+$J$30*S7+$J$31*T7 -> 3865.2054 | G36: =E36+F36 -> 14007.359 | H36: ='Losses env. after'!$J$60+'Ventilation losses'!$L$29+'Ventilation losses'!$O$69 -> 18374.055 | I36: =G36/H36 -> 0.76234445 | J36: =(1-I36^5)/(1-I36^6) -> 0.92386102 | K36: =H36-J36*G36 -> 5433.2022
A37: April | B37: 15 | C37: 7.2 | D37: =$O$15*B37*24/1000 -> 2.16 | E37: =D37*Building_data!$D$4 -> 5433.2964 | F37: =$J$26*O8+$J$27*P8+$J$28*Q8+$J$29*R8+$J$30*S8+$J$31*T8 -> 898.51556 | G37: =E37+F37 -> 6331.812 | H37: ='Losses env. after'!$K$60+'Ventilation losses'!$M$29+'Ventilation losses'!$P$69 -> 3374.16 | I37: =G37/H37 -> 1.8765595 | J37: =(1-I37^5)/(1-I37^6) -> 0.52194285 | K37: =H37-J37*G37 -> 69.316053
A38: October | B38: 14 | C38: 7.3 | D38: =$O$15*B38*24/1000 -> 2.016 | E38: =D38*Building_data!$D$4 -> 5071.0766 | F38: =$J$26*O9+$J$27*P9+$J$28*Q9+$J$29*R9+$J$30*S9+$J$31*T9 -> 902.13353 | G38: =E38+F38 -> 5973.2102 | H38: ='Losses env. after'!$E$60+'Ventilation losses'!$G$29+'Ventilation losses'!$J$69 -> 6652.6368 | I38: =G38/H38 -> 0.89787108 | J38: =(1-I38^5)/(1-I38^6) -> 0.87481291 | K38: =H38-J38*G38 -> 1427.1954
A39: November | B39: 26 | C39: 3.9 | D39: =$O$15*B39*24/1000 -> 3.744 | E39: =D39*Building_data!$D$4 -> 9417.7138 | F39: =$J$26*O10+$J$27*P10+$J$28*Q10+$J$29*R10+$J$30*S10+$J$31*T10 -> 2150.3618 | G39: =E39+F39 -> 11568.076 | H39: ='Losses env. after'!$F$60+'Ventilation losses'!$H$29+'Ventilation losses'!$K$69 -> 20740.519 | I39: =G39/H39 -> 0.55775247 | J39: =(1-I39^5)/(1-I39^6) -> 0.97538791 | K39: =H39-J39*G39 -> 9457.1577
A40: December | B40: 28 | C40: -0.9 | D40: =$O$15*B40*24/1000 -> 4.032 | E40: =D40*Building_data!$D$4 -> 10142.153 | F40: =$J$26*O11+$J$27*P11+$J$28*Q11+$J$29*R11+$J$30*S11+$J$31*T11 -> 2005.5798 | G40: =E40+F40 -> 12147.733 | H40: ='Losses env. after'!$G$60+'Ventilation losses'!$I$29+'Ventilation losses'!$L$69 -> 29972.19 | I40: =G40/H40 -> 0.40530014 | J40: =(1-I40^5)/(1-I40^6) -> 0.99346703 | K40: =H40-J40*G40 -> 17903.818
A41: Total | B41: =SUM(B34:B40) -> 163 | C41: =SUMPRODUCT(B34:B40,C34:C40)/B41 -> 1.2343558 | D41: =SUM(D34:D40) -> 23.472 | E41: =SUM(E34:E40) -> 59041.821 | F41: =SUM(F34:F40) -> 15218.334 | G41: =SUM(G34:G40) -> 74260.155 | H41: =SUM(H34:H40) -> 136064.94 | I41: =G41/H41 -> 0.54576995 | K41: =SUM(K34:K40) -> 67221.308

Sheet Heat distr. efficiency
B2: Heat distribution losses inside basement
C3: Building name | D3: Interior nominal diameter of pipe (DN), [mm] | E3: Length [m] | F3: Percentage of insulated pipes | G3: Length of insulated pipes [m] | H3: Length of non-insulated pipes [m] | I3: Losses through non-insulated pipes [W/m] | J3: Losses through insulated pipes [W/m] | K3: Hours per year [h/y] | L3: Q [kWh/y]
P4: Pierderea maximă a densităţii fluxului de căldură prin țevi izolate în spații neîncălzite, [W/m]
P5: Diametrul nominal interior al conductei (DN), [mm] | Q5: Temperatura medie a agentului termic, [°C]
B6: Before renovation | L6: =(((G6*J6)+(H6*I6))*K6)/1000 -> 0 | Y6: Month | Z6: Oct | AA6: Nov | AB6: Dec | AC6: Jan | AD6: Feb | AE6: Mar | AF6: Apr
L7: =(((G7*J7)+(H7*I7))*K7)/1000 -> 0 | Y7: Average temp [°C] | Z7: 12,4 | AA7: 6,6 | AB7: 1,2 | AC7: -0,1 | AD7: 2,5 | AE7: 8,6 | AF7: 15,3
L8: =(((G8*J8)+(H8*I8))*K8)/1000 -> 0 | Q8: ≤50 | R8: 60 | S8: 70 | T8: 80 | U8: ≥90 | Y8: Duration [days] | Z8: 15 | AA8: 27 | AB8: 28 | AC8: 28 | AD8: 25 | AE8: 28 | AF8: 12
C9: ='Heat gains Mec Vent'!C5 -> 3-DMTT | L9: =(((G9*J9)+(H9*I9))*K9)/1000 -> 0 | P9: 15 – 25 | Q9: 7 | R9: 11 | S9: 13 | T9: 14 | U9: 16 | Y9: Δt [°C] | Z9: =Building_data!$D$9-'Losses env. before'!Z7 -> 22 | AA9: =Building_data!$D$9-'Losses env. before'!AA7 -> 22 | AB9: =Building_data!$D$9-'Losses env. before'!AB7 -> 22 | AC9: =Building_data!$D$9-'Losses env. before'!AC7 -> 22 | AD9: =Building_data!$D$9-'Losses env. before'!AD7 -> 22 | AE9: =Building_data!$D$9-'Losses env. before'!AE7 -> 22 | AF9: =Building_data!$D$9-'Losses env. before'!AF7 -> 22
D10: 15 – 25 | E10: 480 | F10: 0 | G10: =E10*F10 -> 0 | H10: =E10-G10 -> 480 | I10: =IFERROR(VLOOKUP(D10,$P$17:$Q$19,2,FALSE),"") -> 47 | J10: =IFERROR(VLOOKUP(D10,$P$9:$R$11,3,FALSE),"") -> 11 | K10: =Building_data!D12 -> 1630 | L10: =(((G10*J10)+(H10*I10))*K10)/1000 -> 36772.8 | P10: 32 – 50 | Q10: 10 | R10: 14 | S10: 16 | T10: 18 | U10: 21 | Y10: Duration [h] | Z10: =Z8*Building_data!$D$14 -> 150 | AA10: =AA8*Building_data!$D$14 -> 270 | AB10: =AB8*Building_data!$D$14 -> 280 | AC10: =AC8*Building_data!$D$14 -> 280 | AD10: =AD8*Building_data!$D$14 -> 250 | AE10: =AE8*Building_data!$D$14 -> 280 | AF10: =AF8*Building_data!$D$14 -> 120
L11: =(((G11*J11)+(H11*I11))*K11)/1000 -> 0 | P11: 65 – 100 | Q11: 14 | R11: 19 | S11: 22 | T11: 25 | U11: 29
C12: Total heat losses through heat distribution system before renovation | L12: =SUM(L6:L11) -> 36772.8 | Y12: Month | Z12: Oct | AA12: Nov | AB12: Dec | AC12: Jan | AD12: Feb | AE12: Mar | AF12: Apr
B13: After renovation | L13: =(((G13*J13)+(H13*I13))*K13)/1000 -> 0 | N13: 372 | Y13: Average temp [°C] | Z13: 12,4 | AA13: 6,6 | AB13: 1,2 | AC13: -0,1 | AD13: 2,5 | AE13: 8,6 | AF13: 15,3
L14: =(((G14*J14)+(H14*I14))*K14)/1000 -> 0 | N14: 64 | P14: Pierderea maximă a densității fluxului de căldură prin țevi neizolate în spații neîncălzite, [W/m] | Y14: Duration [days] | Z14: 15 | AA14: 27 | AB14: 28 | AC14: 28 | AD14: 25 | AE14: 28 | AF14: 12
L15: =(((G15*J15)+(H15*I15))*K15)/1000 -> 0 | N15: 152 | P15: Diametrul nominal interior al conductei (DN), [mm] | Q15: Temperatura medie a agentului termic – 60[°C] | Y15: Δt [°C] | Z15: =Building_data!#REF!-'Losses env. before'!Z13 -> #REF! | AA15: =Building_data!#REF!-'Losses env. before'!AA13 -> #REF! | AB15: =Building_data!#REF!-'Losses env. before'!AB13 -> #REF! | AC15: =Building_data!#REF!-'Losses env. before'!AC13 -> #REF! | AD15: =Building_data!#REF!-'Losses env. before'!AD13 -> #REF! | AE15: =Building_data!#REF!-'Losses env. before'!AE13 -> #REF! | AF15: =Building_data!#REF!-'Losses env. before'!AF13 -> #REF!
C16: =C9 -> 3-DMTT | L16: =(((G16*J16)+(H16*I16))*K16)/1000 -> 0 | Y16: Duration [h] | Z16: =Z14*Building_data!$D$13 -> 210 | AA16: =AA14*Building_data!$D$13 -> 378 | AB16: =AB14*Building_data!$D$13 -> 392 | AC16: =AC14*Building_data!$D$13 -> 392 | AD16: =AD14*Building_data!$D$13 -> 350 | AE16: =AE14*Building_data!$D$13 -> 392 | AF16: =AF14*Building_data!$D$13 -> 168
D17: 15 – 25 | E17: =E10 -> 480 | F17: 1 | G17: =E17*F17 -> 480 | H17: =E17-G17 -> 0 | I17: =IFERROR(VLOOKUP(D17,$P$17:$Q$19,2,FALSE),"") -> 47 | J17: =IFERROR(VLOOKUP(D17,$P$9:$R$11,3,FALSE),"") -> 11 | K17: =Building_data!D12 -> 1630 | L17: =(((G17*J17)+(H17*I17))*K17)/1000 -> 8606.4 | P17: 15 – 25 | Q17: 47
L18: =(((G18*J18)+(H18*I18))*K18)/1000 -> 0 | P18: 32 – 50 | Q18: 74
C19: Total heat losses through heat distribution system after renovation | L19: =SUM(L13:L18) -> 8606.4 | P19: 65 – 100 | Q19: 140 | Y19: Element | Z19: Type | AB19: Q Oct | AC19: Q Nov | AD19: Q Dec | AE19: Q Jan | AF19: Q Feb | AG19: Q Mar | AH19: Q Apr
B20: Heat savings from heat distribution system | L20: =L12-L19 -> 28166.4 | AB20: [kWh/month] | AC20: [kWh/month] | AD20: [kWh/month] | AE20: [kWh/month] | AF20: [kWh/month] | AG20: [kWh/month] | AH20: [kWh/month]
Z21: Chugun (ish vaqti)
Q23: Costs to be applied in CAPEX
Q24: Diameter | R24: Pipe price [USD/m] | S24: Fitings [USD] | T24: Insulation price [USD/m] | U24: Labour [USD] | V24: Total [USD/m]
C25: Building name | D25: Radiator turi | E25: Soni | F25: A (m²) | G25: Jami (m²) | H25: K (W/m²K) | I25: Q [kWh/y] | Q25: 15 – 25 | R25: 3 | S25: =R25/2 -> 1.5 | T25: 2 | U25: =(T25+S25+R25)/3 -> 2.1666667 | V25: =U25+T25+S25+R25 -> 8.6666667
Q26: 32 – 50 | R26: 7 | S26: =R26/2 -> 3.5 | T26: 4 | U26: =(T26+S26+R26)/3 -> 4.8333333 | V26: =U26+T26+S26+R26 -> 19.333333
Q27: 65 – 100 | R27: 24 | S27: =R27/2 -> 12 | T27: 10 | U27: =(T27+S27+R27)/3 -> 15.333333 | V27: =U27+T27+S27+R27 -> 61.333333
B28: Before renovation | C28: =C16 -> 3-DMTT | D28: Chugun | E28: 10 | F28: 1.2 | G28: =E28*F28 -> 12 | H28: 9
O32: CAPEX
P33: Unit cost [USD] | Q33: Units
C34: Radiatorlarni almashtirish (15% samaradorlik) | O34: Bimetal radiators with an average dimension of 500x800mm equiped with antivandal type mechanical thermostatic valve, fitings and labour.
B35: After renovation | O35: Bitubular distribution of PP-RCT/PP-RCT+BF/PP-RCT pipe insulated with expended polyethene with a thickness of at least 25mm including fitings.
O36: Labour for uninstall the old system and install the new one.
O37: Heating system replacement | R37: 18000
O38: in case of external networks, using pipes 65-100mm: 1. to replace the description with: Steel electric welved pipe, placed in concrete channels at 1m depth in the ground, treated with anticorrosion, insulated with high density MW of at least 40mm covered with aluminum foil including fitings and labour. Asphalt or tile rehabilitaiton included. 2. to replace unit price of 61 USD/m2 with 340 USD/m2
B42: Heat savings from heat distribution system

Sheet DHW generation
B2: Before implementation
B3: Descriotion of source | C3: Energy used for DHW preparation | D3: Consumption [litres/person * day] | E3: No of persons | F3: During heating season | H3: Outside heating season | J3: Conversion coeff. | K3: Q [kWh/y] | R3: Electrical energy
F4: ΔT [°C] | G4: Working days [days/y] | H4: ΔT [°C] | I4: Working days [days/y] | R4: Other energy
B5: ARISTON | C5: Electrical energy | D5: 15 | E5: 13 | F5: =60-5 -> 55 | G5: =Building_data!$D$7 -> 163 | H5: =60-15 -> 45 | I5: =365-G5 -> 202 | J5: 1.163 | K5: =D5*E5*((F5*G5)+(H5*I5))*J5/1000 -> 4094.6032
D6: 15 | F6: =60-5 -> 55 | G6: =Building_data!$D$7 -> 163 | H6: =60-15 -> 45 | I6: =365-G6 -> 202 | J6: 1.163 | K6: =D6*E6*((F6*G6)+(H6*I6))*J6/1000 -> 0
D7: 15 | F7: =60-5 -> 55 | G7: =Building_data!$D$7 -> 163 | H7: =60-15 -> 45 | I7: =365-G7 -> 202 | J7: 1.163 | K7: =D7*E7*((F7*G7)+(H7*I7))*J7/1000 -> 0
D8: 15 | F8: =60-5 -> 55 | G8: =Building_data!$D$7 -> 163 | H8: =60-15 -> 45 | I8: =365-G8 -> 202 | J8: 1.163 | K8: =D8*E8*((F8*G8)+(H8*I8))*J8/1000 -> 0
D9: 15 | F9: =60-5 -> 55 | G9: =Building_data!$D$7 -> 163 | H9: =60-15 -> 45 | I9: =365-G9 -> 202 | J9: 1.163 | K9: =D9*E9*((F9*G9)+(H9*I9))*J9/1000 -> 0
D10: 15 | F10: =60-5 -> 55 | G10: =Building_data!$D$7 -> 163 | H10: =60-15 -> 45 | I10: =365-G10 -> 202 | J10: 1.163 | K10: =D10*E10*((F10*G10)+(H10*I10))*J10/1000 -> 0
D11: 15 | F11: =60-5 -> 55 | G11: =Building_data!$D$7 -> 163 | H11: =60-15 -> 45 | I11: =365-G11 -> 202 | J11: 1.163 | K11: =D11*E11*((F11*G11)+(H11*I11))*J11/1000 -> 0
D12: 15 | F12: =60-5 -> 55 | G12: =Building_data!$D$7 -> 163 | H12: =60-15 -> 45 | I12: =365-G12 -> 202 | J12: 1.163 | K12: =D12*E12*((F12*G12)+(H12*I12))*J12/1000 -> 0
D13: 15 | F13: =60-5 -> 55 | G13: =Building_data!$D$7 -> 163 | H13: =60-15 -> 45 | I13: =365-G13 -> 202 | J13: 1.163 | K13: =D13*E13*((F13*G13)+(H13*I13))*J13/1000 -> 0
D14: 15 | F14: =60-5 -> 55 | G14: =Building_data!$D$7 -> 163 | H14: =60-15 -> 45 | I14: =365-G14 -> 202 | J14: 1.163 | K14: =D14*E14*((F14*G14)+(H14*I14))*J14/1000 -> 0
D15: 15 | F15: =60-5 -> 55 | G15: =Building_data!$D$7 -> 163 | H15: =60-15 -> 45 | I15: =365-G15 -> 202 | J15: 1.163 | K15: =D15*E15*((F15*G15)+(H15*I15))*J15/1000 -> 0
B16: Total electrical energy needs for DHW preparation | K16: =SUM(IF(C5="Electrical energy",K5,"0"),IF(C6="Electrical energy",K6,"0"),IF(C7="Electrical energy",K7,"0"),IF(C8="Electrical energy",K8,"0"),IF(C9="Electrical energy",K9,"0"),IF(C10="Electrical energy",K10,"0"),IF(C11="Electrical energy",K11,"0"),IF(C12="Electrical energy",K12,"0"),IF(C13="Electrical energy",K13,"0"),IF(C14="Electrical energy",K14,"0"),IF(C15="Electrical energy",K15,"0")) -> 4094.6032
B17: Total other energy needs for DHW preparation | K17: =SUM(IF(C5="Other energy",K5,"0"),IF(C6="Other energy",K6,"0"),IF(C7="Other energy",K7,"0"),IF(C8="Other energy",K8,"0"),IF(C9="Other energy",K9,"0"),IF(C10="Other energy",K10,"0"),IF(C11="Other energy",K11,"0"),IF(C12="Other energy",K12,"0"),IF(C13="Other energy",K13,"0"),IF(C14="Other energy",K14,"0"),IF(C15="Other energy",K15,"0")) -> 0
B18: Total energy needs for DHW preparation | K18: =SUM(K5:K15) -> 4094.6032
B20: After implementation
B21: Descriotion of source | C21: Energy used for DHW preparation | D21: Consumption [litres/person * day] | E21: No of persons | F21: During heating season | H21: Outside heating season | J21: Conversion coeff. | K21: Q [kWh/y]
F22: ΔT [°C] | G22: Working days [days/y] | H22: ΔT [°C] | I22: Working days [days/y]
B23: =B5 -> ARISTON | C23: =C5 -> Electrical energy | D23: 15 | E23: =E5 -> 13 | F23: =60-5 -> 55 | G23: =Building_data!$D$7 -> 163 | H23: =60-15 -> 45 | I23: =365-G23 -> 202 | J23: 1.163 | K23: =D23*E23*((F23*G23)+(H23*I23))*J23/1000 -> 4094.6032
D24: 15 | F24: =60-5 -> 55 | G24: =Building_data!$D$7 -> 163 | H24: =60-15 -> 45 | I24: =365-G24 -> 202 | J24: 1.163 | K24: 0
D25: 15 | F25: =60-5 -> 55 | G25: =Building_data!$D$7 -> 163 | H25: =60-15 -> 45 | I25: =365-G25 -> 202 | J25: 1.163 | K25: =D25*E25*((F25*G25)+(H25*I25))*J25/1000 -> 0
D26: 15 | F26: =60-5 -> 55 | G26: =Building_data!$D$7 -> 163 | H26: =60-15 -> 45 | I26: =365-G26 -> 202 | J26: 1.163 | K26: =D26*E26*((F26*G26)+(H26*I26))*J26/1000 -> 0
D27: 15 | F27: =60-5 -> 55 | G27: =Building_data!$D$7 -> 163 | H27: =60-15 -> 45 | I27: =365-G27 -> 202 | J27: 1.163 | K27: =D27*E27*((F27*G27)+(H27*I27))*J27/1000 -> 0
D28: 15 | F28: =60-5 -> 55 | G28: =Building_data!$D$7 -> 163 | H28: =60-15 -> 45 | I28: =365-G28 -> 202 | J28: 1.163 | K28: =D28*E28*((F28*G28)+(H28*I28))*J28/1000 -> 0
D29: 15 | F29: =60-5 -> 55 | G29: =Building_data!$D$7 -> 163 | H29: =60-15 -> 45 | I29: =365-G29 -> 202 | J29: 1.163 | K29: =D29*E29*((F29*G29)+(H29*I29))*J29/1000 -> 0
D30: 15 | F30: =60-5 -> 55 | G30: =Building_data!$D$7 -> 163 | H30: =60-15 -> 45 | I30: =365-G30 -> 202 | J30: 1.163 | K30: =D30*E30*((F30*G30)+(H30*I30))*J30/1000 -> 0
D31: 15 | F31: =60-5 -> 55 | G31: =Building_data!$D$7 -> 163 | H31: =60-15 -> 45 | I31: =365-G31 -> 202 | J31: 1.163 | K31: =D31*E31*((F31*G31)+(H31*I31))*J31/1000 -> 0
D32: 15 | F32: =60-5 -> 55 | G32: =Building_data!$D$7 -> 163 | H32: =60-15 -> 45 | I32: =365-G32 -> 202 | J32: 1.163 | K32: =D32*E32*((F32*G32)+(H32*I32))*J32/1000 -> 0
D33: 15 | F33: =60-5 -> 55 | G33: =Building_data!$D$7 -> 163 | H33: =60-15 -> 45 | I33: =365-G33 -> 202 | J33: 1.163 | K33: =D33*E33*((F33*G33)+(H33*I33))*J33/1000 -> 0
B34: Total electrical energy needs for DHW preparation | K34: =SUM(IF(C23="Electrical energy",K23,"0"),IF(C24="Electrical energy",K24,"0"),IF(C25="Electrical energy",K25,"0"),IF(C26="Electrical energy",K26,"0"),IF(C27="Electrical energy",K27,"0"),IF(C28="Electrical energy",K28,"0"),IF(C29="Electrical energy",K29,"0"),IF(C30="Electrical energy",K30,"0"),IF(C31="Electrical energy",K31,"0"),IF(C32="Electrical energy",K32,"0"),IF(C33="Electrical energy",K33,"0")) -> 4094.6032
B35: Total other energy needs for DHW preparation | K35: =SUM(IF(C23="Other energy",K23,"0"),IF(C24="Other energy",K24,"0"),IF(C25="Other energy",K25,"0"),IF(C26="Other energy",K26,"0"),IF(C27="Other energy",K27,"0"),IF(C28="Other energy",K28,"0"),IF(C29="Other energy",K29,"0"),IF(C30="Other energy",K30,"0"),IF(C31="Other energy",K31,"0"),IF(C32="Other energy",K32,"0"),IF(C33="Other energy",K33,"0")) -> 0
B36: Total energy needs for DHW preparation | K36: =SUM(K23:K33) -> 4094.6032

Sheet DHW distr. efficiency
C3: Building name | D3: Interior nominal diameter of pipe (DN), [mm] | E3: Length [m] | F3: Percentage of insulated pipes | G3: Length of insulated pipes [m] | H3: Length of non-insulated pipes [m] | I3: Losses through non-insulated pipes [W/m] | J3: Losses through insulated pipes [W/m] | K3: Hours per year [h/y] | L3: Q [kWh/y]
P4: Pierderea maximă a densităţii fluxului de căldură prin țevi izolate în spații neîncălzite, [W/m]
P5: Diametrul nominal interior al conductei (DN), [mm] | Q5: Temperatura medie a agentului termic, [°C]
B6: Before renovation
Q8: ≤50 | R8: 60 assumed | S8: 70 | T8: 80 | U8: ≥90 | W8: 60
I9: =IFERROR(VLOOKUP(D9,$P$17:$Q$19,2,FALSE),"") | J9: =IFERROR(VLOOKUP(D9,$P$9:$R$11,3,FALSE),"") | P9: 15 – 25 | Q9: 7 | R9: =W9/75*'DHW generation'!$D$5 -> 2.2 | S9: 13 | T9: 14 | U9: 16 | W9: 11
I10: =IFERROR(VLOOKUP(D10,$P$17:$Q$19,2,FALSE),"") | J10: =IFERROR(VLOOKUP(D10,$P$9:$R$11,3,FALSE),"") | P10: 32 – 50 | Q10: 10 | R10: =W10/75*'DHW generation'!$D$5 -> 2.8 | S10: 16 | T10: 18 | U10: 21 | W10: 14
I11: =IFERROR(VLOOKUP(D11,$P$17:$Q$19,2,FALSE),"") | J11: =IFERROR(VLOOKUP(D11,$P$9:$R$11,3,FALSE),"") | P11: 65 – 100 | Q11: 14 | R11: =W11/75*'DHW generation'!$D$5 -> 3.8 | S11: 22 | T11: 25 | U11: 29 | W11: 19
C12: Total heat losses through DHW distribution system before renovation | L12: =SUM(L6:L11) -> 0
B13: After renovation
P14: Pierderea maximă a densității fluxului de căldură prin țevi neizolate în spații neîncălzite, [W/m]
P15: Diametrul nominal interior al conductei (DN), [mm] | Q15: Temperatura medie a agentului termic asumata – 60[°C] | R15: Temperatura medie a agentului termic – 60[°C]
P17: 15 – 25 | Q17: =R17/75*'DHW generation'!$D$5 -> 9.4 | R17: 47
P18: 32 – 50 | Q18: =R18/75*'DHW generation'!$D$5 -> 14.8 | R18: 74
C19: Total heat losses through DHW distribution system after renovation | L19: =SUM(L13:L18) -> 0 | P19: 65 – 100 | Q19: =R19/75*'DHW generation'!$D$5 -> 28 | R19: 140
B20: Heat savings from DHW distribution system | L20: =L12-L19 -> 0
P26: Costs to be applied in CAPEX
P27: Diameter | Q27: Pipe price [USD/m] | R27: Fitings [USD] | S27: Insulation price [USD/m] | T27: Labour [USD] | U27: Total [USD/m]
P28: 15 – 25 | Q28: 3 | R28: =Q28/2 -> 1.5 | S28: 2 | T28: =(S28+R28+Q28)/3 -> 2.1666667 | U28: =T28+S28+R28+Q28 -> 8.6666667
P29: 32 – 50 | Q29: 7 | R29: =Q29/2 -> 3.5 | S29: 4 | T29: =(S29+R29+Q29)/3 -> 4.8333333 | U29: =T29+S29+R29+Q29 -> 19.333333
P30: 65 – 100 | Q30: 24 | R30: =Q30/2 -> 12 | S30: 10 | T30: =(S30+R30+Q30)/3 -> 15.333333 | U30: =T30+S30+R30+Q30 -> 61.333333
M31: CAPEX
M32: Pipe diameter | N32: Description | O32: Unit cost [USD/m] | P32: Length [m] | Q32: Total [USD]
M33: 15-25 | N33: PP-RCT/PP-RCT+BF/PP-RCT pipe insulated with expended polyethene with a thickness of at least 20mm including fitings and labour | O33: 15 | Q33: =O33*P33 -> 0
M34: 32-50 | N34: PP-RCT/PP-RCT+BF/PP-RCT pipe insulated with expended polyethene with a thickness of at least 25mm including fitings and labour | O34: 28 | Q34: =O34*P34 -> 0
M35: 65-100 | N35: Steel electric welved pipe, treated with anticorrosion, insulated with high density MW of at least 40mm covered with aluminum foil including fitings and labour | O35: =U30 -> 61.333333 | Q35: =O35*P35 -> 0
M36: Labour | Q36: =SUM(Q33:Q35)*0.5 -> 0
M37: Other unforeseen works | Q37: =SUM(Q33:Q36)*0.2 -> 0
M38: DHW distribution system replacement | Q38: =SUM(Q33:Q37) -> 0
M40: in case of external networks, using pipes 65-100mm: 1. to replace the description with: Steel electric welved pipe, placed in concrete channels at 1m depth in the ground, treated with anticorrosion, insulated with high density MW of at least 40mm covered with aluminum foil including fitings and labour. Asphalt or tile rehabilitaiton included. 2. to replace unit price of 61 EUR/m2 with 340 EUR/m2

Sheet IHS
B3: Modernization of IHS
B4: Individual Heat Substation with weather compensation control
B5: Heat exchanger for heating [kW]
B6: Heat exchanger for DHW [kW]
B7: Heat exchanger for ventilation [kW]
B8: Savings [kWh/y]
B10: CAPEX for IHS with weather compensation control | C10: EUR
B11: Heat exchanger for heating system in prefabricated insulation | C11: =C5*25 -> 0
B12: Heat exchanger for DHW in prefabricated insulation | C12: =C6*25 -> 0
B13: Heat exchanger for ventilation in prefabricated insulation | C13: =C7*25 -> 0
B14: Circulation pumps, working & reserve for heating system equipped with frequency drive in prefabricated insulation | C14: =(C11/100)*60*2 -> 0
B15: Circulation pumps, working & reserve for DHW equipped with frequency drive in prefabricated insulation | C15: =(C12/100)*60*2 -> 0
B16: Circulation pumps, working & reserve for ventilation system equipped with frequency drive in prefabricated insulation | C16: =(C13/100)*60*2 -> 0
B17: Water treatment station | C17: 0
B18: Accessories (valves, anemometers, thermometers, insulation etc.) | C18: =(C11+C12+C13)*0.05 -> 0
B19: Automatization | C19: 0
B20: Labour | C20: =(SUM(C11:C19))*0.1 -> 0
B21: Total | C21: 22770

Sheet Lighting
B4: Annual electricity consumption for artificial lighting before and after renovation
C5: Name of the Building | D5: Area [m²] | E5: Floor ratio covered by various lighting sources | I5: Average installed power per sq m including losses [W/m²] | J5: Operation hours per year [h/y] | K5: Utilization factor | L5: Annual energy consumption [kWh/y] | V5: Percentage share by room types in hospital institutions
E6: Incandescent | F6: Fluorescent | G6: Fluorescent | H6: LED | Q6: Normative values for hospitals - average | V6: Nr. | W6: Nivel de iluminat, lx | X6: Cota %
B7: Before renovation | I7: =(E7*$R$8)+(F7*$R$9)+(G7*$R$10)+(H7*$R$11) -> 0 | K7: 0.3 | L7: =(D7*I7*J7*K7)/1000 -> 0 | Q7: Source | R7: W/m2 | V7: 1 | W7: 20 | X7: 0,1
C8: ='Ventilation losses'!C44 -> 3-DMTT | D8: =Envelope!L95 -> 2515.415 | E8: 0.01 | F8: 0.98 | G8: 0 | H8: 0.01 | I8: =(E8*$R$8)+(F8*$R$9)+(G8*$R$10)+(H8*$R$11) -> 17.768 | J8: =Building_data!D12 -> 1630 | K8: 0.55 | L8: =(D8*I8*J8*K8)/1000 -> 40068.076 | Q8: Incandescent | R8: 25 | S8: do not ensure 300 lx | V8: 2 | W8: 30 | X8: 0,5
I9: =(E9*$R$8)+(F9*$R$9)+(G9*$R$10)+(H9*$R$11) -> 0 | K9: 0.3 | L9: =(D9*I9*J9*K9)/1000 -> 0 | Q9: Fluorescent, electromagnetic ballast, 4x18W | R9: 17.8 | V9: 3 | W9: 50 | X9: 1,5
I10: =(E10*$R$8)+(F10*$R$9)+(G10*$R$10)+(H10*$R$11) -> 0 | K10: 0.3 | L10: =(D10*I10*J10*K10)/1000 -> 0 | Q10: Fluorescent, electronic ballast, 4x18 | R10: 14.81 | V10: 4 | W10: 75 | X10: 1,75
C11: Total annual energy consumption for artificial lighting before renovation | L11: =SUM(L7:L10) -> 40068.076 | Q11: LED 600x600 mm, 37W, 3684 lm | R11: 7.4 | V11: 5 | W11: 100 | X11: 2,25
B12: After renovation | I12: =(E12*$R$8)+(F12*$R$9)+(G12*$R$10)+(H12*$R$11) -> 0 | J12: =J7 -> 0 | K12: =K7 -> 0.3 | L12: =(D12*I12*J12*K12)/1000 -> 0 | V12: 6 | W12: 150 | X12: 3,5
C13: =C8 -> 3-DMTT | D13: =D8 -> 2515.415 | E13: 0 | F13: 0 | G13: 0 | H13: 1 | I13: =(E13*$R$8)+(F13*$R$9)+(G13*$R$10)+(H13*$R$11) -> 7.4 | J13: =J8 -> 1630 | K13: =K8 -> 0.55 | L13: =(D13*I13*J13*K13)/1000 -> 16687.515 | V13: 7 | W13: 200 | X13: 6,4
D14: =D9 -> 0 | I14: =(E14*$R$8)+(F14*$R$9)+(G14*$R$10)+(H14*$R$11) -> 0 | J14: =J9 -> 0 | K14: =K9 -> 0.3 | L14: =(D14*I14*J14*K14)/1000 -> 0 | V14: 8 | W14: 300 | X14: 60
D15: =D10 -> 0 | I15: =(E15*$R$8)+(F15*$R$9)+(G15*$R$10)+(H15*$R$11) -> 0 | J15: =J10 -> 0 | K15: =K10 -> 0.3 | L15: =(D15*I15*J15*K15)/1000 -> 0 | V15: 9 | W15: 400 | X15: 16
C16: Total annual energy consumption for artificial lighting after renovation | L16: =SUM(L12:L15) -> 16687.515 | V16: 10 | W16: 500 | X16: 8
B17: Electricity savings | L17: =L11-L16 -> 23380.561 | V17: Average 300 lx considered
C19: CAPEX
C20: Installation of LED lighting and replacing of distribution system | P20: Specific powers of general lighting according to lighting levels for rooms in hospital institutions
C21: Description | D21: Cost [USD/m²] | E21: Surface | F21: Total Investment [USD] | P21: N | Q21: Names of rooms | R21: The value of lighting, Emin, lx | S21: Area | T21: LED | U21: FLUO-T8 | V21: FLUO-T8 | W21: INCANDES,
C22: Instalaltion of LED lighting and replacing of interior electrical distribution system. LED lumminaires to be selected in-line with results of simulation from DIALUX for each specific space according to the destination and normative requirements. LED lighting sources placed in commonly used spaces to be equipped with presence sensors. All wiring to be replaced, including electrical cabinets, switches and plugs | D22: 21 | E22: =SUMIF(H12:H15,100%,D12:D15) -> 2515.415 | F22: 30000 | S22: m2 | T22: W/m2 | U22: -BALAST ELECTRONIC, | V22: -BALAST ELECTROM. W/m2 | W22: W/m2
U23: W/m2
P24: 1 | Q24: Delivery room, dialysis, resuscitation rooms, anesthesia, toilet for newborns; Bandage room (clean, purulent, plaster sectors); Angiography room; Offices for surgeons, obstetricians, gynecologists, traumatologists, paediatricians, specialists in infectious diseases, dermatovenerologists, allergists, dentists, examination, reception and examination boxes; Urgent analysis room, booths, serological examination rooms, colorimetric rooms, clerical laboratory; Working room for dental technicians, amalgam sector; Room for plaster, polymerisation; Rooms for epidemiologists, bacteriologists, booths for serological studies of particularly dangerous infections; | R24: 500 | S24: xx | T24: 11,42 | U24: 24,69 | V24: 35,5 | W24: -
Q25: Rooms for the zoo-parasitologist for the reception and analysis of material infected with dangerous infections; Procedure room, handling, blood transfusion, BCG, defibrillation, acupuncture, pneumothorax;
P26: 2 | Q26: Operating room, hypothymia room, cystoscopy; Installation chambers for cardiopulmonary bypass, artificial kidney, etc.; | R26: 400 | S26: xx | T26: 9,55 | U26: 22,0 | V26: 26,66 | W26: -
Q27: Intracavitary gamma-therapy cabin; The dissection-autopsy room; Rooms for entomologists, helminthologists, virologists, bacteriologists, laboratory, chemical, biochemical laboratories, serological boxes, preparation rooms; Vivarium. Rooms for keeping animals;
Q28: Procedure rooms: bacteriology, virology, toxicology; The offices of the chief physician, the deputy chief physician, the head of department;
P29: 3 | Q29: Preoperative room, room for observation during operations; Doctors' offices in outpatient clinics not listed above; Medical offices without receiving patients, staff room, training room / acquisition of methods; Occupational therapy; | R29: 300 | S29: xx | T29: 7,4 | U29: 14,8 | V29: 17,8 | W29: -
Q30: X-ray operating unit: X-ray operating room; X-ray computed tomography room: procedure room;
Q31: Roentgen-therapy room: procedure room; Radiometry room, dosimetry; Radiotherapy room with high energy radiation, scanner room; Preparation and general clinical, hematological and biochemical, bacteriological, histological and cytological laboratories;
Q32: Medical laboratory offices, blood sampling, cytological sampling, coagulography, photometry; Weighing room, thermostatic room, medium preparation room with medium pouring box, room for staining samples, centrifuge; Room for the repair and sharpening of surgical instruments; Rooms for the study of autopsy and biopsy material; Departments of radiology, radiochemistry, spectroscopy and polarography Rooms, acoustics laboratories, vibrations, electromagnetic fields, work physiology, can cooking, termite; Laundries;
Q33: Încăperi pentru preluarea de probe; Încăpere de preluare biotest, Încăperi pentru depozitarea mediilor nutritive, pre-box;
Q34: Dispatch room for receiving calls and directing emergency service crews; Milk filtering and bottling room; Room for the preparation of fermented dairy products and lactic acid mixtures; Rooms for the preparation and packaging of cow's cheese; Rooms for the preparation of fruits, vegetables and the preparation of fruit and vegetable mixtures, Rooms for the preparation of fish, meat and the preparation of fish and meat cuts; Offices of nurses, housewives, on-call nurse positions;
Q35: Guard post;
P36: 4 | Q36: Fotarii, rooms for electroluminotherapy, aeroionotherapy, thermotherapy, kinetherapy, massage, mechanotherapy, ultrasound, UHF; | R36: 200 | S36: xx | T36: 4,7 | U36: 10,9 | V36: 13,0 | W36: -
Q37: X-ray bronchoscopy and laparoscopy; The roentgen-diagnostic room, the roentgenoscopy procedure room, the generator room;
Q38: photo examination room of x-ray departments; Storage room for analyzes of patients undergoing research, extracts of solid and liquid radioactive waste; Wards of children's wards for newborns, postoperative wards, intensive care and glaucoma wards, filters and reception boxes, isolator; Rooms for receiving, issuing and recording tests, receiving and sorting samples;
Q39: Rooms with booths for duodenal sounding and gastric juice collection; Glass blowing room; Linear sector, to be glued;
Q40: Spălătorie vase; Sector sterilizare în autoclav; Încăpere pentru recepția și depozitarea materialelor sterile, depozit pentru depozitarea materialelor sterile; Încăpere pentru pregătirea instrumentelor chirurgicale pentru sterilizare; Camera de pre-secționare-autopsie, de fixare; Încăperi pentru îmbrăcarea cadavrelor, sala de înmormântare; Secții de expediere, ambalare, Încăperi pentru depozitare și distribuție de momeli gata preparate, distribuție de dezinfectanți și preparate bacteriene; Încăperi de dezinfectare, secții de spălare; Izolatoare pentru animale infecțioase, carantine; Sala preparare a bucătăriilor; Sala de posturi radio; Sala echipelor de teren;
Q41: Încăperi pentru recepția și păstrarea veselei; Camera de distribuție; Sala de control (panouri de control) in secțiile radiologice etc.;
Q42: Camere de zi, pentru conversații cu medicul, hrănirea copiilor sub 1 an, extragerea laptelui matern și sterilizarea acestuia; Registratura;
P43: 5 | Q43: Blood storage room; Functional diagnostic rooms, endoscopy rooms; Hydrotherapy, therapeutic baths, shower rooms; | R43: 150 | S43: xx | T43: 3,65 | U43: 7,41 | V43: 8,89 | W43: 28,5
Q44: Hall with oxygenation barochambers; procedure room for fluography; engineering room; Room for keeping: laboratory vessels;
Q45: Rooms for storing disinfection equipment and inventory, dirty and clean linen; Rooms of the current stock of medicines; Central material and linen rooms; Corridors in operating theaters, maternity wards, resuscitation and intensive care units, waiting corridors in ambulatory institutions and polyclinics; Corridors in lounge sections, main halls;
P46: 6 | Q46: Changing room area; waiting room; barium preparation booth; Condenser room; Storage of radioactive substances; | R46: 100 | S46: xx | T46: 2,5 | U46: 5,9 | V46: 4,9 | W46: 20,5
Q47: Lounges of psychiatric wards; Other lounges and bedrooms for mothers; Room for keeping: reagents; Storage rooms for biological, medical and diagnostic products, reagents, disinfectants, acids; Storage rooms for mobile team boxes;
Q48: Dairy cooling room; Staircase, vestibule;
P49: 7 | Q49: Room for keeping and preparing plaster; Rooms for the preparation of paraffin, ozokerite, treatment of pads, washing and drying of sheets, cloths, tarpaulins, regeneration of mud; photo lab; The room of the disinfection rooms; Small animal and waste incineration rooms; Crematories for small animals; Feed room; Rooms for washing and sterilizing dishes, washing and drying films, sanitary room, rooms for enemas, sanitary filters; Passage corridors, vestibules; | R49: 75 | S49: xx | T49: 1,85 | U49: 3,7 | V49: 3,9 | W49: 16,5
P51: 8 | Q51: Sleep treatment room; the control room of the x-ray departments, the x-ray operations unit, the x-ray computed tomography room; Rooms for keeping dead bodies; Rooms for funeral accessories; | R51: 50 | S51: xx | T51: 1,23 | U51: 1,44 | V51: 1728 | W51: 9,26
P52: 9 | Q52: Room for temporary storage of roentgen film; Disinfectant storage room; Rooms and places for keeping portable equipment, stands; Lockers and sheds for storing patient belongings, for clean linen, Sorting rooms and linen storage. | R52: 30 | S52: xx | T52: 0,64 | U52: 0,72 | V52: 0,864 | W52: 4,85
P53: 10 | Q53: Dark rooms for ophthalmologists, soundproof cabin | R53: 20 | S53: xx | T53: 0,58 | U53: 0,576 | V53: 0,864 | W53: 3,09

Sheet Equipment
B1: Electric devices before renovation
B2: No. | C2: Electric device (or devices group) | D2: Power unit [kW] | E2: Units | F2: Total Power kW | G2: Hours of operation [hours] | I2: Utilization coeficient | K2: Annual consumption [kWh/y]
G3: During heating season | H3: During cooling season | I3: During heating season | J3: During cooling season
C4: =Envelope!$B$7 -> 3-DMTT
C5: Electrical technological devices | K5: =IF(ISNUMBER(F5),F5*G5*I5+F5*H5*J5,"")
B6: 1 | C6: TV | D6: 0.2 | E6: 13 | F6: =D6*E6 -> 2.6 | G6: 120 | H6: 120 | I6: 0.36 | J6: 0.37 | K6: =IF(ISNUMBER(F6),F6*G6*I6+F6*H6*J6,"") -> 227.76 | M6: =IF(ISNUMBER(F6),F6*H6*J6,"") -> 115.44
B7: 2 | K7: =IF(ISNUMBER(F7),F7*G7*I7+F7*H7*J7,"") | M7: =IF(ISNUMBER(F7),F7*H7*J7,"")
B8: 3 | C8: Dazmol | D8: 2.5 | E8: 1 | F8: =D8*E8 -> 2.5 | G8: 125 | H8: 125 | I8: 0.48 | J8: 0.47 | K8: =IF(ISNUMBER(F8),F8*G8*I8+F8*H8*J8,"") -> 296.875 | M8: =IF(ISNUMBER(F8),F8*H8*J8,"") -> 146.875
B9: 4 | F9: =D9*E9 -> 0 | K9: =IF(ISNUMBER(F9),F9*G9*I9+F9*H9*J9,"") -> 0 | M9: =IF(ISNUMBER(F9),F9*H9*J9,"") -> 0
B10: 5 | F10: =D10*E10 -> 0 | K10: =IF(ISNUMBER(F10),F10*G10*I10+F10*H10*J10,"") -> 0 | M10: =IF(ISNUMBER(F10),F10*H10*J10,"") -> 0
B11: 6 | F11: =D11*E11 -> 0 | K11: =IF(ISNUMBER(F11),F11*G11*I11+F11*H11*J11,"") -> 0 | M11: =IF(ISNUMBER(F11),F11*H11*J11,"") -> 0
B12: 7 | F12: =D12*E12 -> 0 | K12: =IF(ISNUMBER(F12),F12*G12*I12+F12*H12*J12,"") -> 0 | M12: =IF(ISNUMBER(F12),F12*H12*J12,"") -> 0
B13: 8 | F13: =D13*E13 -> 0 | K13: =IF(ISNUMBER(F13),F13*G13*I13+F13*H13*J13,"") -> 0 | M13: =IF(ISNUMBER(F13),F13*H13*J13,"") -> 0
B14: 9 | F14: =D14*E14 -> 0 | K14: =IF(ISNUMBER(F14),F14*G14*I14+F14*H14*J14,"") -> 0 | M14: =IF(ISNUMBER(F14),F14*H14*J14,"") -> 0
B15: 10 | F15: =D15*E15 -> 0 | K15: =IF(ISNUMBER(F15),F15*G15*I15+F15*H15*J15,"") -> 0 | M15: =IF(ISNUMBER(F15),F15*H15*J15,"") -> 0
B16: 11 | F16: =D16*E16 -> 0 | K16: =IF(ISNUMBER(F16),F16*G16*I16+F16*H16*J16,"") -> 0 | M16: =IF(ISNUMBER(F16),F16*H16*J16,"") -> 0
B17: 12 | F17: =D17*E17 -> 0 | K17: =IF(ISNUMBER(F17),F17*G17*I17+F17*H17*J17,"") -> 0 | M17: =IF(ISNUMBER(F17),F17*H17*J17,"") -> 0
C18: Technological equipment (kitchen) | K18: =IF(ISNUMBER(F18),F18*G18*I18+F18*H18*J18,"") | M18: =IF(ISNUMBER(F18),F18*H18*J18,"")
B19: 1 | C19: Termos | D19: 1.5 | E19: 2 | F19: =D19*E19 -> 3 | G19: 125 | H19: 125 | I19: 0.48 | J19: 0.47 | K19: =IF(ISNUMBER(F19),F19*G19*I19+F19*H19*J19,"") -> 356.25 | M19: =IF(ISNUMBER(F19),F19*H19*J19,"") -> 176.25
B20: 2 | K20: =IF(ISNUMBER(F20),F20*G20*I20+F20*H20*J20,"") | M20: =IF(ISNUMBER(F20),F20*H20*J20,"")
B21: 3 | C21: Electric stove | D21: 15 | E21: 2 | F21: =D21*E21 -> 30 | G21: 500 | H21: 500 | I21: 0.52 | J21: 0.54 | K21: =IF(ISNUMBER(F21),F21*G21*I21+F21*H21*J21,"") -> 15900 | M21: =IF(ISNUMBER(F21),F21*H21*J21,"") -> 8100
B22: 4 | C22: Meat grinder | D22: 1 | E22: 1 | F22: =D22*E22 -> 1 | G22: 140 | H22: 140 | I22: 0.45 | J22: 0.46 | K22: =IF(ISNUMBER(F22),F22*G22*I22+F22*H22*J22,"") -> 127.4 | M22: =IF(ISNUMBER(F22),F22*H22*J22,"") -> 64.4
B23: 5 | C23: Refrigerators (new) | D23: 0.8 | E23: 3 | F23: =D23*E23 -> 2.4 | G23: 467 | H23: 467 | I23: 0.63 | J23: 0.64 | K23: =IF(ISNUMBER(F23),F23*G23*I23+F23*H23*J23,"") -> 1423.416 | M23: =IF(ISNUMBER(F23),F23*H23*J23,"") -> 717.312
B24: 6 | C24: Refrigerators (old) | D24: 1.2 | E24: 2 | F24: =D24*E24 -> 2.4 | G24: 467 | H24: 467 | I24: 0.63 | J24: 0.64 | K24: =IF(ISNUMBER(F24),F24*G24*I24+F24*H24*J24,"") -> 1423.416 | M24: =IF(ISNUMBER(F24),F24*H24*J24,"") -> 717.312
B25: 7 | F25: =D25*E25 -> 0 | K25: =IF(ISNUMBER(F25),F25*G25*I25+F25*H25*J25,"") -> 0 | M25: =IF(ISNUMBER(F25),F25*H25*J25,"") -> 0
B26: 8 | F26: =D26*E26 -> 0 | K26: =IF(ISNUMBER(F26),F26*G26*I26+F26*H26*J26,"") -> 0 | M26: =IF(ISNUMBER(F26),F26*H26*J26,"") -> 0
B27: 9 | F27: =D27*E27 -> 0 | K27: =IF(ISNUMBER(F27),F27*G27*I27+F27*H27*J27,"") -> 0 | M27: =IF(ISNUMBER(F27),F27*H27*J27,"") -> 0
B28: 10 | F28: =D28*E28 -> 0 | K28: =IF(ISNUMBER(F28),F28*G28*I28+F28*H28*J28,"") -> 0 | M28: =IF(ISNUMBER(F28),F28*H28*J28,"") -> 0
B29: 11 | F29: =D29*E29 -> 0 | K29: =IF(ISNUMBER(F29),F29*G29*I29+F29*H29*J29,"") -> 0 | M29: =IF(ISNUMBER(F29),F29*H29*J29,"") -> 0
B30: 12 | F30: =D30*E30 -> 0 | K30: =IF(ISNUMBER(F30),F30*G30*I30+F30*H30*J30,"") -> 0 | M30: =IF(ISNUMBER(F30),F30*H30*J30,"") -> 0
B31: 13 | F31: =D31*E31 -> 0 | K31: =IF(ISNUMBER(F31),F31*G31*I31+F31*H31*J31,"") -> 0 | M31: =IF(ISNUMBER(F31),F31*H31*J31,"") -> 0
C32: Laundry technological equipment | K32: =IF(ISNUMBER(F32),F32*G32*I32+F32*H32*J32,"") | M32: =IF(ISNUMBER(F32),F32*H32*J32,"")
B33: 1 | C33: Washing machine | D33: 2 | E33: 1 | F33: =D33*E33 -> 2 | G33: 417 | H33: 417 | I33: 0.45 | J33: 0.46 | K33: =IF(ISNUMBER(F33),F33*G33*I33+F33*H33*J33,"") -> 758.94 | M33: =IF(ISNUMBER(F33),F33*H33*J33,"") -> 383.64
C34: Ventilation and air conditioning units | K34: =IF(ISNUMBER(F34),F34*G34*I34+F34*H34*J34,"") | M34: =IF(ISNUMBER(F34),F34*H34*J34,"")
B35: 1 | F35: =D35*E35 -> 0 | K35: =IF(ISNUMBER(F35),F35*G35*I35+F35*H35*J35,"") -> 0
B36: 2
C37: Other electrical devices (computers, coffee machines etc) | K37: =IF(ISNUMBER(F37),F37*G37*I37+F37*H37*J37,"") | M37: =IF(ISNUMBER(F37),F37*H37*J37,"")
B38: 1 | C38: Computers | D38: 0.2 | E38: 2 | F38: =D38*E38 -> 0.4 | G38: 1440 | H38: 1557 | I38: 0.9 | J38: 0.9 | K38: =IF(ISNUMBER(F38),F38*G38*I38+F38*H38*J38,"") -> 1078.92 | M38: =IF(ISNUMBER(F38),F38*H38*J38,"") -> 560.52
B39: 2 | C39: Printers | D39: 1 | E39: 2 | F39: =D39*E39 -> 2 | G39: 143 | H39: 143 | I39: 0.08 | J39: 0.09 | K39: =IF(ISNUMBER(F39),F39*G39*I39+F39*H39*J39,"") -> 48.62 | M39: =IF(ISNUMBER(F39),F39*H39*J39,"") -> 25.74
B40: 3 | C40: Proektor | D40: 0.2 | E40: 1 | F40: =D40*E40 -> 0.2 | G40: 217 | H40: 217 | I40: 0.11 | J40: 0.12 | K40: =IF(ISNUMBER(F40),F40*G40*I40+F40*H40*J40,"") -> 9.982 | M40: =IF(ISNUMBER(F40),F40*H40*J40,"") -> 5.208
B41: 4 | F41: =D41*E41 -> 0 | K41: =IF(ISNUMBER(F41),F41*G41*I41+F41*H41*J41,"") -> 0
B42: 5 | F42: =D42*E42 -> 0 | K42: =IF(ISNUMBER(F42),F42*G42*I42+F42*H42*J42,"") -> 0 | M42: =IF(ISNUMBER(F42),F42*H42*J42,"") -> 0
B43: 6 | F43: =D43*E43 -> 0 | K43: =IF(ISNUMBER(F43),F43*G43*I43+F43*H43*J43,"") -> 0 | M43: =IF(ISNUMBER(F43),F43*H43*J43,"") -> 0
B44: 7 | F44: =D44*E44 -> 0 | K44: =IF(ISNUMBER(F44),F44*G44*I44+F44*H44*J44,"") -> 0 | M44: =IF(ISNUMBER(F44),F44*H44*J44,"") -> 0
B45: 8 | F45: =D45*E45 -> 0 | K45: =IF(ISNUMBER(F45),F45*G45*I45+F45*H45*J45,"") -> 0 | M45: =IF(ISNUMBER(F45),F45*H45*J45,"") -> 0
C46: Elevators | K46: =IF(ISNUMBER(F46),F46*G46*I46+F46*H46*J46,"") | M46: =IF(ISNUMBER(F46),F46*H46*J46,"")
B47: 1 | F47: =D47*E47 -> 0 | K47: =IF(ISNUMBER(F47),F47*G47*I47+F47*H47*J47,"") -> 0 | M47: =IF(ISNUMBER(F47),F47*H47*J47,"") -> 0
B48: 2 | F48: =D48*E48 -> 0 | K48: =IF(ISNUMBER(F48),F48*G48*I48+F48*H48*J48,"") -> 0 | M48: =IF(ISNUMBER(F48),F48*H48*J48,"") -> 0
B49: Total annual energy used by equipment before renovation | K49: =SUM(K38:K48)+SUM(K5:K33)-K41 -> 21651.579 | M49: =SUM(M6:M48) -> 11012.697
B51: Electric devices after renovation
B52: No. | C52: Electric device (or devices group) | D52: Power [kW] | E52: Units | F52: Total Power kW | G52: Hours of operation [hours] | I52: Utilization coeficient | K52: Annual consumption [kWh/y]
G53: During heating season | H53: During cooling season | I53: During heating season | J53: During cooling season
C54: =C4 -> 3-DMTT
C55: =C5 -> Electrical technological devices | K55: =IF(ISNUMBER(F55),F55*G55*I55+F55*H55*J55,"")
B56: =B6 -> 1 | C56: =C6 -> TV | D56: =D6 -> 0.2 | E56: =E6 -> 13 | F56: =F6 -> 2.6 | G56: =G6 -> 120 | H56: =H6 -> 120 | I56: =I6 -> 0.36 | J56: =J6 -> 0.37 | K56: =IF(ISNUMBER(F56),F56*G56*I56+F56*H56*J56,"") -> 227.76 | M56: =IF(ISNUMBER(F56),F56*H56*J56,"") -> 115.44
B57: =B7 -> 2 | C57: =C7 -> 0 | D57: =D7 -> 0 | E57: =E7 -> 0 | F57: =F7 -> 0 | G57: =G7 -> 0 | H57: =H7 -> 0 | I57: =I7 -> 0 | J57: =J7 -> 0 | K57: =IF(ISNUMBER(F57),F57*G57*I57+F57*H57*J57,"") -> 0 | M57: =IF(ISNUMBER(F57),F57*H57*J57,"") -> 0
B58: =B8 -> 3 | C58: Dazmol | D58: 2 | E58: 1 | F58: =D58*E58 -> 2 | G58: 125 | H58: 0.48 | I58: 0.47 | J58: =J8 -> 0.47 | K58: =IF(ISNUMBER(F58),F58*G58*I58+F58*H58*J58,"") -> 117.9512 | M58: =IF(ISNUMBER(F58),F58*H58*J58,"") -> 0.4512
B59: =B9 -> 4 | C59: =C9 -> 0 | D59: =D9 -> 0 | E59: =E9 -> 0 | F59: =F9 -> 0 | G59: =G9 -> 0 | H59: =H9 -> 0 | I59: =I9 -> 0 | J59: =J9 -> 0 | K59: =IF(ISNUMBER(F59),F59*G59*I59+F59*H59*J59,"") -> 0 | M59: =IF(ISNUMBER(F59),F59*H59*J59,"") -> 0
B60: =B10 -> 5 | C60: =C10 -> 0 | D60: =D10 -> 0 | E60: =E10 -> 0 | F60: =F10 -> 0 | G60: =G10 -> 0 | H60: =H10 -> 0 | I60: =I10 -> 0 | J60: =J10 -> 0 | K60: =IF(ISNUMBER(F60),F60*G60*I60+F60*H60*J60,"") -> 0 | M60: =IF(ISNUMBER(F60),F60*H60*J60,"") -> 0
B61: =B11 -> 6 | C61: =C11 -> 0 | D61: =D11 -> 0 | E61: =E11 -> 0 | F61: =F11 -> 0 | G61: =G11 -> 0 | H61: =H11 -> 0 | I61: =I11 -> 0 | J61: =J11 -> 0 | K61: =IF(ISNUMBER(F61),F61*G61*I61+F61*H61*J61,"") -> 0 | M61: =IF(ISNUMBER(F61),F61*H61*J61,"") -> 0
B62: =B12 -> 7 | C62: =C12 -> 0 | D62: =D12 -> 0 | E62: =E12 -> 0 | F62: =F12 -> 0 | G62: =G12 -> 0 | H62: =H12 -> 0 | I62: =I12 -> 0 | J62: =J12 -> 0 | K62: =IF(ISNUMBER(F62),F62*G62*I62+F62*H62*J62,"") -> 0 | M62: =IF(ISNUMBER(F62),F62*H62*J62,"") -> 0
B63: =B13 -> 8 | C63: =C13 -> 0 | D63: =D13 -> 0 | E63: =E13 -> 0 | F63: =F13 -> 0 | G63: =G13 -> 0 | H63: =H13 -> 0 | I63: =I13 -> 0 | J63: =J13 -> 0 | K63: =IF(ISNUMBER(F63),F63*G63*I63+F63*H63*J63,"") -> 0 | M63: =IF(ISNUMBER(F63),F63*H63*J63,"") -> 0
B64: =B14 -> 9 | C64: =C14 -> 0 | D64: =D14 -> 0 | E64: =E14 -> 0 | F64: =F14 -> 0 | G64: =G14 -> 0 | H64: =H14 -> 0 | I64: =I14 -> 0 | J64: =J14 -> 0 | K64: =IF(ISNUMBER(F64),F64*G64*I64+F64*H64*J64,"") -> 0 | M64: =IF(ISNUMBER(F64),F64*H64*J64,"") -> 0
B65: =B15 -> 10 | C65: =C15 -> 0 | D65: =D15 -> 0 | E65: =E15 -> 0 | F65: =F15 -> 0 | G65: =G15 -> 0 | H65: =H15 -> 0 | I65: =I15 -> 0 | J65: =J15 -> 0 | K65: =IF(ISNUMBER(F65),F65*G65*I65+F65*H65*J65,"") -> 0 | M65: =IF(ISNUMBER(F65),F65*H65*J65,"") -> 0
B66: =B16 -> 11 | C66: =C16 -> 0 | D66: =D16 -> 0 | E66: =E16 -> 0 | F66: =F16 -> 0 | G66: =G16 -> 0 | H66: =H16 -> 0 | I66: =I16 -> 0 | J66: =J16 -> 0 | K66: =IF(ISNUMBER(F66),F66*G66*I66+F66*H66*J66,"") -> 0 | M66: =IF(ISNUMBER(F66),F66*H66*J66,"") -> 0
B67: =B17 -> 12 | C67: =C17 -> 0 | D67: =D17 -> 0 | E67: =E17 -> 0 | F67: =F17 -> 0 | G67: =G17 -> 0 | H67: =H17 -> 0 | I67: =I17 -> 0 | J67: =J17 -> 0 | K67: =IF(ISNUMBER(F67),F67*G67*I67+F67*H67*J67,"") -> 0 | M67: =IF(ISNUMBER(F67),F67*H67*J67,"") -> 0
C68: =C18 -> Technological equipment (kitchen) | M68: =IF(ISNUMBER(F68),F68*H68*J68,"")
B69: =B19 -> 1 | C69: =C19 -> Termos | D69: =D19 -> 1.5 | E69: =E19 -> 2 | F69: =F19 -> 3 | G69: =G19 -> 125 | H69: =H19 -> 125 | I69: =I19 -> 0.48 | J69: =J19 -> 0.47 | K69: =IF(ISNUMBER(F69),F69*G69*I69+F69*H69*J69,"") -> 356.25 | M69: =IF(ISNUMBER(F69),F69*H69*J69,"") -> 176.25
B70: =B20 -> 2 | C70: =C20 -> 0 | D70: =D20 -> 0 | E70: =E20 -> 0 | F70: =F20 -> 0 | G70: =G20 -> 0 | H70: =H20 -> 0 | I70: =I20 -> 0 | J70: =J20 -> 0 | K70: =IF(ISNUMBER(F70),F70*G70*I70+F70*H70*J70,"") -> 0 | M70: =IF(ISNUMBER(F70),F70*H70*J70,"") -> 0
B71: =B21 -> 3 | C71: =C21 -> Electric stove | D71: 10 | E71: =E21 -> 2 | F71: =D71*E71 -> 20 | G71: =G21 -> 500 | H71: =H21 -> 500 | I71: =I21 -> 0.52 | J71: =J21 -> 0.54 | K71: =IF(ISNUMBER(F71),F71*G71*I71+F71*H71*J71,"") -> 10600 | M71: =IF(ISNUMBER(F71),F71*H71*J71,"") -> 5400
B72: =B22 -> 4 | C72: =C22 -> Meat grinder | D72: =D22 -> 1 | E72: =E22 -> 1 | F72: =F22 -> 1 | G72: =G22 -> 140 | H72: =H22 -> 140 | I72: =I22 -> 0.45 | J72: =J22 -> 0.46 | K72: =IF(ISNUMBER(F72),F72*G72*I72+F72*H72*J72,"") -> 127.4 | M72: =IF(ISNUMBER(F72),F72*H72*J72,"") -> 64.4
B73: =B23 -> 5 | C73: =C23 -> Refrigerators (new) | D73: =D23 -> 0.8 | E73: =E23 -> 3 | F73: =F23 -> 2.4 | G73: =G23 -> 467 | H73: =H23 -> 467 | I73: =I23 -> 0.63 | J73: =J23 -> 0.64 | K73: =IF(ISNUMBER(F73),F73*G73*I73+F73*H73*J73,"") -> 1423.416 | M73: =IF(ISNUMBER(F73),F73*H73*J73,"") -> 717.312
B74: =B24 -> 6 | C74: =C24 -> Refrigerators (old) | D74: 0.8 | E74: =E24 -> 2 | F74: =D74*E74 -> 1.6 | G74: =G24 -> 467 | H74: =H24 -> 467 | I74: =I24 -> 0.63 | J74: =J24 -> 0.64 | K74: =IF(ISNUMBER(F74),F74*G74*I74+F74*H74*J74,"") -> 948.944 | M74: =IF(ISNUMBER(F74),F74*H74*J74,"") -> 478.208
B75: =B25 -> 7 | C75: =C25 -> 0 | D75: =D25 -> 0 | E75: =E25 -> 0 | F75: =F25 -> 0 | G75: =G25 -> 0 | H75: =H25 -> 0 | I75: =I25 -> 0 | J75: =J25 -> 0 | K75: =IF(ISNUMBER(F75),F75*G75*I75+F75*H75*J75,"") -> 0 | M75: =IF(ISNUMBER(F75),F75*H75*J75,"") -> 0
B76: =B26 -> 8 | C76: =C26 -> 0 | D76: =D26 -> 0 | E76: =E26 -> 0 | F76: =F26 -> 0 | G76: =G26 -> 0 | H76: =H26 -> 0 | I76: =I26 -> 0 | J76: =J26 -> 0 | K76: =IF(ISNUMBER(F76),F76*G76*I76+F76*H76*J76,"") -> 0 | M76: =IF(ISNUMBER(F76),F76*H76*J76,"") -> 0
B77: =B27 -> 9 | C77: =C27 -> 0 | D77: =D27 -> 0 | E77: =E27 -> 0 | F77: =F27 -> 0 | G77: =G27 -> 0 | H77: =H27 -> 0 | I77: =I27 -> 0 | J77: =J27 -> 0 | K77: =IF(ISNUMBER(F77),F77*G77*I77+F77*H77*J77,"") -> 0 | M77: =IF(ISNUMBER(F77),F77*H77*J77,"") -> 0
B78: =B28 -> 10 | C78: =C28 -> 0 | D78: =D28 -> 0 | E78: =E28 -> 0 | F78: =F28 -> 0 | G78: =G28 -> 0 | H78: =H28 -> 0 | I78: =I28 -> 0 | J78: =J28 -> 0 | K78: =IF(ISNUMBER(F78),F78*G78*I78+F78*H78*J78,"") -> 0 | M78: =IF(ISNUMBER(F78),F78*H78*J78,"") -> 0
B79: =B29 -> 11 | C79: =C29 -> 0 | D79: =D29 -> 0 | E79: =E29 -> 0 | F79: =F29 -> 0 | G79: =G29 -> 0 | H79: =H29 -> 0 | I79: =I29 -> 0 | J79: =J29 -> 0 | K79: =IF(ISNUMBER(F79),F79*G79*I79+F79*H79*J79,"") -> 0 | M79: =IF(ISNUMBER(F79),F79*H79*J79,"") -> 0
B80: =B30 -> 12 | C80: =C30 -> 0 | D80: =D30 -> 0 | E80: =E30 -> 0 | F80: =F30 -> 0 | G80: =G30 -> 0 | H80: =H30 -> 0 | I80: =I30 -> 0 | J80: =J30 -> 0 | K80: =IF(ISNUMBER(F80),F80*G80*I80+F80*H80*J80,"") -> 0 | M80: =IF(ISNUMBER(F80),F80*H80*J80,"") -> 0
B81: =B31 -> 13 | C81: =C31 -> 0 | D81: =D31 -> 0 | E81: =E31 -> 0 | F81: =F31 -> 0 | G81: =G31 -> 0 | H81: =H31 -> 0 | I81: =I31 -> 0 | J81: =J31 -> 0 | K81: =IF(ISNUMBER(F81),F81*G81*I81+F81*H81*J81,"") -> 0 | M81: =IF(ISNUMBER(F81),F81*H81*J81,"") -> 0
C82: =C32 -> Laundry technological equipment | M82: =IF(ISNUMBER(F82),F82*H82*J82,"")
B83: =B33 -> 1 | C83: =C33 -> Washing machine | D83: =D33 -> 2 | E83: =E33 -> 1 | F83: =F33 -> 2 | G83: =G33 -> 417 | H83: =H33 -> 417 | I83: =I33 -> 0.45 | J83: =J33 -> 0.46 | K83: =IF(ISNUMBER(F83),F83*G83*I83+F83*H83*J83,"") -> 758.94 | M83: =IF(ISNUMBER(F83),F83*H83*J83,"") -> 383.64
C84: =C34 -> Ventilation and air conditioning units | M84: =IF(ISNUMBER(F84),F84*H84*J84,"")
B85: =B35 -> 1
B86: 2 | C86: AHU's with heat recovery | D86: 0.04 | E86: ='Ventilation losses'!G76 -> 41.8 | F86: =D86*E86 -> 1.672 | G86: 1660 | H86: 900 | I86: 0.8 | J86: 0.8 | K86: =IF(ISNUMBER(F86),F86*G86*I86+F86*H86*J86,"") -> 3424.256
B87: 3
C88: =C37 -> Other electrical devices (computers, coffee machines etc) | M88: =IF(ISNUMBER(F88),F88*H88*J88,"")
B89: =B38 -> 1 | C89: =C38 -> Computers | D89: =D38 -> 0.2 | E89: =E38 -> 2 | F89: =F38 -> 0.4 | G89: =G38 -> 1440 | H89: =H38 -> 1557 | I89: =I38 -> 0.9 | J89: =J38 -> 0.9 | K89: =IF(ISNUMBER(F89),F89*G89*I89+F89*H89*J89,"") -> 1078.92 | M89: =IF(ISNUMBER(F89),F89*H89*J89,"") -> 560.52
B90: =B39 -> 2 | C90: =C39 -> Printers | D90: =D39 -> 1 | E90: =E39 -> 2 | F90: =F39 -> 2 | G90: =G39 -> 143 | H90: =H39 -> 143 | I90: =I39 -> 0.08 | J90: =J39 -> 0.09 | K90: =IF(ISNUMBER(F90),F90*G90*I90+F90*H90*J90,"") -> 48.62 | M90: =IF(ISNUMBER(F90),F90*H90*J90,"") -> 25.74
B91: =B40 -> 3 | C91: =C40 -> Proektor | D91: =D40 -> 0.2 | E91: =E40 -> 1 | F91: =F40 -> 0.2 | G91: =G40 -> 217 | H91: =H40 -> 217 | I91: =I40 -> 0.11 | J91: =J40 -> 0.12 | K91: =IF(ISNUMBER(F91),F91*G91*I91+F91*H91*J91,"") -> 9.982 | M91: =IF(ISNUMBER(F91),F91*H91*J91,"") -> 5.208
B92: =B41 -> 4 | C92: =C42 -> 0 | D92: =D42 -> 0 | E92: =E42 -> 0 | F92: =F42 -> 0 | G92: =G42 -> 0 | H92: =H42 -> 0 | I92: =I42 -> 0 | J92: =J42 -> 0 | K92: =IF(ISNUMBER(F92),F92*G92*I92+F92*H92*J92,"") -> 0 | M92: =IF(ISNUMBER(F92),F92*H92*J92,"") -> 0
B93: =B42 -> 5 | C93: =C43 -> 0 | D93: =D43 -> 0 | E93: =E43 -> 0 | F93: =F43 -> 0 | G93: =G43 -> 0 | H93: =H43 -> 0 | I93: =I43 -> 0 | J93: =J43 -> 0 | K93: =IF(ISNUMBER(F93),F93*G93*I93+F93*H93*J93,"") -> 0 | M93: =IF(ISNUMBER(F93),F93*H93*J93,"") -> 0
B94: =B43 -> 6 | C94: =C44 -> 0 | D94: =D44 -> 0 | E94: =E44 -> 0 | F94: =F44 -> 0 | G94: =G44 -> 0 | H94: =H44 -> 0 | I94: =I44 -> 0 | J94: =J44 -> 0 | K94: =IF(ISNUMBER(F94),F94*G94*I94+F94*H94*J94,"") -> 0 | M94: =IF(ISNUMBER(F94),F94*H94*J94,"") -> 0
B95: =B44 -> 7 | C95: =C45 -> 0 | D95: =D45 -> 0 | E95: =E45 -> 0 | F95: =F45 -> 0 | G95: =G45 -> 0 | H95: =H45 -> 0 | I95: =I45 -> 0 | J95: =J45 -> 0 | K95: =IF(ISNUMBER(F95),F95*G95*I95+F95*H95*J95,"") -> 0 | M95: =IF(ISNUMBER(F95),F95*H95*J95,"") -> 0
C96: =C46 -> Elevators | M96: =IF(ISNUMBER(F96),F96*H96*J96,"")
B97: =B47 -> 1 | F97: =D97*E97 -> 0 | G97: =G47 -> 0 | H97: =H47 -> 0 | I97: =I47 -> 0 | J97: =J47 -> 0 | K97: =IF(ISNUMBER(F97),F97*G97*I97+F97*H97*J97,"") -> 0 | M97: =IF(ISNUMBER(F97),F97*H97*J97,"") -> 0
B98: =B48 -> 2 | F98: =D98*E98 -> 0 | G98: =G48 -> 0 | H98: =H48 -> 0 | I98: =I48 -> 0 | J98: =J48 -> 0 | K98: =IF(ISNUMBER(F98),F98*G98*I98+F98*H98*J98,"") -> 0 | M98: =IF(ISNUMBER(F98),F98*H98*J98,"") -> 0
K99: =IF(ISNUMBER(F99),F99*G99*I99+F99*H99*J99,"")
B100: Total annual energy used by equipment after renovation | K100: =SUM(K89:K98)+SUM(K56:K83) -> 15698.183 | M100: =SUM(M56:M99) -> 7927.1692
J102: savings | K102: =K49-K100 -> 5953.3958
...

Sheet Cooling
C3: Space name | D3: Element | F3: Orientation | G3: Glazed Area [m²] | H3: Reduction factor g value | I3: Shading reduction factor | J3: Solar radiation | O3: Q [kWh/y]
J4: [kWh/m²]
J5: V* | K5: VI | L5: VII | M5: VIII | N5: IX*
D6: Window | F6: S | G6: =(SUMIF(Envelope!$C$7:$C$73,Cooling!F6,Envelope!$Q$7:$Q$73))+(SUMIF(Envelope!$C$7:$C$73,Cooling!F6,Envelope!$R$7:$R$73))+(SUMIF(Envelope!$C$7:$C$73,Cooling!F6,Envelope!$S$7:$S$73)) -> 79.02 | H6: 0.75 | I6: 0.8 | J6: =IFERROR(VLOOKUP(F6,$W$27:$AB$35,2,FALSE),"") -> 31.5 | K6: =IFERROR(VLOOKUP(F6,$W$27:$AB$35,3,FALSE),"") -> 65 | L6: =IFERROR(VLOOKUP(F6,$W$27:$AB$35,4,FALSE),"") -> 68 | M6: =IFERROR(VLOOKUP(F6,$W$27:$AB$35,5,FALSE),"") -> 61 | N6: =IFERROR(VLOOKUP(F6,$W$27:$AB$35,6,FALSE),"") -> 31 | O6: =(N6+M6+L6+K6+J6)*G6*H6*I6 -> 12161.178
D7: Window | F7: E | G7: =(SUMIF(Envelope!$C$7:$C$73,Cooling!F7,Envelope!$Q$7:$Q$73))+(SUMIF(Envelope!$C$7:$C$73,Cooling!F7,Envelope!$R$7:$R$73))+(SUMIF(Envelope!$C$7:$C$73,Cooling!F7,Envelope!$S$7:$S$73)) -> 10.8 | H7: 0.75 | I7: 0.8 | J7: =IFERROR(VLOOKUP(F7,$W$27:$AB$35,2,FALSE),"") -> 59 | K7: =IFERROR(VLOOKUP(F7,$W$27:$AB$35,3,FALSE),"") -> 125 | L7: =IFERROR(VLOOKUP(F7,$W$27:$AB$35,4,FALSE),"") -> 135 | M7: =IFERROR(VLOOKUP(F7,$W$27:$AB$35,5,FALSE),"") -> 106 | N7: =IFERROR(VLOOKUP(F7,$W$27:$AB$35,6,FALSE),"") -> 39.5 | O7: =(N7+M7+L7+K7+J7)*G7*H7*I7 -> 3009.96
D8: Window | F8: SE | G8: =(SUMIF(Envelope!$C$7:$C$73,Cooling!F8,Envelope!$Q$7:$Q$73))+(SUMIF(Envelope!$C$7:$C$73,Cooling!F8,Envelope!$R$7:$R$73))+(SUMIF(Envelope!$C$7:$C$73,Cooling!F8,Envelope!$S$7:$S$73)) -> 0 | H8: 0.75 | I8: 0.8 | J8: =IFERROR(VLOOKUP(F8,$W$27:$AB$35,2,FALSE),"") -> 52.5 | K8: =IFERROR(VLOOKUP(F8,$W$27:$AB$35,3,FALSE),"") -> 111 | L8: =IFERROR(VLOOKUP(F8,$W$27:$AB$35,4,FALSE),"") -> 120 | M8: =IFERROR(VLOOKUP(F8,$W$27:$AB$35,5,FALSE),"") -> 99 | N8: =IFERROR(VLOOKUP(F8,$W$27:$AB$35,6,FALSE),"") -> 41 | O8: =(N8+M8+L8+K8+J8)*G8*H8*I8 -> 0
D9: Window | F9: SW | G9: =(SUMIF(Envelope!$C$7:$C$73,Cooling!F9,Envelope!$Q$7:$Q$73))+(SUMIF(Envelope!$C$7:$C$73,Cooling!F9,Envelope!$R$7:$R$73))+(SUMIF(Envelope!$C$7:$C$73,Cooling!F9,Envelope!$S$7:$S$73)) -> 0 | H9: 0.75 | I9: 0.8 | J9: =IFERROR(VLOOKUP(F9,$W$27:$AB$35,2,FALSE),"") -> 52.5 | K9: =IFERROR(VLOOKUP(F9,$W$27:$AB$35,3,FALSE),"") -> 111 | L9: =IFERROR(VLOOKUP(F9,$W$27:$AB$35,4,FALSE),"") -> 120 | M9: =IFERROR(VLOOKUP(F9,$W$27:$AB$35,5,FALSE),"") -> 99 | N9: =IFERROR(VLOOKUP(F9,$W$27:$AB$35,6,FALSE),"") -> 41 | O9: =(N9+M9+L9+K9+J9)*G9*H9*I9 -> 0
D10: Window | F10: NE | G10: =(SUMIF(Envelope!$C$7:$C$73,Cooling!F10,Envelope!$Q$7:$Q$73))+(SUMIF(Envelope!$C$7:$C$73,Cooling!F10,Envelope!$R$7:$R$73))+(SUMIF(Envelope!$C$7:$C$73,Cooling!F10,Envelope!$S$7:$S$73)) -> 0 | H10: 0.75 | I10: 0.8 | J10: =IFERROR(VLOOKUP(F10,$W$27:$AB$35,2,FALSE),"") -> 45 | K10: =IFERROR(VLOOKUP(F10,$W$27:$AB$35,3,FALSE),"") -> 93 | L10: =IFERROR(VLOOKUP(F10,$W$27:$AB$35,4,FALSE),"") -> 98 | M10: =IFERROR(VLOOKUP(F10,$W$27:$AB$35,5,FALSE),"") -> 76 | N10: =IFERROR(VLOOKUP(F10,$W$27:$AB$35,6,FALSE),"") -> 24.5 | O10: =(N10+M10+L10+K10+J10)*G10*H10*I10 -> 0
D11: Window | F11: NW | G11: =(SUMIF(Envelope!$C$7:$C$73,Cooling!F11,Envelope!$Q$7:$Q$73))+(SUMIF(Envelope!$C$7:$C$73,Cooling!F11,Envelope!$R$7:$R$73))+(SUMIF(Envelope!$C$7:$C$73,Cooling!F11,Envelope!$S$7:$S$73)) -> 0 | H11: 0.75 | I11: 0.8 | J11: =IFERROR(VLOOKUP(F11,$W$27:$AB$35,2,FALSE),"") -> 45 | K11: =IFERROR(VLOOKUP(F11,$W$27:$AB$35,3,FALSE),"") -> 93 | L11: =IFERROR(VLOOKUP(F11,$W$27:$AB$35,4,FALSE),"") -> 98 | M11: =IFERROR(VLOOKUP(F11,$W$27:$AB$35,5,FALSE),"") -> 76 | N11: =IFERROR(VLOOKUP(F11,$W$27:$AB$35,6,FALSE),"") -> 24.5 | O11: =(N11+M11+L11+K11+J11)*G11*H11*I11 -> 0
D12: Window
D13: Window
C14: Total annual solar heat gains before renovation | O14: =SUM(O6:O13) -> 15171.138
C15: =C6 -> 0 | D15: =D6 -> Window | F15: =F6 -> S | G15: =G6 -> 79.02 | H15: 0.5 | I15: =I6 -> 0.8 | J15: =IFERROR(VLOOKUP(F15,$W$27:$AB$35,2,FALSE),"") -> 31.5 | K15: =IFERROR(VLOOKUP(F15,$W$27:$AB$35,3,FALSE),"") -> 65 | L15: =IFERROR(VLOOKUP(F15,$W$27:$AB$35,4,FALSE),"") -> 68 | M15: =IFERROR(VLOOKUP(F15,$W$27:$AB$35,5,FALSE),"") -> 61 | N15: =IFERROR(VLOOKUP(F15,$W$27:$AB$35,6,FALSE),"") -> 31 | O15: =(N15+M15+L15+K15+J15)*G15*H15*I15 -> 8107.452
C16: =C7 -> 0 | D16: =D7 -> Window | F16: =F7 -> E | G16: =G7 -> 10.8 | H16: 0.5 | I16: =I7 -> 0.8 | J16: =J7 -> 59 | K16: =K7 -> 125 | L16: =L7 -> 135 | M16: =M7 -> 106 | N16: =N7 -> 39.5 | O16: =O7 -> 3009.96
C17: =C8 -> 0 | D17: =D8 -> Window | F17: =F8 -> SE | G17: =G8 -> 0 | H17: 0.5 | I17: =I8 -> 0.8 | J17: =J8 -> 52.5 | K17: =K8 -> 111 | L17: =L8 -> 120 | M17: =M8 -> 99 | N17: =N8 -> 41 | O17: =O8 -> 0
C18: =C9 -> 0 | D18: =D9 -> Window | F18: =F9 -> SW | G18: =G9 -> 0 | H18: 0.5 | I18: =I9 -> 0.8 | J18: =IFERROR(VLOOKUP(F18,$W$27:$AB$35,2,FALSE),"") -> 52.5 | K18: =IFERROR(VLOOKUP(F18,$W$27:$AB$35,3,FALSE),"") -> 111 | L18: =IFERROR(VLOOKUP(F18,$W$27:$AB$35,4,FALSE),"") -> 120 | M18: =IFERROR(VLOOKUP(F18,$W$27:$AB$35,5,FALSE),"") -> 99 | N18: =IFERROR(VLOOKUP(F18,$W$27:$AB$35,6,FALSE),"") -> 41 | O18: =(N18+M18+L18+K18+J18)*G18*H18*I18 -> 0
C19: =C10 -> 0 | D19: =D10 -> Window | F19: =F10 -> NE | G19: =G10 -> 0 | H19: 0.5 | I19: =I10 -> 0.8 | J19: =IFERROR(VLOOKUP(F19,$W$27:$AB$35,2,FALSE),"") -> 45 | K19: =IFERROR(VLOOKUP(F19,$W$27:$AB$35,3,FALSE),"") -> 93 | L19: =IFERROR(VLOOKUP(F19,$W$27:$AB$35,4,FALSE),"") -> 98 | M19: =IFERROR(VLOOKUP(F19,$W$27:$AB$35,5,FALSE),"") -> 76 | N19: =IFERROR(VLOOKUP(F19,$W$27:$AB$35,6,FALSE),"") -> 24.5 | O19: =(N19+M19+L19+K19+J19)*G19*H19*I19 -> 0
C20: =C11 -> 0 | D20: =D11 -> Window | F20: =F11 -> NW | G20: =G11 -> 0 | H20: 0.5 | I20: =I11 -> 0.8 | J20: =IFERROR(VLOOKUP(F20,$W$27:$AB$35,2,FALSE),"") -> 45 | K20: =IFERROR(VLOOKUP(F20,$W$27:$AB$35,3,FALSE),"") -> 93 | L20: =IFERROR(VLOOKUP(F20,$W$27:$AB$35,4,FALSE),"") -> 98 | M20: =IFERROR(VLOOKUP(F20,$W$27:$AB$35,5,FALSE),"") -> 76 | N20: =IFERROR(VLOOKUP(F20,$W$27:$AB$35,6,FALSE),"") -> 24.5 | O20: =(N20+M20+L20+K20+J20)*G20*H20*I20 -> 0
C21: =C12 -> 0 | D21: =D12 -> Window | J21: =IFERROR(VLOOKUP(F21,$W$27:$AB$35,2,FALSE),"") | K21: =IFERROR(VLOOKUP(F21,$W$27:$AB$35,3,FALSE),"") | L21: =IFERROR(VLOOKUP(F21,$W$27:$AB$35,4,FALSE),"") | M21: =IFERROR(VLOOKUP(F21,$W$27:$AB$35,5,FALSE),"") | N21: =IFERROR(VLOOKUP(F21,$W$27:$AB$35,6,FALSE),"") | O21: =(N21+M21+L21+K21+J21)*G21*H21*I21 -> #VALUE!
C22: =C13 -> 0 | D22: =D13 -> Window | J22: =IFERROR(VLOOKUP(F22,$W$27:$AB$35,2,FALSE),"") | K22: =IFERROR(VLOOKUP(F22,$W$27:$AB$35,3,FALSE),"") | L22: =IFERROR(VLOOKUP(F22,$W$27:$AB$35,4,FALSE),"") | M22: =IFERROR(VLOOKUP(F22,$W$27:$AB$35,5,FALSE),"") | N22: =IFERROR(VLOOKUP(F22,$W$27:$AB$35,6,FALSE),"") | O22: =(N22+M22+L22+K22+J22)*G22*H22*I22 -> #VALUE!
C23: Total annual solar heat gains after renovation | O23: =SUM(O15:O22) -> #VALUE!
B24: Total solar heat gains savings from replacement of openings | O24: =O14-O23 -> #VALUE!
X25: V* | Y25: VI. | Z25: VII. | AA25: VIII. | AB25: IX*
W27: S | X27: =63/2 -> 31.5 | Y27: 65 | Z27: 68 | AA27: 61 | AB27: =62/2 -> 31
W28: N | X28: =53/2 -> 26.5 | Y28: 54 | Z28: 53 | AA28: 44 | AB28: =34/2 -> 17
W29: E | X29: =118/2 -> 59 | Y29: 125 | Z29: 135 | AA29: 106 | AB29: =79/2 -> 39.5
W30: W | X30: =118/2 -> 59 | Y30: 125 | Z30: 135 | AA30: 106 | AB30: =79/2 -> 39.5
W31: SE | X31: =105/2 -> 52.5 | Y31: 111 | Z31: 120 | AA31: 99 | AB31: =82/2 -> 41
W32: SW | X32: =105/2 -> 52.5 | Y32: 111 | Z32: 120 | AA32: 99 | AB32: =82/2 -> 41
W33: NE | X33: =90/2 -> 45 | Y33: 93 | Z33: 98 | AA33: 76 | AB33: =49/2 -> 24.5
B34: Equipment heat gains before renovation | J34: Equipment heat gains after renovation | S34: glazing type | T34: Factor transmission of total solar energy when falling on the perpendicular surface, | W34: NW | X34: =90/2 -> 45 | Y34: 93 | Z34: 98 | AA34: 76 | AB34: =49/2 -> 24.5
B35: No. | C35: Block/floor name | D35: Annual heat gains from equipment [kWh/y] | E35: Solar heat gains [kWh/y] | F35: Total needs for cooling [kWh/y] | G35: Seasonal Coefficient of Performance (SEER) | H35: Electrical energy used for cooling purposes [kWh/y] | J35: No. | K35: Block/floor name | L35: Annual heat gains from equipment [kWh/y] | M35: Solar heat gains [kWh/y] | N35: Total needs for cooling [kWh/y] | O35: Seasonal Coefficient of Performance (SEER) | P35: Electrical energy used for cooling purposes [kWh/y] | T35: gn | W35: Horizontal | X35: =239.4/2 -> 119.7 | Y35: 244.7 | Z35: 243.6 | AA35: 204.4 | AB35: =163.6/2 -> 81.8
B36: 1 | J36: 1 | S36: Average glazing | T36: 0,85 | W36: * Only 15 days out of 30 are applied in calculations
B37: 2 | C37: ='Heat distr. efficiency'!C9 -> 3-DMTT | D37: =Equipment!M49 -> 11012.697 | E37: =O14 -> 15171.138 | F37: =D37+E37 -> 26183.835 | G37: 3.2 | H37: =F37/G37 -> 8182.4484 | J37: 2 | K37: =C37 -> 3-DMTT | L37: =Equipment!M100 -> 7927.1692 | M37: =O23 -> #VALUE! | N37: =L37+M37 -> #VALUE! | O37: 8.5 | P37: =N37/O37 -> #VALUE! | S37: double glazing | T37: 0,75
B38: 3 | J38: 3 | K38: =C38 -> 0 | S38: Double glazing coated with selective low-e | T38: 0,67
B39: 4 | F39: =D39+E39 -> 0 | G39: 3.2 | H39: =F39/G39 -> 0 | J39: 4 | M39: 0 | N39: =L39+M39 -> 0 | O39: 8.5 | P39: =N39/O39 -> 0 | S39: triple glazing | T39: 0,70
B40: 5 | F40: =D40+E40 -> 0 | G40: 3.2 | H40: =F40/G40 -> 0 | J40: 5 | M40: 0 | N40: =L40+M40 -> 0 | O40: 8.5 | P40: =N40/O40 -> 0 | S40: Triple glazing with double selective low-e coating | T40: 0,50
B41: Total | F41: =SUM(F36:F40) -> 26183.835 | H41: =SUM(H36:H40) -> 8182.4484 | J41: Total | N41: =SUM(N36:N40) -> #VALUE! | P41: =SUM(P36:P40) -> #VALUE! | S41: double window | T41: 0,75
N43: savings | O43: =H41-P41 -> #VALUE!
S44: CAPEX
B45: Actually installed air conditioners | S45: Installation of centralized air cooling system
S46: Description | T46: Units
B47: No. | C47: Installed air conditioner systems | D47: Power [kW] | E47: No of units | F47: Installed power [kW] | G47: Hours of operation during cooling season [hours] | I47: Q cooling [kWh/y] | S47: Compressor-Condensing Unit capacity [kW] | T47: 0 | U47: =(O37*(Building_data!E17-Building_data!E15))/('Heat gains Mec Vent'!L5*'Heat gains Mec Vent'!K5) -> #DIV/0!
S48: Compressor-Condensing Units equipped with heat pump function with Seasonal Energy Efficiency Ratio (SEER) of at least 8.5 [USD/kW] | T48: 340
S49: Investment cost for fully functional freon based system which includes compressor-condensate units with heat pump function and distribution system connected to AHU units | T49: =T48*T47 -> 0
B50: 3 | C50: Split systems | D50: 1.5 | E50: 14 | F50: =D50*E50 -> 21 | G50: =Equipment!H36 -> 0 | I50: =Equipment!K36 -> 0 | S50: Labour | T50: =T49*0.2 -> 0
B51: Total electrical energy consumption used for cooling before renovation | I51: =SUM(I48:I50) -> 0 | S51: Total | T51: =SUM(T49:T50) -> 0

Sheet PV
B2: PV system potential | F2: https://re.jrc.ec.europa.eu/pvg_tools/en/
B3: Description | C3: Area [m²]
B4: Availability of roof space for PV installation | C4: =SUM(Envelope!E86:E94)*0.4 -> 558.182
B5: Necessary area for 1kW PV installation under 45° angle | C5: 10
B6: Capacity of PV system planned to be installed | C6: 10 | D6: should not exceed the installed electrical capacity
B7: Availability of roof space after PV system installation | C7: =IF(C4-(C5*C6)>=0,C4-(C5*C6), "PV system does not fit the roof available area, reduce the installed capacity") -> 458.182
B11: Electricity production from the proposed system
B12: Month | C12: Monthly electricity production [kWh]
B13: January | C13: 1023.37
B14: February | C14: 1042.11
B15: March | C15: 1307.37
B16: April | C16: 1414.05
B17: May | C17: 1470.9
B18: June | C18: 1464.09
B19: July | C19: 1583.16
B20: August | C20: 1622.82
B21: September | C21: 1534.55
B22: October | C22: 1266.93
B23: November | C23: 967.54
B24: December | C24: 910.53
B25: Total annual production [kWh/y] | C25: =SUM(C13:C24) -> 15607.42
B27: Installation of PV system
B28: Description | C28: Unit cost [USD/kW] | D28: Foreseen capacity [kW] | E28: Total [USD]
B29: Monocrystaline PV panels including on-grid inverter, materials and labour | C29: 726.8 | D29: 10 | E29: =C29*D29 -> 7268

Sheet Solar DHW
B2: DHW solar system potential
B3: Description | C3: Area [m²]
B4: Availability of roof space for solar DHW installation | C4: 500
B5: Necessary area for one solar DHW panel of 2.5m² under 45° angle | C5: 4
B6: Number of solar DHW collectors planned to be installed | C6: 4 | D6: =IF(I13>('DHW generation'!K18*0.6),"Reduce number of Collectors!!!","") -> Reduce number of Collectors!!!
B7: Availability of roof space after solar DHW system installation | C7: =IF(C4-(C5*C6)>=0,C4-(C5*C6), "Solar DHW does not fit the available roof area, reduce the installed number") -> 484
B10: Thermal energy produced from solar DHW
C11: No of units | D11: Area of one solar collector [m²] | E11: Average generation during warm period [kWh/m²] | F11: Average generation during cold period [kWh/m²] | G11: Hours of generation during warm period [h] | H11: Hours of generation during cold period [h] | I11: DHW generation Q [kWh/y] | N11: S | O11: litres | P11: MD average daily warm kWh/m2y | Q11: MD average daily cold kWh/m2y | R11: kWh/m2 warm | S11: kWh/m2 cold
B12: Tube type solar collector of 2.5m² | C12: 0 | D12: 2.5 | E12: 0.78 | F12: 0.64 | G12: 1095 | H12: 730 | I12: =(C12*D12*E12*G12)+(C12*D12*F12*H12) -> 0 | M12: Vitosol 200-t | N12: 2.5 | O12: 25 | P12: 1.95 | Q12: 1.6 | R12: =P12/N12 -> 0.78 | S12: =Q12/N12 -> 0.64
B13: Proposed solar DHW capacity | C13: =C6 -> 4 | D13: 2.5 | E13: 0.78 | F13: 0.64 | G13: 1095 | H13: 730 | I13: =((C13*D13*E13*G13)+(C13*D13*F13*H13))*0.6 -> 7927.8
B16: Installation of solar DHW system
B17: Equipment | C17: No of units | D17: Price per unit [USD] | E17: Total [USD]
B18: Boiler of 1000l, with 2 integrated heat exchangers (1 for solar collectors and 1 for district heating) | C18: =IF(C19/12<1,1,C19/12) -> 1 | D18: 6900 | E18: =C18*D18 -> 6900
B19: Tube type solar collector with area of 2,5m² | C19: =C13 -> 4 | D19: 1800 | E19: =C19*D19 -> 7200
B20: Automatization | C20: 1 | D20: 1800 | E20: =C20*D20 -> 1800
B21: Water treatment | C21: 1 | D21: 3000 | E21: =C21*D21 -> 3000
B22: Pumps | C22: 2 | D22: 1600 | E22: =C22*D22 -> 3200
B23: Expansions tanks, valves, fitings, pipes & insullation | C23: =C19 -> 4 | D23: 715 | E23: =D23*C23 -> 2860
B24: Total investment per DHW equipment | E24: =SUM(E18:E23) -> 24960
B25: Labour | E25: =E24*0.3 -> 7488
B26: Total cost for a complete and functional system | E26: 4000 | G26: Installed at Block 2

Sheet Shading
C3: Space name | D3: Element | E3: Type | F3: Orientation | G3: Glazed Area [m²] | H3: Reduction factor g value | I3: Shading reduction factor | J3: Solar radiation | O3: Q [kWh/y]
J4: [kWh/m²]
J5: V* | K5: VI | L5: VII | M5: VIII | N5: IX*
B6: After renovation | D6: =Cooling!D18 -> Window | E6: =Cooling!E18 -> 0 | F6: =Cooling!F6 -> S | G6: =Cooling!G6 -> 79.02 | H6: =Cooling!H18 -> 0.5 | I6: =Cooling!I18 -> 0.8 | J6: =IFERROR(VLOOKUP(F6,$W$20:$AB$28,2,FALSE),"") -> 31.5 | K6: =IFERROR(VLOOKUP(F6,$W$20:$AB$28,3,FALSE),"") -> 65 | L6: =IFERROR(VLOOKUP(F6,$W$20:$AB$28,4,FALSE),"") -> 68 | M6: =IFERROR(VLOOKUP(F6,$W$20:$AB$28,5,FALSE),"") -> 61 | N6: =IFERROR(VLOOKUP(F6,$W$20:$AB$28,6,FALSE),"") -> 31 | O6: =(N6+M6+L6+K6+J6)*G6*H6*I6 -> 8107.452
D7: =Cooling!D19 -> Window | E7: =Cooling!E19 -> 0 | F7: =Cooling!F7 -> E | G7: =Cooling!G7 -> 10.8 | H7: =Cooling!H19 -> 0.5 | I7: =Cooling!I19 -> 0.8 | J7: =IFERROR(VLOOKUP(F7,$W$20:$AB$28,2,FALSE),"") -> 59 | K7: =IFERROR(VLOOKUP(F7,$W$20:$AB$28,3,FALSE),"") -> 125 | L7: =IFERROR(VLOOKUP(F7,$W$20:$AB$28,4,FALSE),"") -> 135 | M7: =IFERROR(VLOOKUP(F7,$W$20:$AB$28,5,FALSE),"") -> 106 | N7: =IFERROR(VLOOKUP(F7,$W$20:$AB$28,6,FALSE),"") -> 39.5 | O7: =(N7+M7+L7+K7+J7)*G7*H7*I7 -> 2006.64
D8: =Cooling!D20 -> Window | E8: =Cooling!E20 -> 0 | F8: =Cooling!F20 -> NW | G8: =Cooling!G20 -> 0 | H8: =Cooling!H20 -> 0.5 | I8: =Cooling!I20 -> 0.8 | J8: =IFERROR(VLOOKUP(F8,$W$20:$AB$28,2,FALSE),"") -> 45 | K8: =IFERROR(VLOOKUP(F8,$W$20:$AB$28,3,FALSE),"") -> 93 | L8: =IFERROR(VLOOKUP(F8,$W$20:$AB$28,4,FALSE),"") -> 98 | M8: =IFERROR(VLOOKUP(F8,$W$20:$AB$28,5,FALSE),"") -> 76 | N8: =IFERROR(VLOOKUP(F8,$W$20:$AB$28,6,FALSE),"") -> 24.5 | O8: =(N8+M8+L8+K8+J8)*G8*H8*I8 -> 0
D9: =Cooling!D21 -> Window | E9: =Cooling!E21 -> 0 | F9: =Cooling!F21 -> 0 | G9: =Cooling!G21 -> 0 | H9: =Cooling!H21 -> 0 | I9: =Cooling!I21 -> 0 | J9: =IFERROR(VLOOKUP(F9,$W$20:$AB$28,2,FALSE),"") | K9: =IFERROR(VLOOKUP(F9,$W$20:$AB$28,3,FALSE),"") | L9: =IFERROR(VLOOKUP(F9,$W$20:$AB$28,4,FALSE),"") | M9: =IFERROR(VLOOKUP(F9,$W$20:$AB$28,5,FALSE),"") | N9: =IFERROR(VLOOKUP(F9,$W$20:$AB$28,6,FALSE),"") | S9: Input data table with shading factors:
D10: =Cooling!D22 -> Window | E10: =Cooling!E22 -> 0 | F10: =Cooling!F22 -> 0 | G10: =Cooling!G22 -> 0 | H10: =Cooling!H22 -> 0 | I10: =Cooling!I22 -> 0 | J10: =IFERROR(VLOOKUP(F10,$W$20:$AB$28,2,FALSE),"") | K10: =IFERROR(VLOOKUP(F10,$W$20:$AB$28,3,FALSE),"") | L10: =IFERROR(VLOOKUP(F10,$W$20:$AB$28,4,FALSE),"") | M10: =IFERROR(VLOOKUP(F10,$W$20:$AB$28,5,FALSE),"") | N10: =IFERROR(VLOOKUP(F10,$W$20:$AB$28,6,FALSE),"") | S10: Type of shading element | V10: Factor
C11: Total annual solar heat gains after renovation | O11: =SUM(O6:O10) -> 10114.092 | Q11: No of openings | S11: Fixed horizontal shading (S, SW and SE) | V11: 0.7
